Workbook
Name Lista_Canal: Parametros!$L$5:$L$11
Name Lista_CondicionPago: Parametros!$N$5:$N$10
Name Lista_EstadoCobranza: Parametros!$J$5:$J$9
Name Lista_EstadoVenta: Parametros!$D$5:$D$9
Name Lista_IDCliente: CRM!$B$8:$B$1007
Name Lista_ProximaAccion: Parametros!$F$5:$F$11
Name Lista_Responsable: Parametros!$H$5:$H$8

Sheet Inicio
C1: CRM CLIENTES, VENTAS Y COBRANZA PARA PYMES
C2: Gestiona clientes, oportunidades, próximas acciones, ventas cerradas y cobranzas pendientes.
D4: Promesa de la plantilla
D6: Organiza tus clientes, controla oportunidades de venta y revisa automáticamente qué ventas están cerradas, pendientes de cobro o vencidas.
D10: Paso | E10: Hoja | F10: Qué hace | H10: Idea clave
D11: 1 | E11: CRM | F11: Registra clientes, estado de venta, próxima acción, valor del servicio y responsable. | H11: Solo rellena CRM y Cobranza. El Dashboard y Reporte se actualizan automáticamente con fórmulas.
D12: 2 | E12: Cobranza | F12: Registra facturas, montos, pagos, vencimientos y saldo pendiente.
D13: 3 | E13: Parametros | F13: Edita estados, acciones, responsables, canales y condiciones de pago.
D14: 4 | E14: Dashboard | F14: Visualiza oportunidades, ventas cerradas, cobranza pendiente y vencida.
D15: 5 | E15: Reporte | F15: Revisa un resumen limpio para análisis mensual o comercial.

Sheet Dashboard
B1: DASHBOARD CRM, VENTAS Y COBRANZA
B2: Visualiza oportunidades, ventas cerradas, responsables, cobranza pendiente y cuentas vencidas.
B4: Clientes | E4: Valor total ventas | H4: En negociación | K4: Ventas cerradas
B5: =COUNTA(CRM!B8:B1007) -> 10 | E5: =SUMIFS(CRM!J8:J1007,CRM!F8:F1007,"<>Perdida") -> 11250000 | H5: =SUMIFS(CRM!J8:J1007,CRM!F8:F1007,"En negociación") -> 5950000 | K5: =SUMIFS(CRM!J8:J1007,CRM!F8:F1007,"Cerrada") -> 1900000
B8: Cobranza pendiente | E8: Monto vencido | H8: Cuentas vencidas | K8: Tasa cierre
B9: =SUM(Cobranza!L9:L1008) -> 3500000 | E9: =SUMIFS(Cobranza!L9:L1008,Cobranza!N9:N1008,"Vencida") -> 1100000 | H9: =COUNTIF(Cobranza!N9:N1008,"Vencida") -> 1 | K9: =IFERROR(COUNTIF(CRM!F8:F1007,"Cerrada")/COUNTA(CRM!B8:B1007),0) -> 0.2
B12: Estado venta | C12: Clientes | D12: Valor | F12: Estado cobranza | G12: Facturas | H12: Saldo
B13: Prospecto | C13: =COUNTIF(CRM!$F$8:$F$1007,B13) -> 2 | D13: =SUMIF(CRM!$F$8:$F$1007,B13,CRM!$J$8:$J$1007) -> 2800000 | F13: Pendiente | G13: =COUNTIF(Cobranza!$N$9:$N$1008,F13) -> 1 | H13: =SUMIF(Cobranza!$N$9:$N$1008,F13,Cobranza!$L$9:$L$1008) -> 1300000
B14: En negociación | C14: =COUNTIF(CRM!$F$8:$F$1007,B14) -> 4 | D14: =SUMIF(CRM!$F$8:$F$1007,B14,CRM!$J$8:$J$1007) -> 5950000 | F14: Parcial | G14: =COUNTIF(Cobranza!$N$9:$N$1008,F14) -> 1 | H14: =SUMIF(Cobranza!$N$9:$N$1008,F14,Cobranza!$L$9:$L$1008) -> 1100000
B15: Cerrada | C15: =COUNTIF(CRM!$F$8:$F$1007,B15) -> 2 | D15: =SUMIF(CRM!$F$8:$F$1007,B15,CRM!$J$8:$J$1007) -> 1900000 | F15: Pagada | G15: =COUNTIF(Cobranza!$N$9:$N$1008,F15) -> 3 | H15: =SUMIF(Cobranza!$N$9:$N$1008,F15,Cobranza!$L$9:$L$1008) -> 0
B16: Perdida | C16: =COUNTIF(CRM!$F$8:$F$1007,B16) -> 1 | D16: =SUMIF(CRM!$F$8:$F$1007,B16,CRM!$J$8:$J$1007) -> 700000 | F16: Vencida | G16: =COUNTIF(Cobranza!$N$9:$N$1008,F16) -> 1 | H16: =SUMIF(Cobranza!$N$9:$N$1008,F16,Cobranza!$L$9:$L$1008) -> 1100000
B17: Pausada | C17: =COUNTIF(CRM!$F$8:$F$1007,B17) -> 1 | D17: =SUMIF(CRM!$F$8:$F$1007,B17,CRM!$J$8:$J$1007) -> 600000 | F17: Incobrable | G17: =COUNTIF(Cobranza!$N$9:$N$1008,F17) -> 0 | H17: =SUMIF(Cobranza!$N$9:$N$1008,F17,Cobranza!$L$9:$L$1008) -> 0
B19: Responsable | C19: Clientes | D19: Valor | E19: Cerradas
B20: Kevin Ramírez | C20: =COUNTIF(CRM!$K$8:$K$1007,B20) -> 3 | D20: =SUMIF(CRM!$K$8:$K$1007,B20,CRM!$J$8:$J$1007) -> 4100000 | E20: =COUNTIFS(CRM!$K$8:$K$1007,B20,CRM!$F$8:$F$1007,"Cerrada") -> 1
B21: José González | C21: =COUNTIF(CRM!$K$8:$K$1007,B21) -> 3 | D21: =SUMIF(CRM!$K$8:$K$1007,B21,CRM!$J$8:$J$1007) -> 3200000 | E21: =COUNTIFS(CRM!$K$8:$K$1007,B21,CRM!$F$8:$F$1007,"Cerrada") -> 0
B22: Ana López | C22: =COUNTIF(CRM!$K$8:$K$1007,B22) -> 2 | D22: =SUMIF(CRM!$K$8:$K$1007,B22,CRM!$J$8:$J$1007) -> 3100000 | E22: =COUNTIFS(CRM!$K$8:$K$1007,B22,CRM!$F$8:$F$1007,"Cerrada") -> 1
B23: María Fernández | C23: =COUNTIF(CRM!$K$8:$K$1007,B23) -> 2 | D23: =SUMIF(CRM!$K$8:$K$1007,B23,CRM!$J$8:$J$1007) -> 1550000 | E23: =COUNTIFS(CRM!$K$8:$K$1007,B23,CRM!$F$8:$F$1007,"Cerrada") -> 0
B25: SEGUIMIENTO URGENTE
B26: ID | C26: Cliente | D26: Estado | E26: Próxima acción | F26: Responsable | G26: Días sin actualizar | H26: Valor | I26: Nota
B27: =IFERROR(INDEX(CRM!$B$8:$B$1007,MATCH(1,CRM!$P$8:$P$1007,0)),"") -> 2 | C27: =IFERROR(INDEX(CRM!$C$8:$C$1007,MATCH(1,CRM!$P$8:$P$1007,0)),"") -> Andrea Morales | D27: =IFERROR(INDEX(CRM!$F$8:$F$1007,MATCH(1,CRM!$P$8:$P$1007,0)),"") -> En negociación | E27: =IFERROR(INDEX(CRM!$H$8:$H$1007,MATCH(1,CRM!$P$8:$P$1007,0)),"") -> Reunión de cierre | F27: =IFERROR(INDEX(CRM!$K$8:$K$1007,MATCH(1,CRM!$P$8:$P$1007,0)),"") -> José González | G27: =IFERROR(INDEX(CRM!$N$8:$N$1007,MATCH(1,CRM!$P$8:$P$1007,0)),"") -> 30 | H27: =IFERROR(INDEX(CRM!$J$8:$J$1007,MATCH(1,CRM!$P$8:$P$1007,0)),"") -> 1200000 | I27: =IFERROR(INDEX(CRM!$O$8:$O$1007,MATCH(1,CRM!$P$8:$P$1007,0)),"") -> Seguimiento activo
B28: =IFERROR(INDEX(CRM!$B$8:$B$1007,MATCH(2,CRM!$P$8:$P$1007,0)),"") -> 7 | C28: =IFERROR(INDEX(CRM!$C$8:$C$1007,MATCH(2,CRM!$P$8:$P$1007,0)),"") -> Diego Ramírez | D28: =IFERROR(INDEX(CRM!$F$8:$F$1007,MATCH(2,CRM!$P$8:$P$1007,0)),"") -> En negociación | E28: =IFERROR(INDEX(CRM!$H$8:$H$1007,MATCH(2,CRM!$P$8:$P$1007,0)),"") -> Enviar contrato | F28: =IFERROR(INDEX(CRM!$K$8:$K$1007,MATCH(2,CRM!$P$8:$P$1007,0)),"") -> Kevin Ramírez | G28: =IFERROR(INDEX(CRM!$N$8:$N$1007,MATCH(2,CRM!$P$8:$P$1007,0)),"") -> 22 | H28: =IFERROR(INDEX(CRM!$J$8:$J$1007,MATCH(2,CRM!$P$8:$P$1007,0)),"") -> 1800000 | I28: =IFERROR(INDEX(CRM!$O$8:$O$1007,MATCH(2,CRM!$P$8:$P$1007,0)),"") -> Contrato en revisión
B29: =IFERROR(INDEX(CRM!$B$8:$B$1007,MATCH(3,CRM!$P$8:$P$1007,0)),"") | C29: =IFERROR(INDEX(CRM!$C$8:$C$1007,MATCH(3,CRM!$P$8:$P$1007,0)),"") | D29: =IFERROR(INDEX(CRM!$F$8:$F$1007,MATCH(3,CRM!$P$8:$P$1007,0)),"") | E29: =IFERROR(INDEX(CRM!$H$8:$H$1007,MATCH(3,CRM!$P$8:$P$1007,0)),"") | F29: =IFERROR(INDEX(CRM!$K$8:$K$1007,MATCH(3,CRM!$P$8:$P$1007,0)),"") | G29: =IFERROR(INDEX(CRM!$N$8:$N$1007,MATCH(3,CRM!$P$8:$P$1007,0)),"") | H29: =IFERROR(INDEX(CRM!$J$8:$J$1007,MATCH(3,CRM!$P$8:$P$1007,0)),"") | I29: =IFERROR(INDEX(CRM!$O$8:$O$1007,MATCH(3,CRM!$P$8:$P$1007,0)),"")
B30: =IFERROR(INDEX(CRM!$B$8:$B$1007,MATCH(4,CRM!$P$8:$P$1007,0)),"") | C30: =IFERROR(INDEX(CRM!$C$8:$C$1007,MATCH(4,CRM!$P$8:$P$1007,0)),"") | D30: =IFERROR(INDEX(CRM!$F$8:$F$1007,MATCH(4,CRM!$P$8:$P$1007,0)),"") | E30: =IFERROR(INDEX(CRM!$H$8:$H$1007,MATCH(4,CRM!$P$8:$P$1007,0)),"") | F30: =IFERROR(INDEX(CRM!$K$8:$K$1007,MATCH(4,CRM!$P$8:$P$1007,0)),"") | G30: =IFERROR(INDEX(CRM!$N$8:$N$1007,MATCH(4,CRM!$P$8:$P$1007,0)),"") | H30: =IFERROR(INDEX(CRM!$J$8:$J$1007,MATCH(4,CRM!$P$8:$P$1007,0)),"") | I30: =IFERROR(INDEX(CRM!$O$8:$O$1007,MATCH(4,CRM!$P$8:$P$1007,0)),"")
B31: =IFERROR(INDEX(CRM!$B$8:$B$1007,MATCH(5,CRM!$P$8:$P$1007,0)),"") | C31: =IFERROR(INDEX(CRM!$C$8:$C$1007,MATCH(5,CRM!$P$8:$P$1007,0)),"") | D31: =IFERROR(INDEX(CRM!$F$8:$F$1007,MATCH(5,CRM!$P$8:$P$1007,0)),"") | E31: =IFERROR(INDEX(CRM!$H$8:$H$1007,MATCH(5,CRM!$P$8:$P$1007,0)),"") | F31: =IFERROR(INDEX(CRM!$K$8:$K$1007,MATCH(5,CRM!$P$8:$P$1007,0)),"") | G31: =IFERROR(INDEX(CRM!$N$8:$N$1007,MATCH(5,CRM!$P$8:$P$1007,0)),"") | H31: =IFERROR(INDEX(CRM!$J$8:$J$1007,MATCH(5,CRM!$P$8:$P$1007,0)),"") | I31: =IFERROR(INDEX(CRM!$O$8:$O$1007,MATCH(5,CRM!$P$8:$P$1007,0)),"")
B32: =IFERROR(INDEX(CRM!$B$8:$B$1007,MATCH(6,CRM!$P$8:$P$1007,0)),"") | C32: =IFERROR(INDEX(CRM!$C$8:$C$1007,MATCH(6,CRM!$P$8:$P$1007,0)),"") | D32: =IFERROR(INDEX(CRM!$F$8:$F$1007,MATCH(6,CRM!$P$8:$P$1007,0)),"") | E32: =IFERROR(INDEX(CRM!$H$8:$H$1007,MATCH(6,CRM!$P$8:$P$1007,0)),"") | F32: =IFERROR(INDEX(CRM!$K$8:$K$1007,MATCH(6,CRM!$P$8:$P$1007,0)),"") | G32: =IFERROR(INDEX(CRM!$N$8:$N$1007,MATCH(6,CRM!$P$8:$P$1007,0)),"") | H32: =IFERROR(INDEX(CRM!$J$8:$J$1007,MATCH(6,CRM!$P$8:$P$1007,0)),"") | I32: =IFERROR(INDEX(CRM!$O$8:$O$1007,MATCH(6,CRM!$P$8:$P$1007,0)),"")
B33: =IFERROR(INDEX(CRM!$B$8:$B$1007,MATCH(7,CRM!$P$8:$P$1007,0)),"") | C33: =IFERROR(INDEX(CRM!$C$8:$C$1007,MATCH(7,CRM!$P$8:$P$1007,0)),"") | D33: =IFERROR(INDEX(CRM!$F$8:$F$1007,MATCH(7,CRM!$P$8:$P$1007,0)),"") | E33: =IFERROR(INDEX(CRM!$H$8:$H$1007,MATCH(7,CRM!$P$8:$P$1007,0)),"") | F33: =IFERROR(INDEX(CRM!$K$8:$K$1007,MATCH(7,CRM!$P$8:$P$1007,0)),"") | G33: =IFERROR(INDEX(CRM!$N$8:$N$1007,MATCH(7,CRM!$P$8:$P$1007,0)),"") | H33: =IFERROR(INDEX(CRM!$J$8:$J$1007,MATCH(7,CRM!$P$8:$P$1007,0)),"") | I33: =IFERROR(INDEX(CRM!$O$8:$O$1007,MATCH(7,CRM!$P$8:$P$1007,0)),"")
B34: =IFERROR(INDEX(CRM!$B$8:$B$1007,MATCH(8,CRM!$P$8:$P$1007,0)),"") | C34: =IFERROR(INDEX(CRM!$C$8:$C$1007,MATCH(8,CRM!$P$8:$P$1007,0)),"") | D34: =IFERROR(INDEX(CRM!$F$8:$F$1007,MATCH(8,CRM!$P$8:$P$1007,0)),"") | E34: =IFERROR(INDEX(CRM!$H$8:$H$1007,MATCH(8,CRM!$P$8:$P$1007,0)),"") | F34: =IFERROR(INDEX(CRM!$K$8:$K$1007,MATCH(8,CRM!$P$8:$P$1007,0)),"") | G34: =IFERROR(INDEX(CRM!$N$8:$N$1007,MATCH(8,CRM!$P$8:$P$1007,0)),"") | H34: =IFERROR(INDEX(CRM!$J$8:$J$1007,MATCH(8,CRM!$P$8:$P$1007,0)),"") | I34: =IFERROR(INDEX(CRM!$O$8:$O$1007,MATCH(8,CRM!$P$8:$P$1007,0)),"")
B35: =IFERROR(INDEX(CRM!$B$8:$B$1007,MATCH(9,CRM!$P$8:$P$1007,0)),"") | C35: =IFERROR(INDEX(CRM!$C$8:$C$1007,MATCH(9,CRM!$P$8:$P$1007,0)),"") | D35: =IFERROR(INDEX(CRM!$F$8:$F$1007,MATCH(9,CRM!$P$8:$P$1007,0)),"") | E35: =IFERROR(INDEX(CRM!$H$8:$H$1007,MATCH(9,CRM!$P$8:$P$1007,0)),"") | F35: =IFERROR(INDEX(CRM!$K$8:$K$1007,MATCH(9,CRM!$P$8:$P$1007,0)),"") | G35: =IFERROR(INDEX(CRM!$N$8:$N$1007,MATCH(9,CRM!$P$8:$P$1007,0)),"") | H35: =IFERROR(INDEX(CRM!$J$8:$J$1007,MATCH(9,CRM!$P$8:$P$1007,0)),"") | I35: =IFERROR(INDEX(CRM!$O$8:$O$1007,MATCH(9,CRM!$P$8:$P$1007,0)),"")
B36: =IFERROR(INDEX(CRM!$B$8:$B$1007,MATCH(10,CRM!$P$8:$P$1007,0)),"") | C36: =IFERROR(INDEX(CRM!$C$8:$C$1007,MATCH(10,CRM!$P$8:$P$1007,0)),"") | D36: =IFERROR(INDEX(CRM!$F$8:$F$1007,MATCH(10,CRM!$P$8:$P$1007,0)),"") | E36: =IFERROR(INDEX(CRM!$H$8:$H$1007,MATCH(10,CRM!$P$8:$P$1007,0)),"") | F36: =IFERROR(INDEX(CRM!$K$8:$K$1007,MATCH(10,CRM!$P$8:$P$1007,0)),"") | G36: =IFERROR(INDEX(CRM!$N$8:$N$1007,MATCH(10,CRM!$P$8:$P$1007,0)),"") | H36: =IFERROR(INDEX(CRM!$J$8:$J$1007,MATCH(10,CRM!$P$8:$P$1007,0)),"") | I36: =IFERROR(INDEX(CRM!$O$8:$O$1007,MATCH(10,CRM!$P$8:$P$1007,0)),"")
B37: =IFERROR(INDEX(CRM!$B$8:$B$1007,MATCH(11,CRM!$P$8:$P$1007,0)),"") | C37: =IFERROR(INDEX(CRM!$C$8:$C$1007,MATCH(11,CRM!$P$8:$P$1007,0)),"") | D37: =IFERROR(INDEX(CRM!$F$8:$F$1007,MATCH(11,CRM!$P$8:$P$1007,0)),"") | E37: =IFERROR(INDEX(CRM!$H$8:$H$1007,MATCH(11,CRM!$P$8:$P$1007,0)),"") | F37: =IFERROR(INDEX(CRM!$K$8:$K$1007,MATCH(11,CRM!$P$8:$P$1007,0)),"") | G37: =IFERROR(INDEX(CRM!$N$8:$N$1007,MATCH(11,CRM!$P$8:$P$1007,0)),"") | H37: =IFERROR(INDEX(CRM!$J$8:$J$1007,MATCH(11,CRM!$P$8:$P$1007,0)),"") | I37: =IFERROR(INDEX(CRM!$O$8:$O$1007,MATCH(11,CRM!$P$8:$P$1007,0)),"")
B38: =IFERROR(INDEX(CRM!$B$8:$B$1007,MATCH(12,CRM!$P$8:$P$1007,0)),"") | C38: =IFERROR(INDEX(CRM!$C$8:$C$1007,MATCH(12,CRM!$P$8:$P$1007,0)),"") | D38: =IFERROR(INDEX(CRM!$F$8:$F$1007,MATCH(12,CRM!$P$8:$P$1007,0)),"") | E38: =IFERROR(INDEX(CRM!$H$8:$H$1007,MATCH(12,CRM!$P$8:$P$1007,0)),"") | F38: =IFERROR(INDEX(CRM!$K$8:$K$1007,MATCH(12,CRM!$P$8:$P$1007,0)),"") | G38: =IFERROR(INDEX(CRM!$N$8:$N$1007,MATCH(12,CRM!$P$8:$P$1007,0)),"") | H38: =IFERROR(INDEX(CRM!$J$8:$J$1007,MATCH(12,CRM!$P$8:$P$1007,0)),"") | I38: =IFERROR(INDEX(CRM!$O$8:$O$1007,MATCH(12,CRM!$P$8:$P$1007,0)),"")

Sheet Parametros
C1: PARÁMETROS
C2: Listas editables para estados, próximas acciones, responsables, canales y cobranza.
D4: Estado de venta | F4: Próxima acción | H4: Responsable | J4: Estado cobranza | L4: Canal | N4: Condición de pago
D5: Prospecto | F5: Llamar para presentación | H5: Kevin Ramírez | J5: Pendiente | L5: Instagram | N5: Contado
D6: En negociación | F6: Enviar propuesta | H6: José González | J6: Parcial | L6: WhatsApp | N6: 7 días
D7: Cerrada | F7: Llamar para seguimiento | H7: Ana López | J7: Pagada | L7: Referido | N7: 15 días
D8: Perdida | F8: Reunión de cierre | H8: María Fernández | J8: Vencida | L8: Página web | N8: 30 días
D9: Pausada | F9: Enviar contrato | J9: Incobrable | L9: Tienda física | N9: 45 días
F10: Enviar encuesta de satisfacción | L10: Email | N10: 60 días
F11: Reactivar cliente | L11: Otro
F12: Sin acción

Sheet CRM
B1: GESTIÓN DE CLIENTES Y VENTAS
B2: Registra clientes, oportunidades, acciones comerciales y responsables.
B4: Clientes registrados | E4: Valor total ventas | H4: Ventas cerradas | K4: Cobranza pendiente | N4: Cuentas vencidas
B5: =COUNTA(B8:B1007) -> 10 | E5: =SUMIFS(J8:J1007,F8:F1007,"<>Perdida") -> 11250000 | H5: =SUMIFS(J8:J1007,F8:F1007,"Cerrada") -> 1900000 | K5: =SUM(Cobranza!L9:L1008) -> 3500000 | N5: =COUNTIF(Cobranza!N9:N1008,"Vencida") -> 1
B7: ID | C7: Nombre del cliente | D7: Correo electrónico | E7: Teléfono | F7: Estado de venta | G7: Fecha primer contacto | H7: Próxima acción | I7: Última actualización | J7: Valor del servicio | K7: Responsable | L7: Canal | M7: Estado cobranza | N7: Días sin actualizar | O7: Nota | P7: Orden urgente
B8: 1 | C8: Juan Pérez | D8: juanp@ejemplo.com | E8: 321-1234567 | F8: Prospecto | G8: 46144 | H8: Llamar para presentación | I8: 46185 | J8: 1500000 | K8: Kevin Ramírez | L8: WhatsApp | M8: =IF(B8="","",IF(COUNTIFS(Cobranza!$C$9:$C$1008,B8,Cobranza!$N$9:$N$1008,"Vencida")>0,"Vencida",IF(COUNTIFS(Cobranza!$C$9:$C$1008,B8,Cobranza!$N$9:$N$1008,"Parcial")>0,"Parcial",IF(COUNTIFS(Cobranza!$C$9:$C$1008,B8,Cobranza!$N$9:$N$1008,"Pendiente")>0,"Pendiente",IF(COUNTIFS(Cobranza!$C$9:$C$1008,B8,Cobranza!$N$9:$N$1008,"Pagada")>0,"Pagada",""))))) | N8: =IF(I8="","",MAX(0,TODAY()-I8)) -> 7 | O8: Cliente nuevo | P8: =IF(AND(B8<>"",F8<>"Cerrada",F8<>"Perdida",N8<>"",N8>14),COUNTIFS($F$8:$F8,"<>Cerrada",$F$8:$F8,"<>Perdida",$N$8:$N8,">14"),"")
B9: 2 | C9: Andrea Morales | D9: andream@ejemplo.com | E9: 312-7654321 | F9: En negociación | G9: 46122 | H9: Reunión de cierre | I9: 46162 | J9: 1200000 | K9: José González | L9: Instagram | M9: =IF(B9="","",IF(COUNTIFS(Cobranza!$C$9:$C$1008,B9,Cobranza!$N$9:$N$1008,"Vencida")>0,"Vencida",IF(COUNTIFS(Cobranza!$C$9:$C$1008,B9,Cobranza!$N$9:$N$1008,"Parcial")>0,"Parcial",IF(COUNTIFS(Cobranza!$C$9:$C$1008,B9,Cobranza!$N$9:$N$1008,"Pendiente")>0,"Pendiente",IF(COUNTIFS(Cobranza!$C$9:$C$1008,B9,Cobranza!$N$9:$N$1008,"Pagada")>0,"Pagada",""))))) -> Pagada | N9: =IF(I9="","",MAX(0,TODAY()-I9)) -> 30 | O9: Seguimiento activo | P9: =IF(AND(B9<>"",F9<>"Cerrada",F9<>"Perdida",N9<>"",N9>14),COUNTIFS($F$8:$F9,"<>Cerrada",$F$8:$F9,"<>Perdida",$N$8:$N9,">14"),"") -> 1
B10: 3 | C10: Carlos García | D10: carlosg@ejemplo.com | E10: 314-1239874 | F10: Cerrada | G10: 46096 | H10: Enviar encuesta de satisfacción | I10: 46183 | J10: 800000 | K10: Kevin Ramírez | L10: Referido | M10: =IF(B10="","",IF(COUNTIFS(Cobranza!$C$9:$C$1008,B10,Cobranza!$N$9:$N$1008,"Vencida")>0,"Vencida",IF(COUNTIFS(Cobranza!$C$9:$C$1008,B10,Cobranza!$N$9:$N$1008,"Parcial")>0,"Parcial",IF(COUNTIFS(Cobranza!$C$9:$C$1008,B10,Cobranza!$N$9:$N$1008,"Pendiente")>0,"Pendiente",IF(COUNTIFS(Cobranza!$C$9:$C$1008,B10,Cobranza!$N$9:$N$1008,"Pagada")>0,"Pagada",""))))) -> Pagada | N10: =IF(I10="","",MAX(0,TODAY()-I10)) -> 9 | O10: Venta cerrada | P10: =IF(AND(B10<>"",F10<>"Cerrada",F10<>"Perdida",N10<>"",N10>14),COUNTIFS($F$8:$F10,"<>Cerrada",$F$8:$F10,"<>Perdida",$N$8:$N10,">14"),"")
B11: 4 | C11: Lucía Méndez | D11: luciam@ejemplo.com | E11: 315-2223344 | F11: En negociación | G11: 46134 | H11: Enviar propuesta | I11: 46198 | J11: 2000000 | K11: Ana López | L11: Página web | M11: =IF(B11="","",IF(COUNTIFS(Cobranza!$C$9:$C$1008,B11,Cobranza!$N$9:$N$1008,"Vencida")>0,"Vencida",IF(COUNTIFS(Cobranza!$C$9:$C$1008,B11,Cobranza!$N$9:$N$1008,"Parcial")>0,"Parcial",IF(COUNTIFS(Cobranza!$C$9:$C$1008,B11,Cobranza!$N$9:$N$1008,"Pendiente")>0,"Pendiente",IF(COUNTIFS(Cobranza!$C$9:$C$1008,B11,Cobranza!$N$9:$N$1008,"Pagada")>0,"Pagada",""))))) | N11: =IF(I11="","",MAX(0,TODAY()-I11)) -> 0 | O11: Propuesta enviada | P11: =IF(AND(B11<>"",F11<>"Cerrada",F11<>"Perdida",N11<>"",N11>14),COUNTIFS($F$8:$F11,"<>Cerrada",$F$8:$F11,"<>Perdida",$N$8:$N11,">14"),"")
B12: 5 | C12: Pedro Sánchez | D12: pedros@ejemplo.com | E12: 316-5556677 | F12: En negociación | G12: 46040 | H12: Llamar para seguimiento | I12: 46186 | J12: 950000 | K12: María Fernández | L12: Email | M12: =IF(B12="","",IF(COUNTIFS(Cobranza!$C$9:$C$1008,B12,Cobranza!$N$9:$N$1008,"Vencida")>0,"Vencida",IF(COUNTIFS(Cobranza!$C$9:$C$1008,B12,Cobranza!$N$9:$N$1008,"Parcial")>0,"Parcial",IF(COUNTIFS(Cobranza!$C$9:$C$1008,B12,Cobranza!$N$9:$N$1008,"Pendiente")>0,"Pendiente",IF(COUNTIFS(Cobranza!$C$9:$C$1008,B12,Cobranza!$N$9:$N$1008,"Pagada")>0,"Pagada",""))))) | N12: =IF(I12="","",MAX(0,TODAY()-I12)) -> 6 | O12: Interesado | P12: =IF(AND(B12<>"",F12<>"Cerrada",F12<>"Perdida",N12<>"",N12>14),COUNTIFS($F$8:$F12,"<>Cerrada",$F$8:$F12,"<>Perdida",$N$8:$N12,">14"),"")
B13: 6 | C13: Laura Díaz | D13: laurad@ejemplo.com | E13: 317-8889900 | F13: Perdida | G13: 46063 | I13: 46182 | J13: 700000 | K13: José González | L13: Tienda física | M13: =IF(B13="","",IF(COUNTIFS(Cobranza!$C$9:$C$1008,B13,Cobranza!$N$9:$N$1008,"Vencida")>0,"Vencida",IF(COUNTIFS(Cobranza!$C$9:$C$1008,B13,Cobranza!$N$9:$N$1008,"Parcial")>0,"Parcial",IF(COUNTIFS(Cobranza!$C$9:$C$1008,B13,Cobranza!$N$9:$N$1008,"Pendiente")>0,"Pendiente",IF(COUNTIFS(Cobranza!$C$9:$C$1008,B13,Cobranza!$N$9:$N$1008,"Pagada")>0,"Pagada",""))))) | N13: =IF(I13="","",MAX(0,TODAY()-I13)) -> 10 | O13: No avanzó | P13: =IF(AND(B13<>"",F13<>"Cerrada",F13<>"Perdida",N13<>"",N13>14),COUNTIFS($F$8:$F13,"<>Cerrada",$F$8:$F13,"<>Perdida",$N$8:$N13,">14"),"")
B14: 7 | C14: Diego Ramírez | D14: diegor@ejemplo.com | E14: 318-1112233 | F14: En negociación | G14: 46143 | H14: Enviar contrato | I14: 46170 | J14: 1800000 | K14: Kevin Ramírez | L14: Referido | M14: =IF(B14="","",IF(COUNTIFS(Cobranza!$C$9:$C$1008,B14,Cobranza!$N$9:$N$1008,"Vencida")>0,"Vencida",IF(COUNTIFS(Cobranza!$C$9:$C$1008,B14,Cobranza!$N$9:$N$1008,"Parcial")>0,"Parcial",IF(COUNTIFS(Cobranza!$C$9:$C$1008,B14,Cobranza!$N$9:$N$1008,"Pendiente")>0,"Pendiente",IF(COUNTIFS(Cobranza!$C$9:$C$1008,B14,Cobranza!$N$9:$N$1008,"Pagada")>0,"Pagada",""))))) -> Parcial | N14: =IF(I14="","",MAX(0,TODAY()-I14)) -> 22 | O14: Contrato en revisión | P14: =IF(AND(B14<>"",F14<>"Cerrada",F14<>"Perdida",N14<>"",N14>14),COUNTIFS($F$8:$F14,"<>Cerrada",$F$8:$F14,"<>Perdida",$N$8:$N14,">14"),"") -> 2
B15: 8 | C15: Sofía Castro | D15: sofiac@ejemplo.com | E15: 319-4445566 | F15: Cerrada | G15: 46101 | H15: Enviar encuesta de satisfacción | I15: 46184 | J15: 1100000 | K15: Ana López | L15: WhatsApp | M15: =IF(B15="","",IF(COUNTIFS(Cobranza!$C$9:$C$1008,B15,Cobranza!$N$9:$N$1008,"Vencida")>0,"Vencida",IF(COUNTIFS(Cobranza!$C$9:$C$1008,B15,Cobranza!$N$9:$N$1008,"Parcial")>0,"Parcial",IF(COUNTIFS(Cobranza!$C$9:$C$1008,B15,Cobranza!$N$9:$N$1008,"Pendiente")>0,"Pendiente",IF(COUNTIFS(Cobranza!$C$9:$C$1008,B15,Cobranza!$N$9:$N$1008,"Pagada")>0,"Pagada",""))))) -> Vencida | N15: =IF(I15="","",MAX(0,TODAY()-I15)) -> 8 | O15: Cliente recurrente | P15: =IF(AND(B15<>"",F15<>"Cerrada",F15<>"Perdida",N15<>"",N15>14),COUNTIFS($F$8:$F15,"<>Cerrada",$F$8:$F15,"<>Perdida",$N$8:$N15,">14"),"")
B16: 9 | C16: Miguel Ruiz | D16: miguelr@ejemplo.com | E16: 320-7778899 | F16: Pausada | G16: 46117 | H16: Reactivar cliente | I16: 46180 | J16: 600000 | K16: María Fernández | L16: Email | M16: =IF(B16="","",IF(COUNTIFS(Cobranza!$C$9:$C$1008,B16,Cobranza!$N$9:$N$1008,"Vencida")>0,"Vencida",IF(COUNTIFS(Cobranza!$C$9:$C$1008,B16,Cobranza!$N$9:$N$1008,"Parcial")>0,"Parcial",IF(COUNTIFS(Cobranza!$C$9:$C$1008,B16,Cobranza!$N$9:$N$1008,"Pendiente")>0,"Pendiente",IF(COUNTIFS(Cobranza!$C$9:$C$1008,B16,Cobranza!$N$9:$N$1008,"Pagada")>0,"Pagada",""))))) | N16: =IF(I16="","",MAX(0,TODAY()-I16)) -> 12 | O16: En pausa | P16: =IF(AND(B16<>"",F16<>"Cerrada",F16<>"Perdida",N16<>"",N16>14),COUNTIFS($F$8:$F16,"<>Cerrada",$F$8:$F16,"<>Perdida",$N$8:$N16,">14"),"")
B17: 10 | C17: Valentina Gómez | D17: valentinag@ejemplo.com | E17: 321-3334455 | F17: Prospecto | G17: 46174 | H17: Enviar propuesta | I17: 46187 | J17: 1300000 | K17: José González | L17: Instagram | M17: =IF(B17="","",IF(COUNTIFS(Cobranza!$C$9:$C$1008,B17,Cobranza!$N$9:$N$1008,"Vencida")>0,"Vencida",IF(COUNTIFS(Cobranza!$C$9:$C$1008,B17,Cobranza!$N$9:$N$1008,"Parcial")>0,"Parcial",IF(COUNTIFS(Cobranza!$C$9:$C$1008,B17,Cobranza!$N$9:$N$1008,"Pendiente")>0,"Pendiente",IF(COUNTIFS(Cobranza!$C$9:$C$1008,B17,Cobranza!$N$9:$N$1008,"Pagada")>0,"Pagada",""))))) -> Pendiente | N17: =IF(I17="","",MAX(0,TODAY()-I17)) -> 5 | O17: Reunión agendada | P17: =IF(AND(B17<>"",F17<>"Cerrada",F17<>"Perdida",N17<>"",N17>14),COUNTIFS($F$8:$F17,"<>Cerrada",$F$8:$F17,"<>Perdida",$N$8:$N17,">14"),"")
M18: =IF(B18="","",IF(COUNTIFS(Cobranza!$C$9:$C$1008,B18,Cobranza!$N$9:$N$1008,"Vencida")>0,"Vencida",IF(COUNTIFS(Cobranza!$C$9:$C$1008,B18,Cobranza!$N$9:$N$1008,"Parcial")>0,"Parcial",IF(COUNTIFS(Cobranza!$C$9:$C$1008,B18,Cobranza!$N$9:$N$1008,"Pendiente")>0,"Pendiente",IF(COUNTIFS(Cobranza!$C$9:$C$1008,B18,Cobranza!$N$9:$N$1008,"Pagada")>0,"Pagada",""))))) | N18: =IF(I18="","",MAX(0,TODAY()-I18)) | P18: =IF(AND(B18<>"",F18<>"Cerrada",F18<>"Perdida",N18<>"",N18>14),COUNTIFS($F$8:$F18,"<>Cerrada",$F$8:$F18,"<>Perdida",$N$8:$N18,">14"),"")
M19: =IF(B19="","",IF(COUNTIFS(Cobranza!$C$9:$C$1008,B19,Cobranza!$N$9:$N$1008,"Vencida")>0,"Vencida",IF(COUNTIFS(Cobranza!$C$9:$C$1008,B19,Cobranza!$N$9:$N$1008,"Parcial")>0,"Parcial",IF(COUNTIFS(Cobranza!$C$9:$C$1008,B19,Cobranza!$N$9:$N$1008,"Pendiente")>0,"Pendiente",IF(COUNTIFS(Cobranza!$C$9:$C$1008,B19,Cobranza!$N$9:$N$1008,"Pagada")>0,"Pagada",""))))) | N19: =IF(I19="","",MAX(0,TODAY()-I19)) | P19: =IF(AND(B19<>"",F19<>"Cerrada",F19<>"Perdida",N19<>"",N19>14),COUNTIFS($F$8:$F19,"<>Cerrada",$F$8:$F19,"<>Perdida",$N$8:$N19,">14"),"")
M20: =IF(B20="","",IF(COUNTIFS(Cobranza!$C$9:$C$1008,B20,Cobranza!$N$9:$N$1008,"Vencida")>0,"Vencida",IF(COUNTIFS(Cobranza!$C$9:$C$1008,B20,Cobranza!$N$9:$N$1008,"Parcial")>0,"Parcial",IF(COUNTIFS(Cobranza!$C$9:$C$1008,B20,Cobranza!$N$9:$N$1008,"Pendiente")>0,"Pendiente",IF(COUNTIFS(Cobranza!$C$9:$C$1008,B20,Cobranza!$N$9:$N$1008,"Pagada")>0,"Pagada",""))))) | N20: =IF(I20="","",MAX(0,TODAY()-I20)) | P20: =IF(AND(B20<>"",F20<>"Cerrada",F20<>"Perdida",N20<>"",N20>14),COUNTIFS($F$8:$F20,"<>Cerrada",$F$8:$F20,"<>Perdida",$N$8:$N20,">14"),"")
M21: =IF(B21="","",IF(COUNTIFS(Cobranza!$C$9:$C$1008,B21,Cobranza!$N$9:$N$1008,"Vencida")>0,"Vencida",IF(COUNTIFS(Cobranza!$C$9:$C$1008,B21,Cobranza!$N$9:$N$1008,"Parcial")>0,"Parcial",IF(COUNTIFS(Cobranza!$C$9:$C$1008,B21,Cobranza!$N$9:$N$1008,"Pendiente")>0,"Pendiente",IF(COUNTIFS(Cobranza!$C$9:$C$1008,B21,Cobranza!$N$9:$N$1008,"Pagada")>0,"Pagada",""))))) | N21: =IF(I21="","",MAX(0,TODAY()-I21)) | P21: =IF(AND(B21<>"",F21<>"Cerrada",F21<>"Perdida",N21<>"",N21>14),COUNTIFS($F$8:$F21,"<>Cerrada",$F$8:$F21,"<>Perdida",$N$8:$N21,">14"),"")
M22: =IF(B22="","",IF(COUNTIFS(Cobranza!$C$9:$C$1008,B22,Cobranza!$N$9:$N$1008,"Vencida")>0,"Vencida",IF(COUNTIFS(Cobranza!$C$9:$C$1008,B22,Cobranza!$N$9:$N$1008,"Parcial")>0,"Parcial",IF(COUNTIFS(Cobranza!$C$9:$C$1008,B22,Cobranza!$N$9:$N$1008,"Pendiente")>0,"Pendiente",IF(COUNTIFS(Cobranza!$C$9:$C$1008,B22,Cobranza!$N$9:$N$1008,"Pagada")>0,"Pagada",""))))) | N22: =IF(I22="","",MAX(0,TODAY()-I22)) | P22: =IF(AND(B22<>"",F22<>"Cerrada",F22<>"Perdida",N22<>"",N22>14),COUNTIFS($F$8:$F22,"<>Cerrada",$F$8:$F22,"<>Perdida",$N$8:$N22,">14"),"")
M23: =IF(B23="","",IF(COUNTIFS(Cobranza!$C$9:$C$1008,B23,Cobranza!$N$9:$N$1008,"Vencida")>0,"Vencida",IF(COUNTIFS(Cobranza!$C$9:$C$1008,B23,Cobranza!$N$9:$N$1008,"Parcial")>0,"Parcial",IF(COUNTIFS(Cobranza!$C$9:$C$1008,B23,Cobranza!$N$9:$N$1008,"Pendiente")>0,"Pendiente",IF(COUNTIFS(Cobranza!$C$9:$C$1008,B23,Cobranza!$N$9:$N$1008,"Pagada")>0,"Pagada",""))))) | N23: =IF(I23="","",MAX(0,TODAY()-I23)) | P23: =IF(AND(B23<>"",F23<>"Cerrada",F23<>"Perdida",N23<>"",N23>14),COUNTIFS($F$8:$F23,"<>Cerrada",$F$8:$F23,"<>Perdida",$N$8:$N23,">14"),"")
M24: =IF(B24="","",IF(COUNTIFS(Cobranza!$C$9:$C$1008,B24,Cobranza!$N$9:$N$1008,"Vencida")>0,"Vencida",IF(COUNTIFS(Cobranza!$C$9:$C$1008,B24,Cobranza!$N$9:$N$1008,"Parcial")>0,"Parcial",IF(COUNTIFS(Cobranza!$C$9:$C$1008,B24,Cobranza!$N$9:$N$1008,"Pendiente")>0,"Pendiente",IF(COUNTIFS(Cobranza!$C$9:$C$1008,B24,Cobranza!$N$9:$N$1008,"Pagada")>0,"Pagada",""))))) | N24: =IF(I24="","",MAX(0,TODAY()-I24)) | P24: =IF(AND(B24<>"",F24<>"Cerrada",F24<>"Perdida",N24<>"",N24>14),COUNTIFS($F$8:$F24,"<>Cerrada",$F$8:$F24,"<>Perdida",$N$8:$N24,">14"),"")
M25: =IF(B25="","",IF(COUNTIFS(Cobranza!$C$9:$C$1008,B25,Cobranza!$N$9:$N$1008,"Vencida")>0,"Vencida",IF(COUNTIFS(Cobranza!$C$9:$C$1008,B25,Cobranza!$N$9:$N$1008,"Parcial")>0,"Parcial",IF(COUNTIFS(Cobranza!$C$9:$C$1008,B25,Cobranza!$N$9:$N$1008,"Pendiente")>0,"Pendiente",IF(COUNTIFS(Cobranza!$C$9:$C$1008,B25,Cobranza!$N$9:$N$1008,"Pagada")>0,"Pagada",""))))) | N25: =IF(I25="","",MAX(0,TODAY()-I25)) | P25: =IF(AND(B25<>"",F25<>"Cerrada",F25<>"Perdida",N25<>"",N25>14),COUNTIFS($F$8:$F25,"<>Cerrada",$F$8:$F25,"<>Perdida",$N$8:$N25,">14"),"")
M26: =IF(B26="","",IF(COUNTIFS(Cobranza!$C$9:$C$1008,B26,Cobranza!$N$9:$N$1008,"Vencida")>0,"Vencida",IF(COUNTIFS(Cobranza!$C$9:$C$1008,B26,Cobranza!$N$9:$N$1008,"Parcial")>0,"Parcial",IF(COUNTIFS(Cobranza!$C$9:$C$1008,B26,Cobranza!$N$9:$N$1008,"Pendiente")>0,"Pendiente",IF(COUNTIFS(Cobranza!$C$9:$C$1008,B26,Cobranza!$N$9:$N$1008,"Pagada")>0,"Pagada",""))))) | N26: =IF(I26="","",MAX(0,TODAY()-I26)) | P26: =IF(AND(B26<>"",F26<>"Cerrada",F26<>"Perdida",N26<>"",N26>14),COUNTIFS($F$8:$F26,"<>Cerrada",$F$8:$F26,"<>Perdida",$N$8:$N26,">14"),"")
M27: =IF(B27="","",IF(COUNTIFS(Cobranza!$C$9:$C$1008,B27,Cobranza!$N$9:$N$1008,"Vencida")>0,"Vencida",IF(COUNTIFS(Cobranza!$C$9:$C$1008,B27,Cobranza!$N$9:$N$1008,"Parcial")>0,"Parcial",IF(COUNTIFS(Cobranza!$C$9:$C$1008,B27,Cobranza!$N$9:$N$1008,"Pendiente")>0,"Pendiente",IF(COUNTIFS(Cobranza!$C$9:$C$1008,B27,Cobranza!$N$9:$N$1008,"Pagada")>0,"Pagada",""))))) | N27: =IF(I27="","",MAX(0,TODAY()-I27)) | P27: =IF(AND(B27<>"",F27<>"Cerrada",F27<>"Perdida",N27<>"",N27>14),COUNTIFS($F$8:$F27,"<>Cerrada",$F$8:$F27,"<>Perdida",$N$8:$N27,">14"),"")
M28: =IF(B28="","",IF(COUNTIFS(Cobranza!$C$9:$C$1008,B28,Cobranza!$N$9:$N$1008,"Vencida")>0,"Vencida",IF(COUNTIFS(Cobranza!$C$9:$C$1008,B28,Cobranza!$N$9:$N$1008,"Parcial")>0,"Parcial",IF(COUNTIFS(Cobranza!$C$9:$C$1008,B28,Cobranza!$N$9:$N$1008,"Pendiente")>0,"Pendiente",IF(COUNTIFS(Cobranza!$C$9:$C$1008,B28,Cobranza!$N$9:$N$1008,"Pagada")>0,"Pagada",""))))) | N28: =IF(I28="","",MAX(0,TODAY()-I28)) | P28: =IF(AND(B28<>"",F28<>"Cerrada",F28<>"Perdida",N28<>"",N28>14),COUNTIFS($F$8:$F28,"<>Cerrada",$F$8:$F28,"<>Perdida",$N$8:$N28,">14"),"")
M29: =IF(B29="","",IF(COUNTIFS(Cobranza!$C$9:$C$1008,B29,Cobranza!$N$9:$N$1008,"Vencida")>0,"Vencida",IF(COUNTIFS(Cobranza!$C$9:$C$1008,B29,Cobranza!$N$9:$N$1008,"Parcial")>0,"Parcial",IF(COUNTIFS(Cobranza!$C$9:$C$1008,B29,Cobranza!$N$9:$N$1008,"Pendiente")>0,"Pendiente",IF(COUNTIFS(Cobranza!$C$9:$C$1008,B29,Cobranza!$N$9:$N$1008,"Pagada")>0,"Pagada",""))))) | N29: =IF(I29="","",MAX(0,TODAY()-I29)) | P29: =IF(AND(B29<>"",F29<>"Cerrada",F29<>"Perdida",N29<>"",N29>14),COUNTIFS($F$8:$F29,"<>Cerrada",$F$8:$F29,"<>Perdida",$N$8:$N29,">14"),"")
... M1007: =IF(B1007="","",IF(COUNTIFS(Cobranza!$C$9:$C$1008,B1007,Cobranza!$N$9:$N$1008,"Vencida")>0,"Vencida",IF(COUNTIFS(Cobranza!$C$9:$C$1008,B1007,Cobranza!$N$9:$N$1008,"Parcial")>0,"Parcial",IF(COUNTIFS(Cobranza!$C$9:$C$1008,B1007,Cobranza!$N$9:$N$1008,"Pendiente")>0,"Pendiente",IF(COUNTIFS(Cobranza!$C$9:$C$1008,B1007,Cobranza!$N$9:$N$1008,"Pagada")>0,"Pagada",""))))) | N1007: =IF(I1007="","",MAX(0,TODAY()-I1007)) | P1007: =IF(AND(B1007<>"",F1007<>"Cerrada",F1007<>"Perdida",N1007<>"",N1007>14),COUNTIFS($F$8:$F1007,"<>Cerrada",$F$8:$F1007,"<>Perdida",$N$8:$N1007,">14"),"")

Sheet Cobranza
A1: COBRANZA Y CUENTAS POR COBRAR
A2: Registra facturas, vencimientos, pagos, saldo pendiente y estado automático de cobranza.
A4: Facturado total | D4: Cobrado total | G4: Saldo pendiente | J4: Monto vencido
A5: =SUM(G9:G1008) -> 6700000 | D5: =SUM(I9:I1008)+SUM(K9:K1008) -> 3200000 | G5: =SUM(L9:L1008) -> 3500000 | J5: =SUMIFS(L9:L1008,N9:N1008,"Vencida") -> 1100000
A8: N° factura | B8: Fecha emisión | C8: ID cliente | D8: Cliente | E8: Condición pago | F8: Fecha vencimiento | G8: Monto factura | H8: Fecha pago 1 | I8: Monto pago 1 | J8: Fecha pago 2 | K8: Monto pago 2 | L8: Saldo pendiente | M8: Días vencido | N8: Estado cobranza | O8: Responsable | P8: Nota
A9: F-001 | B9: 46113 | C9: 3 | D9: =IF(C9="","",IFERROR(VLOOKUP(C9,CRM!$B$8:$O$1007,2,FALSE()),"Revisar ID")) -> Carlos García | E9: 30 días | F9: =IF(B9="","",B9+IF(E9="Contado",0,IF(E9="7 días",7,IF(E9="15 días",15,IF(E9="30 días",30,IF(E9="45 días",45,IF(E9="60 días",60,0))))))) -> 46143 | G9: 800000 | H9: 46140 | I9: 800000 | L9: =IF(G9="","",MAX(0,G9-SUM(I9,K9))) -> 0 | M9: =IF(G9="","",IF(L9=0,0,MAX(0,TODAY()-F9))) -> 0 | N9: =IF(G9="","",IF(L9=0,"Pagada",IF(M9>0,"Vencida",IF(SUM(I9,K9)>0,"Parcial","Pendiente")))) -> Pagada | O9: Kevin Ramírez | P9: Pagada
A10: F-002 | B10: 46152 | C10: 8 | D10: =IF(C10="","",IFERROR(VLOOKUP(C10,CRM!$B$8:$O$1007,2,FALSE()),"Revisar ID")) -> Sofía Castro | E10: 30 días | F10: =IF(B10="","",B10+IF(E10="Contado",0,IF(E10="7 días",7,IF(E10="15 días",15,IF(E10="30 días",30,IF(E10="45 días",45,IF(E10="60 días",60,0))))))) -> 46182 | G10: 1100000 | L10: =IF(G10="","",MAX(0,G10-SUM(I10,K10))) -> 1100000 | M10: =IF(G10="","",IF(L10=0,0,MAX(0,TODAY()-F10))) -> 10 | N10: =IF(G10="","",IF(L10=0,"Pagada",IF(M10>0,"Vencida",IF(SUM(I10,K10)>0,"Parcial","Pendiente")))) -> Vencida | O10: Ana López | P10: Por cobrar
A11: F-003 | B11: 46178 | C11: 7 | D11: =IF(C11="","",IFERROR(VLOOKUP(C11,CRM!$B$8:$O$1007,2,FALSE()),"Revisar ID")) -> Diego Ramírez | E11: 15 días | F11: =IF(B11="","",B11+IF(E11="Contado",0,IF(E11="7 días",7,IF(E11="15 días",15,IF(E11="30 días",30,IF(E11="45 días",45,IF(E11="60 días",60,0))))))) -> 46193 | G11: 1800000 | H11: 46183 | I11: 700000 | L11: =IF(G11="","",MAX(0,G11-SUM(I11,K11))) -> 1100000 | M11: =IF(G11="","",IF(L11=0,0,MAX(0,TODAY()-F11))) -> 0 | N11: =IF(G11="","",IF(L11=0,"Pagada",IF(M11>0,"Vencida",IF(SUM(I11,K11)>0,"Parcial","Pendiente")))) -> Parcial | O11: Kevin Ramírez | P11: Abono recibido
A12: F-004 | B12: 46183 | C12: 10 | D12: =IF(C12="","",IFERROR(VLOOKUP(C12,CRM!$B$8:$O$1007,2,FALSE()),"Revisar ID")) -> Valentina Gómez | E12: 30 días | F12: =IF(B12="","",B12+IF(E12="Contado",0,IF(E12="7 días",7,IF(E12="15 días",15,IF(E12="30 días",30,IF(E12="45 días",45,IF(E12="60 días",60,0))))))) -> 46213 | G12: 1300000 | L12: =IF(G12="","",MAX(0,G12-SUM(I12,K12))) -> 1300000 | M12: =IF(G12="","",IF(L12=0,0,MAX(0,TODAY()-F12))) -> 0 | N12: =IF(G12="","",IF(L12=0,"Pagada",IF(M12>0,"Vencida",IF(SUM(I12,K12)>0,"Parcial","Pendiente")))) -> Pendiente | O12: José González | P12: Reciente
A13: F-005 | B13: 46127 | C13: 2 | D13: =IF(C13="","",IFERROR(VLOOKUP(C13,CRM!$B$8:$O$1007,2,FALSE()),"Revisar ID")) -> Andrea Morales | E13: 15 días | F13: =IF(B13="","",B13+IF(E13="Contado",0,IF(E13="7 días",7,IF(E13="15 días",15,IF(E13="30 días",30,IF(E13="45 días",45,IF(E13="60 días",60,0))))))) -> 46142 | G13: 1200000 | H13: 46137 | I13: 1200000 | L13: =IF(G13="","",MAX(0,G13-SUM(I13,K13))) -> 0 | M13: =IF(G13="","",IF(L13=0,0,MAX(0,TODAY()-F13))) -> 0 | N13: =IF(G13="","",IF(L13=0,"Pagada",IF(M13>0,"Vencida",IF(SUM(I13,K13)>0,"Parcial","Pendiente")))) -> Pagada | O13: José González | P13: Pagada
A14: F-006 | B14: 46082 | C14: 8 | D14: =IF(C14="","",IFERROR(VLOOKUP(C14,CRM!$B$8:$O$1007,2,FALSE()),"Revisar ID")) -> Sofía Castro | E14: 30 días | F14: =IF(B14="","",B14+IF(E14="Contado",0,IF(E14="7 días",7,IF(E14="15 días",15,IF(E14="30 días",30,IF(E14="45 días",45,IF(E14="60 días",60,0))))))) -> 46112 | G14: 500000 | H14: 46101 | I14: 500000 | L14: =IF(G14="","",MAX(0,G14-SUM(I14,K14))) -> 0 | M14: =IF(G14="","",IF(L14=0,0,MAX(0,TODAY()-F14))) -> 0 | N14: =IF(G14="","",IF(L14=0,"Pagada",IF(M14>0,"Vencida",IF(SUM(I14,K14)>0,"Parcial","Pendiente")))) -> Pagada | O14: Ana López | P14: Pagada
D15: =IF(C15="","",IFERROR(VLOOKUP(C15,CRM!$B$8:$O$1007,2,FALSE()),"Revisar ID")) | F15: =IF(B15="","",B15+IF(E15="Contado",0,IF(E15="7 días",7,IF(E15="15 días",15,IF(E15="30 días",30,IF(E15="45 días",45,IF(E15="60 días",60,0))))))) | L15: =IF(G15="","",MAX(0,G15-SUM(I15,K15))) | M15: =IF(G15="","",IF(L15=0,0,MAX(0,TODAY()-F15))) | N15: =IF(G15="","",IF(L15=0,"Pagada",IF(M15>0,"Vencida",IF(SUM(I15,K15)>0,"Parcial","Pendiente"))))
D16: =IF(C16="","",IFERROR(VLOOKUP(C16,CRM!$B$8:$O$1007,2,FALSE()),"Revisar ID")) | F16: =IF(B16="","",B16+IF(E16="Contado",0,IF(E16="7 días",7,IF(E16="15 días",15,IF(E16="30 días",30,IF(E16="45 días",45,IF(E16="60 días",60,0))))))) | L16: =IF(G16="","",MAX(0,G16-SUM(I16,K16))) | M16: =IF(G16="","",IF(L16=0,0,MAX(0,TODAY()-F16))) | N16: =IF(G16="","",IF(L16=0,"Pagada",IF(M16>0,"Vencida",IF(SUM(I16,K16)>0,"Parcial","Pendiente"))))
D17: =IF(C17="","",IFERROR(VLOOKUP(C17,CRM!$B$8:$O$1007,2,FALSE()),"Revisar ID")) | F17: =IF(B17="","",B17+IF(E17="Contado",0,IF(E17="7 días",7,IF(E17="15 días",15,IF(E17="30 días",30,IF(E17="45 días",45,IF(E17="60 días",60,0))))))) | L17: =IF(G17="","",MAX(0,G17-SUM(I17,K17))) | M17: =IF(G17="","",IF(L17=0,0,MAX(0,TODAY()-F17))) | N17: =IF(G17="","",IF(L17=0,"Pagada",IF(M17>0,"Vencida",IF(SUM(I17,K17)>0,"Parcial","Pendiente"))))
D18: =IF(C18="","",IFERROR(VLOOKUP(C18,CRM!$B$8:$O$1007,2,FALSE()),"Revisar ID")) | F18: =IF(B18="","",B18+IF(E18="Contado",0,IF(E18="7 días",7,IF(E18="15 días",15,IF(E18="30 días",30,IF(E18="45 días",45,IF(E18="60 días",60,0))))))) | L18: =IF(G18="","",MAX(0,G18-SUM(I18,K18))) | M18: =IF(G18="","",IF(L18=0,0,MAX(0,TODAY()-F18))) | N18: =IF(G18="","",IF(L18=0,"Pagada",IF(M18>0,"Vencida",IF(SUM(I18,K18)>0,"Parcial","Pendiente"))))
D19: =IF(C19="","",IFERROR(VLOOKUP(C19,CRM!$B$8:$O$1007,2,FALSE()),"Revisar ID")) | F19: =IF(B19="","",B19+IF(E19="Contado",0,IF(E19="7 días",7,IF(E19="15 días",15,IF(E19="30 días",30,IF(E19="45 días",45,IF(E19="60 días",60,0))))))) | L19: =IF(G19="","",MAX(0,G19-SUM(I19,K19))) | M19: =IF(G19="","",IF(L19=0,0,MAX(0,TODAY()-F19))) | N19: =IF(G19="","",IF(L19=0,"Pagada",IF(M19>0,"Vencida",IF(SUM(I19,K19)>0,"Parcial","Pendiente"))))
D20: =IF(C20="","",IFERROR(VLOOKUP(C20,CRM!$B$8:$O$1007,2,FALSE()),"Revisar ID")) | F20: =IF(B20="","",B20+IF(E20="Contado",0,IF(E20="7 días",7,IF(E20="15 días",15,IF(E20="30 días",30,IF(E20="45 días",45,IF(E20="60 días",60,0))))))) | L20: =IF(G20="","",MAX(0,G20-SUM(I20,K20))) | M20: =IF(G20="","",IF(L20=0,0,MAX(0,TODAY()-F20))) | N20: =IF(G20="","",IF(L20=0,"Pagada",IF(M20>0,"Vencida",IF(SUM(I20,K20)>0,"Parcial","Pendiente"))))
D21: =IF(C21="","",IFERROR(VLOOKUP(C21,CRM!$B$8:$O$1007,2,FALSE()),"Revisar ID")) | F21: =IF(B21="","",B21+IF(E21="Contado",0,IF(E21="7 días",7,IF(E21="15 días",15,IF(E21="30 días",30,IF(E21="45 días",45,IF(E21="60 días",60,0))))))) | L21: =IF(G21="","",MAX(0,G21-SUM(I21,K21))) | M21: =IF(G21="","",IF(L21=0,0,MAX(0,TODAY()-F21))) | N21: =IF(G21="","",IF(L21=0,"Pagada",IF(M21>0,"Vencida",IF(SUM(I21,K21)>0,"Parcial","Pendiente"))))
D22: =IF(C22="","",IFERROR(VLOOKUP(C22,CRM!$B$8:$O$1007,2,FALSE()),"Revisar ID")) | F22: =IF(B22="","",B22+IF(E22="Contado",0,IF(E22="7 días",7,IF(E22="15 días",15,IF(E22="30 días",30,IF(E22="45 días",45,IF(E22="60 días",60,0))))))) | L22: =IF(G22="","",MAX(0,G22-SUM(I22,K22))) | M22: =IF(G22="","",IF(L22=0,0,MAX(0,TODAY()-F22))) | N22: =IF(G22="","",IF(L22=0,"Pagada",IF(M22>0,"Vencida",IF(SUM(I22,K22)>0,"Parcial","Pendiente"))))
D23: =IF(C23="","",IFERROR(VLOOKUP(C23,CRM!$B$8:$O$1007,2,FALSE()),"Revisar ID")) | F23: =IF(B23="","",B23+IF(E23="Contado",0,IF(E23="7 días",7,IF(E23="15 días",15,IF(E23="30 días",30,IF(E23="45 días",45,IF(E23="60 días",60,0))))))) | L23: =IF(G23="","",MAX(0,G23-SUM(I23,K23))) | M23: =IF(G23="","",IF(L23=0,0,MAX(0,TODAY()-F23))) | N23: =IF(G23="","",IF(L23=0,"Pagada",IF(M23>0,"Vencida",IF(SUM(I23,K23)>0,"Parcial","Pendiente"))))
D24: =IF(C24="","",IFERROR(VLOOKUP(C24,CRM!$B$8:$O$1007,2,FALSE()),"Revisar ID")) | F24: =IF(B24="","",B24+IF(E24="Contado",0,IF(E24="7 días",7,IF(E24="15 días",15,IF(E24="30 días",30,IF(E24="45 días",45,IF(E24="60 días",60,0))))))) | L24: =IF(G24="","",MAX(0,G24-SUM(I24,K24))) | M24: =IF(G24="","",IF(L24=0,0,MAX(0,TODAY()-F24))) | N24: =IF(G24="","",IF(L24=0,"Pagada",IF(M24>0,"Vencida",IF(SUM(I24,K24)>0,"Parcial","Pendiente"))))
D25: =IF(C25="","",IFERROR(VLOOKUP(C25,CRM!$B$8:$O$1007,2,FALSE()),"Revisar ID")) | F25: =IF(B25="","",B25+IF(E25="Contado",0,IF(E25="7 días",7,IF(E25="15 días",15,IF(E25="30 días",30,IF(E25="45 días",45,IF(E25="60 días",60,0))))))) | L25: =IF(G25="","",MAX(0,G25-SUM(I25,K25))) | M25: =IF(G25="","",IF(L25=0,0,MAX(0,TODAY()-F25))) | N25: =IF(G25="","",IF(L25=0,"Pagada",IF(M25>0,"Vencida",IF(SUM(I25,K25)>0,"Parcial","Pendiente"))))
D26: =IF(C26="","",IFERROR(VLOOKUP(C26,CRM!$B$8:$O$1007,2,FALSE()),"Revisar ID")) | F26: =IF(B26="","",B26+IF(E26="Contado",0,IF(E26="7 días",7,IF(E26="15 días",15,IF(E26="30 días",30,IF(E26="45 días",45,IF(E26="60 días",60,0))))))) | L26: =IF(G26="","",MAX(0,G26-SUM(I26,K26))) | M26: =IF(G26="","",IF(L26=0,0,MAX(0,TODAY()-F26))) | N26: =IF(G26="","",IF(L26=0,"Pagada",IF(M26>0,"Vencida",IF(SUM(I26,K26)>0,"Parcial","Pendiente"))))
... D1008: =IF(C1008="","",IFERROR(VLOOKUP(C1008,CRM!$B$8:$O$1007,2,FALSE()),"Revisar ID")) | F1008: =IF(B1008="","",B1008+IF(E1008="Contado",0,IF(E1008="7 días",7,IF(E1008="15 días",15,IF(E1008="30 días",30,IF(E1008="45 días",45,IF(E1008="60 días",60,0))))))) | L1008: =IF(G1008="","",MAX(0,G1008-SUM(I1008,K1008))) | M1008: =IF(G1008="","",IF(L1008=0,0,MAX(0,TODAY()-F1008))) | N1008: =IF(G1008="","",IF(L1008=0,"Pagada",IF(M1008>0,"Vencida",IF(SUM(I1008,K1008)>0,"Parcial","Pendiente"))))

Sheet Reporte
A1: REPORTE COMERCIAL Y COBRANZA
A2: Resumen ejecutivo para revisión mensual de clientes, ventas y cuentas por cobrar.
B4: Indicador | C4: Resultado | E4: Lectura rápida
B5: Clientes registrados | C5: =Dashboard!B5 -> 10 | E5: Este reporte permite revisar si la PYME está generando oportunidades, cerrando ventas y cobrando a tiempo. Revisar especialmente las cuentas vencidas y los clientes con más días sin actualización.
B6: Valor total ventas | C6: =Dashboard!E5 -> 11250000
B7: En negociación | C7: =Dashboard!H5 -> 5950000
B8: Ventas cerradas | C8: =Dashboard!K5 -> 1900000
B9: Cobranza pendiente | C9: =Dashboard!B9 -> 3500000
B10: Monto vencido | C10: =Dashboard!E9 -> 1100000
B11: Cuentas vencidas | C11: =Dashboard!H9 -> 1
B12: Tasa de cierre | C12: =Dashboard!K9 -> 0.2
