Workbook

Sheet Inicio
C1: COSTEO Y PRECIO DE PRODUCTOS PARA PYMES
C2: Calcula el costo real de tus productos y define un precio rentable sin tocar fórmulas.
D4: Promesa de la plantilla
D5: Ingresa productos, materiales, mano de obra y gastos. El Excel calcula costo total, precio sugerido, utilidad, margen y estado del precio.
C9: Paso | D9: Hoja | E9: Qué hace | G9: Idea clave
C10: 1 | D10: Productos | E10: Registra los productos que quieres costear. | G10: La plantilla usa una Base de Costos flexible. Si un producto necesita más materiales, agrega más filas con el mismo nombre del producto. La calculadora suma automáticamente por producto y grupo.
C11: 2 | D11: Base de Costos | E11: Agrega todos los materiales, mano de obra y gastos por producto.
C12: 3 | D12: Calculadora | E12: Elige un producto y revisa su costo, precio sugerido y margen.
C13: 4 | D13: Resumen Productos | E13: Compara todos los productos costeados.
C14: 5 | D14: Dashboard | E14: Visualiza precios, costos y composición del producto.

Sheet Dashboard
B1: DASHBOARD DE COSTEO
B2: Visualiza composición del costo, precios de referencia y rentabilidad del producto seleccionado.
B4: Producto a analizar | E4: Valor total unitario | H4: Precio sugerido | K4: Utilidad por unidad | N4: Margen real
B5: Camisa | E5: =SUMIFS('Base de Costos'!$H$5:$H$504,'Base de Costos'!$C$5:$C$504,$B$5) -> 14090 | H5: =IFERROR(E5/(1-IFERROR(VLOOKUP($B$5,Productos!$B$5:$H$124,7,FALSE),0)),0) -> 17612.5 | K5: =H5-E5 -> 3522.5 | N5: =IFERROR(K5/H5,0) -> 0.2
B9: Composición | C9: Monto | E9: Precio | F9: Monto
B10: Materia prima | C10: =SUMIFS('Base de Costos'!$H$5:$H$504,'Base de Costos'!$C$5:$C$504,$B$5,'Base de Costos'!$D$5:$D$504,"Materia prima") -> 9100 | E10: Cliente | F10: =IFERROR(VLOOKUP($B$5,Productos!$B$5:$H$124,4,FALSE),0) -> 20000
B11: Mano de obra | C11: =SUMIFS('Base de Costos'!$H$5:$H$504,'Base de Costos'!$C$5:$C$504,$B$5,'Base de Costos'!$D$5:$D$504,"Mano de obra") -> 4500 | E11: Competencia | F11: =IFERROR(VLOOKUP($B$5,Productos!$B$5:$H$124,5,FALSE),0) -> 30000
B12: CIF | C12: =SUMIFS('Base de Costos'!$H$5:$H$504,'Base de Costos'!$C$5:$C$504,$B$5,'Base de Costos'!$D$5:$D$504,"Costo indirecto fabricación") -> 50 | E12: Deseado PYME | F12: =IFERROR(VLOOKUP($B$5,Productos!$B$5:$H$124,6,FALSE),0) -> 40000
B13: Publicidad | C13: =SUMIFS('Base de Costos'!$H$5:$H$504,'Base de Costos'!$C$5:$C$504,$B$5,'Base de Costos'!$D$5:$D$504,"Gasto publicidad") -> 400 | E13: Sugerido | F13: =H5 -> 17612.5
B14: Administración | C14: =SUMIFS('Base de Costos'!$H$5:$H$504,'Base de Costos'!$C$5:$C$504,$B$5,'Base de Costos'!$D$5:$D$504,"Gasto administrativo") -> 0
B15: Otros gastos | C15: =SUMIFS('Base de Costos'!$H$5:$H$504,'Base de Costos'!$C$5:$C$504,$B$5,'Base de Costos'!$D$5:$D$504,"Otro gasto") -> 40
E16: Estado
E17: =IF($B$5="","",IF($E$5=0,"Sin datos",IF(F10<$E$5,"Riesgo: cliente bajo costo",IF($H$5>F10,"Revisar: sugerido sobre cliente",IF($H$5>F11,"Precio sobre competencia","Precio competitivo"))))) -> Precio competitivo
B20: Uso recomendado: registra todos los componentes en Base de Costos. Si un producto necesita más materiales, agrega más filas con el mismo nombre del producto. La calculadora y el dashboard se actualizan automáticamente.
H21: Esta hoja muestra un resumen automático del producto seleccionado. Aquí puedes revisar su costo total unitario, precio al cliente, precio de la competencia, precio sugerido, utilidad estimada y estado general del precio. No es necesario escribir cálculos en esta hoja; los resultados se actualizan con la información ingresada en Productos y Base de Costos.

Sheet Productos
B1: PRODUCTOS
B2: Registra aquí los productos que quieres costear. Puedes usar las filas vacías disponibles.
B4: Producto | C4: Descripción | D4: Unidad venta | E4: Precio cliente | F4: Precio competencia | G4: Precio deseado PYME | H4: % utilidad deseada
B5: Camisa | C5: Camisa manga corta | D5: 1 unidad | E5: 20000 | F5: 30000 | G5: 40000 | H5: 0.2 | J5: Usa las filas vacías para agregar nuevos productos. Luego usa el mismo nombre del producto en la hoja Base de Costos.
B6: Puff | C6: Puff exterior | D6: 1 unidad | E6: 45000 | F6: 60000 | G6: 70000 | H6: 0.3
B7: Banqueta | C7: Banqueta madera | D7: 1 unidad | E7: 35000 | F7: 42000 | G7: 50000 | H7: 0.25
B8: Servicio diseño | C8: Servicio personalizado | D8: 1 servicio | E8: 50000 | F8: 55000 | G8: 65000 | H8: 0.35

Sheet Base de Costos
C1: BASE DE COSTOS
C2: Agrega una fila por cada material, mano de obra, costo indirecto o gasto de cada producto.
C4: Producto | D4: Grupo | E4: Detalle | F4: Cantidad | G4: Costo unitario | H4: Total | I4: Auxiliar | K4: Auxiliar búsqueda | L4: Grupo | M4: Detalle | N4: Cantidad | O4: Total
C5: Camisa | D5: Materia prima | E5: Tela | F5: 1 | G5: 6000 | H5: =IF(OR(C5="",F5="",G5=""),"",F5*G5) -> 6000 | I5: =IF(C5="","",C5&"|"&COUNTIF($C$5:C5,C5)) -> Camisa|1 | J5: En esta hoja se ingresan los costos de cada producto. Agrega una fila por cada material, mano de obra, costo indirecto o gasto asociado. Selecciona el producto, el grupo de costo, escribe el detalle, la cantidad y el costo unitario. El total se calcula automáticamente. Si ingresas gastos como publicidad o administración, deben estar estimados por unidad de producto para que el cálculo sea claro. | K5: =IF($C5="","",$C5&"|"&COUNTIF($C$5:C5,$C5)) -> Camisa|1 | L5: =IF($C5="","",$D5) -> Materia prima | M5: =IF($C5="","",$E5) -> Tela | N5: =IF($C5="","",$F5) -> 1 | O5: =IF($C5="","",$H5) -> 6000
C6: Camisa | D6: Materia prima | E6: Hilo de coser | F6: 1 | G6: 3100 | H6: =IF(OR(C6="",F6="",G6=""),"",F6*G6) -> 3100 | I6: =IF(C6="","",C6&"|"&COUNTIF($C$5:C6,C6)) -> Camisa|2 | K6: =IF($C6="","",$C6&"|"&COUNTIF($C$5:C6,$C6)) -> Camisa|2 | L6: =IF($C6="","",$D6) -> Materia prima | M6: =IF($C6="","",$E6) -> Hilo de coser | N6: =IF($C6="","",$F6) -> 1 | O6: =IF($C6="","",$H6) -> 3100
C7: Camisa | D7: Gasto publicidad | E7: Botones | F7: 1 | G7: 400 | H7: =IF(OR(C7="",F7="",G7=""),"",F7*G7) -> 400 | I7: =IF(C7="","",C7&"|"&COUNTIF($C$5:C7,C7)) -> Camisa|3 | K7: =IF($C7="","",$C7&"|"&COUNTIF($C$5:C7,$C7)) -> Camisa|3 | L7: =IF($C7="","",$D7) -> Gasto publicidad | M7: =IF($C7="","",$E7) -> Botones | N7: =IF($C7="","",$F7) -> 1 | O7: =IF($C7="","",$H7) -> 400
C8: Camisa | D8: Mano de obra | E8: Salarios operativos | F8: 1 | G8: 4500 | H8: =IF(OR(C8="",F8="",G8=""),"",F8*G8) -> 4500 | I8: =IF(C8="","",C8&"|"&COUNTIF($C$5:C8,C8)) -> Camisa|4 | K8: =IF($C8="","",$C8&"|"&COUNTIF($C$5:C8,$C8)) -> Camisa|4 | L8: =IF($C8="","",$D8) -> Mano de obra | M8: =IF($C8="","",$E8) -> Salarios operativos | N8: =IF($C8="","",$F8) -> 1 | O8: =IF($C8="","",$H8) -> 4500
C9: Camisa | D9: Costo indirecto fabricación | E9: Depreciación equipos operativos | F9: 1 | G9: 50 | H9: =IF(OR(C9="",F9="",G9=""),"",F9*G9) -> 50 | I9: =IF(C9="","",C9&"|"&COUNTIF($C$5:C9,C9)) -> Camisa|5 | K9: =IF($C9="","",$C9&"|"&COUNTIF($C$5:C9,$C9)) -> Camisa|5 | L9: =IF($C9="","",$D9) -> Costo indirecto fabricación | M9: =IF($C9="","",$E9) -> Depreciación equipos operativos | N9: =IF($C9="","",$F9) -> 1 | O9: =IF($C9="","",$H9) -> 50
C10: Camisa | D10: Otro gasto | E10: Etiquetas | F10: 1 | G10: 40 | H10: =IF(OR(C10="",F10="",G10=""),"",F10*G10) -> 40 | I10: =IF(C10="","",C10&"|"&COUNTIF($C$5:C10,C10)) -> Camisa|6 | K10: =IF($C10="","",$C10&"|"&COUNTIF($C$5:C10,$C10)) -> Camisa|6 | L10: =IF($C10="","",$D10) -> Otro gasto | M10: =IF($C10="","",$E10) -> Etiquetas | N10: =IF($C10="","",$F10) -> 1 | O10: =IF($C10="","",$H10) -> 40
H11: =IF(OR(C11="",F11="",G11=""),"",F11*G11) | I11: =IF(C11="","",C11&"|"&COUNTIF($C$5:C11,C11)) | K11: =IF($C11="","",$C11&"|"&COUNTIF($C$5:C11,$C11)) | L11: =IF($C11="","",$D11) | M11: =IF($C11="","",$E11) | N11: =IF($C11="","",$F11) | O11: =IF($C11="","",$H11)
H12: =IF(OR(C12="",F12="",G12=""),"",F12*G12) | I12: =IF(C12="","",C12&"|"&COUNTIF($C$5:C12,C12)) | K12: =IF($C12="","",$C12&"|"&COUNTIF($C$5:C12,$C12)) | L12: =IF($C12="","",$D12) | M12: =IF($C12="","",$E12) | N12: =IF($C12="","",$F12) | O12: =IF($C12="","",$H12)
H13: =IF(OR(C13="",F13="",G13=""),"",F13*G13) | I13: =IF(C13="","",C13&"|"&COUNTIF($C$5:C13,C13)) | K13: =IF($C13="","",$C13&"|"&COUNTIF($C$5:C13,$C13)) | L13: =IF($C13="","",$D13) | M13: =IF($C13="","",$E13) | N13: =IF($C13="","",$F13) | O13: =IF($C13="","",$H13)
H14: =IF(OR(C14="",F14="",G14=""),"",F14*G14) | I14: =IF(C14="","",C14&"|"&COUNTIF($C$5:C14,C14)) | K14: =IF($C14="","",$C14&"|"&COUNTIF($C$5:C14,$C14)) | L14: =IF($C14="","",$D14) | M14: =IF($C14="","",$E14) | N14: =IF($C14="","",$F14) | O14: =IF($C14="","",$H14)
H15: =IF(OR(C15="",F15="",G15=""),"",F15*G15) | I15: =IF(C15="","",C15&"|"&COUNTIF($C$5:C15,C15)) | K15: =IF($C15="","",$C15&"|"&COUNTIF($C$5:C15,$C15)) | L15: =IF($C15="","",$D15) | M15: =IF($C15="","",$E15) | N15: =IF($C15="","",$F15) | O15: =IF($C15="","",$H15)
H16: =IF(OR(C16="",F16="",G16=""),"",F16*G16) | I16: =IF(C16="","",C16&"|"&COUNTIF($C$5:C16,C16)) | K16: =IF($C16="","",$C16&"|"&COUNTIF($C$5:C16,$C16)) | L16: =IF($C16="","",$D16) | M16: =IF($C16="","",$E16) | N16: =IF($C16="","",$F16) | O16: =IF($C16="","",$H16)
H17: =IF(OR(C17="",F17="",G17=""),"",F17*G17) | I17: =IF(C17="","",C17&"|"&COUNTIF($C$5:C17,C17)) | K17: =IF($C17="","",$C17&"|"&COUNTIF($C$5:C17,$C17)) | L17: =IF($C17="","",$D17) | M17: =IF($C17="","",$E17) | N17: =IF($C17="","",$F17) | O17: =IF($C17="","",$H17)
H18: =IF(OR(C18="",F18="",G18=""),"",F18*G18) | I18: =IF(C18="","",C18&"|"&COUNTIF($C$5:C18,C18)) | K18: =IF($C18="","",$C18&"|"&COUNTIF($C$5:C18,$C18)) | L18: =IF($C18="","",$D18) | M18: =IF($C18="","",$E18) | N18: =IF($C18="","",$F18) | O18: =IF($C18="","",$H18)
H19: =IF(OR(C19="",F19="",G19=""),"",F19*G19) | I19: =IF(C19="","",C19&"|"&COUNTIF($C$5:C19,C19)) | K19: =IF($C19="","",$C19&"|"&COUNTIF($C$5:C19,$C19)) | L19: =IF($C19="","",$D19) | M19: =IF($C19="","",$E19) | N19: =IF($C19="","",$F19) | O19: =IF($C19="","",$H19)
H20: =IF(OR(C20="",F20="",G20=""),"",F20*G20) | I20: =IF(C20="","",C20&"|"&COUNTIF($C$5:C20,C20)) | K20: =IF($C20="","",$C20&"|"&COUNTIF($C$5:C20,$C20)) | L20: =IF($C20="","",$D20) | M20: =IF($C20="","",$E20) | N20: =IF($C20="","",$F20) | O20: =IF($C20="","",$H20)
H21: =IF(OR(C21="",F21="",G21=""),"",F21*G21) | I21: =IF(C21="","",C21&"|"&COUNTIF($C$5:C21,C21)) | K21: =IF($C21="","",$C21&"|"&COUNTIF($C$5:C21,$C21)) | L21: =IF($C21="","",$D21) | M21: =IF($C21="","",$E21) | N21: =IF($C21="","",$F21) | O21: =IF($C21="","",$H21)
H22: =IF(OR(C22="",F22="",G22=""),"",F22*G22) | I22: =IF(C22="","",C22&"|"&COUNTIF($C$5:C22,C22)) | K22: =IF($C22="","",$C22&"|"&COUNTIF($C$5:C22,$C22)) | L22: =IF($C22="","",$D22) | M22: =IF($C22="","",$E22) | N22: =IF($C22="","",$F22) | O22: =IF($C22="","",$H22)
... H504: =IF(OR(C504="",F504="",G504=""),"",F504*G504) | I504: =IF(C504="","",C504&"|"&COUNTIF($C$5:C504,C504)) | K504: =IF($C504="","",$C504&"|"&COUNTIF($C$5:C504,$C504)) | L504: =IF($C504="","",$D504) | M504: =IF($C504="","",$E504) | N504: =IF($C504="","",$F504) | O504: =IF($C504="","",$H504)

Sheet Calculadora
C1: CALCULADORA DE COSTEO Y PRECIO
C2: Elige un producto y revisa automáticamente su costo, utilidad, margen y precio sugerido.
D4: Producto seleccionado | G4: Unidad de venta
D5: Camisa | G5: =IFERROR(VLOOKUP($D$5,Productos!$B$5:$H$124,3,FALSE),"") -> 1 unidad
J6: En esta hoja puedes seleccionar un producto y ver su análisis completo. La calculadora muestra automáticamente los costos por grupo, el valor total unitario, el precio sugerido, la utilidad estimada, el margen real y el detalle de los componentes ingresados en Base de Costos. Sirve para revisar si el precio actual es suficiente o si conviene ajustarlo.
D7: RESUMEN DE COSTOS | G7: PRECIO Y DECISIÓN
D8: (+) Materias primas | E8: =SUMIFS('Base de Costos'!$H$5:$H$504,'Base de Costos'!$C$5:$C$504,$D$5,'Base de Costos'!$D$5:$D$504,"Materia prima") -> 9100 | G8: PRECIO CLIENTE | H8: =IFERROR(VLOOKUP($D$5,Productos!$B$5:$H$124,4,FALSE),0) -> 20000
D9: (+) Mano de obra | E9: =SUMIFS('Base de Costos'!$H$5:$H$504,'Base de Costos'!$C$5:$C$504,$D$5,'Base de Costos'!$D$5:$D$504,"Mano de obra") -> 4500 | G9: PRECIO COMPETENCIA | H9: =IFERROR(VLOOKUP($D$5,Productos!$B$5:$H$124,5,FALSE),0) -> 30000
D10: (+) Costos indirectos fabricación | E10: =SUMIFS('Base de Costos'!$H$5:$H$504,'Base de Costos'!$C$5:$C$504,$D$5,'Base de Costos'!$D$5:$D$504,"Costo indirecto fabricación") -> 50 | G10: PRECIO DESEADO PYME | H10: =IFERROR(VLOOKUP($D$5,Productos!$B$5:$H$124,6,FALSE),0) -> 40000
D11: (=) Costo total producción | E11: =SUM(E8:E10) -> 13650 | G11: % UTILIDAD DESEADA | H11: =IFERROR(VLOOKUP($D$5,Productos!$B$5:$H$124,7,FALSE),0) -> 0.2
G12: PRECIO SUGERIDO | H12: =IFERROR($E$18/(1-H11),0) -> 17612.5
D13: (+) Gastos publicidad | E13: =SUMIFS('Base de Costos'!$H$5:$H$504,'Base de Costos'!$C$5:$C$504,$D$5,'Base de Costos'!$D$5:$D$504,"Gasto publicidad") -> 400 | G13: UTILIDAD POR UNIDAD | H13: =H12-$E$18 -> 3522.5
D14: (+) Gastos administrativos | E14: =SUMIFS('Base de Costos'!$H$5:$H$504,'Base de Costos'!$C$5:$C$504,$D$5,'Base de Costos'!$D$5:$D$504,"Gasto administrativo") -> 0 | G14: MARGEN REAL | H14: =IFERROR(H13/H12,0) -> 0.2
D15: (+) Otros gastos | E15: =SUMIFS('Base de Costos'!$H$5:$H$504,'Base de Costos'!$C$5:$C$504,$D$5,'Base de Costos'!$D$5:$D$504,"Otro gasto") -> 40 | G15: DIF. VS COMPETENCIA | H15: =H9-H12 -> 12387.5
D16: (=) Gasto total | E16: =SUM(E13:E15) -> 440 | G16: ESTADO | H16: =IF($D$5="","",IF($E$18=0,"Sin datos",IF(H8<$E$18,"Riesgo: cliente bajo costo",IF(H12>H8,"Revisar: sugerido sobre cliente",IF(H12>H9,"Precio sobre competencia","Precio competitivo"))))) -> Precio competitivo
D18: VALOR TOTAL UNITARIO | E18: =E11+E16 -> 14090
D20: Fórmula usada: Precio de venta = Valor total unitario / (1 - % utilidad deseada)
D23: DETALLE DEL PRODUCTO SELECCIONADO
D24: Grupo | E24: Detalle | F24: Cantidad | G24: Total
D25: =IFERROR(VLOOKUP($D$5&"|"&1,'Base de Costos'!$K$5:$O$504,2,FALSE),"") -> Materia prima | E25: =IFERROR(VLOOKUP($D$5&"|"&1,'Base de Costos'!$K$5:$O$504,3,FALSE),"") -> Tela | F25: =IFERROR(VLOOKUP($D$5&"|"&1,'Base de Costos'!$K$5:$O$504,4,FALSE),"") -> 1 | G25: =IFERROR(VLOOKUP($D$5&"|"&1,'Base de Costos'!$K$5:$O$504,5,FALSE),"") -> 6000
D26: =IFERROR(VLOOKUP($D$5&"|"&2,'Base de Costos'!$K$5:$O$504,2,FALSE),"") -> Materia prima | E26: =IFERROR(VLOOKUP($D$5&"|"&2,'Base de Costos'!$K$5:$O$504,3,FALSE),"") -> Hilo de coser | F26: =IFERROR(VLOOKUP($D$5&"|"&2,'Base de Costos'!$K$5:$O$504,4,FALSE),"") -> 1 | G26: =IFERROR(VLOOKUP($D$5&"|"&2,'Base de Costos'!$K$5:$O$504,5,FALSE),"") -> 3100
D27: =IFERROR(VLOOKUP($D$5&"|"&3,'Base de Costos'!$K$5:$O$504,2,FALSE),"") -> Gasto publicidad | E27: =IFERROR(VLOOKUP($D$5&"|"&3,'Base de Costos'!$K$5:$O$504,3,FALSE),"") -> Botones | F27: =IFERROR(VLOOKUP($D$5&"|"&3,'Base de Costos'!$K$5:$O$504,4,FALSE),"") -> 1 | G27: =IFERROR(VLOOKUP($D$5&"|"&3,'Base de Costos'!$K$5:$O$504,5,FALSE),"") -> 400
D28: =IFERROR(VLOOKUP($D$5&"|"&4,'Base de Costos'!$K$5:$O$504,2,FALSE),"") -> Mano de obra | E28: =IFERROR(VLOOKUP($D$5&"|"&4,'Base de Costos'!$K$5:$O$504,3,FALSE),"") -> Salarios operativos | F28: =IFERROR(VLOOKUP($D$5&"|"&4,'Base de Costos'!$K$5:$O$504,4,FALSE),"") -> 1 | G28: =IFERROR(VLOOKUP($D$5&"|"&4,'Base de Costos'!$K$5:$O$504,5,FALSE),"") -> 4500
D29: =IFERROR(VLOOKUP($D$5&"|"&5,'Base de Costos'!$K$5:$O$504,2,FALSE),"") -> Costo indirecto fabricación | E29: =IFERROR(VLOOKUP($D$5&"|"&5,'Base de Costos'!$K$5:$O$504,3,FALSE),"") -> Depreciación equipos operativos | F29: =IFERROR(VLOOKUP($D$5&"|"&5,'Base de Costos'!$K$5:$O$504,4,FALSE),"") -> 1 | G29: =IFERROR(VLOOKUP($D$5&"|"&5,'Base de Costos'!$K$5:$O$504,5,FALSE),"") -> 50
D30: =IFERROR(VLOOKUP($D$5&"|"&6,'Base de Costos'!$K$5:$O$504,2,FALSE),"") -> Otro gasto | E30: =IFERROR(VLOOKUP($D$5&"|"&6,'Base de Costos'!$K$5:$O$504,3,FALSE),"") -> Etiquetas | F30: =IFERROR(VLOOKUP($D$5&"|"&6,'Base de Costos'!$K$5:$O$504,4,FALSE),"") -> 1 | G30: =IFERROR(VLOOKUP($D$5&"|"&6,'Base de Costos'!$K$5:$O$504,5,FALSE),"") -> 40
D31: =IFERROR(VLOOKUP($D$5&"|"&7,'Base de Costos'!$K$5:$O$504,2,FALSE),"") | E31: =IFERROR(VLOOKUP($D$5&"|"&7,'Base de Costos'!$K$5:$O$504,3,FALSE),"") | F31: =IFERROR(VLOOKUP($D$5&"|"&7,'Base de Costos'!$K$5:$O$504,4,FALSE),"") | G31: =IFERROR(VLOOKUP($D$5&"|"&7,'Base de Costos'!$K$5:$O$504,5,FALSE),"")
D32: =IFERROR(VLOOKUP($D$5&"|"&8,'Base de Costos'!$K$5:$O$504,2,FALSE),"") | E32: =IFERROR(VLOOKUP($D$5&"|"&8,'Base de Costos'!$K$5:$O$504,3,FALSE),"") | F32: =IFERROR(VLOOKUP($D$5&"|"&8,'Base de Costos'!$K$5:$O$504,4,FALSE),"") | G32: =IFERROR(VLOOKUP($D$5&"|"&8,'Base de Costos'!$K$5:$O$504,5,FALSE),"")
D33: =IFERROR(VLOOKUP($D$5&"|"&9,'Base de Costos'!$K$5:$O$504,2,FALSE),"") | E33: =IFERROR(VLOOKUP($D$5&"|"&9,'Base de Costos'!$K$5:$O$504,3,FALSE),"") | F33: =IFERROR(VLOOKUP($D$5&"|"&9,'Base de Costos'!$K$5:$O$504,4,FALSE),"") | G33: =IFERROR(VLOOKUP($D$5&"|"&9,'Base de Costos'!$K$5:$O$504,5,FALSE),"")
D34: =IFERROR(VLOOKUP($D$5&"|"&10,'Base de Costos'!$K$5:$O$504,2,FALSE),"") | E34: =IFERROR(VLOOKUP($D$5&"|"&10,'Base de Costos'!$K$5:$O$504,3,FALSE),"") | F34: =IFERROR(VLOOKUP($D$5&"|"&10,'Base de Costos'!$K$5:$O$504,4,FALSE),"") | G34: =IFERROR(VLOOKUP($D$5&"|"&10,'Base de Costos'!$K$5:$O$504,5,FALSE),"")
D35: =IFERROR(VLOOKUP($D$5&"|"&11,'Base de Costos'!$K$5:$O$504,2,FALSE),"") | E35: =IFERROR(VLOOKUP($D$5&"|"&11,'Base de Costos'!$K$5:$O$504,3,FALSE),"") | F35: =IFERROR(VLOOKUP($D$5&"|"&11,'Base de Costos'!$K$5:$O$504,4,FALSE),"") | G35: =IFERROR(VLOOKUP($D$5&"|"&11,'Base de Costos'!$K$5:$O$504,5,FALSE),"")
D36: =IFERROR(VLOOKUP($D$5&"|"&12,'Base de Costos'!$K$5:$O$504,2,FALSE),"") | E36: =IFERROR(VLOOKUP($D$5&"|"&12,'Base de Costos'!$K$5:$O$504,3,FALSE),"") | F36: =IFERROR(VLOOKUP($D$5&"|"&12,'Base de Costos'!$K$5:$O$504,4,FALSE),"") | G36: =IFERROR(VLOOKUP($D$5&"|"&12,'Base de Costos'!$K$5:$O$504,5,FALSE),"")
D37: =IFERROR(VLOOKUP($D$5&"|"&13,'Base de Costos'!$K$5:$O$504,2,FALSE),"") | E37: =IFERROR(VLOOKUP($D$5&"|"&13,'Base de Costos'!$K$5:$O$504,3,FALSE),"") | F37: =IFERROR(VLOOKUP($D$5&"|"&13,'Base de Costos'!$K$5:$O$504,4,FALSE),"") | G37: =IFERROR(VLOOKUP($D$5&"|"&13,'Base de Costos'!$K$5:$O$504,5,FALSE),"")
D38: =IFERROR(VLOOKUP($D$5&"|"&14,'Base de Costos'!$K$5:$O$504,2,FALSE),"") | E38: =IFERROR(VLOOKUP($D$5&"|"&14,'Base de Costos'!$K$5:$O$504,3,FALSE),"") | F38: =IFERROR(VLOOKUP($D$5&"|"&14,'Base de Costos'!$K$5:$O$504,4,FALSE),"") | G38: =IFERROR(VLOOKUP($D$5&"|"&14,'Base de Costos'!$K$5:$O$504,5,FALSE),"")
D39: =IFERROR(VLOOKUP($D$5&"|"&15,'Base de Costos'!$K$5:$O$504,2,FALSE),"") | E39: =IFERROR(VLOOKUP($D$5&"|"&15,'Base de Costos'!$K$5:$O$504,3,FALSE),"") | F39: =IFERROR(VLOOKUP($D$5&"|"&15,'Base de Costos'!$K$5:$O$504,4,FALSE),"") | G39: =IFERROR(VLOOKUP($D$5&"|"&15,'Base de Costos'!$K$5:$O$504,5,FALSE),"")
D40: =IFERROR(VLOOKUP($D$5&"|"&16,'Base de Costos'!$K$5:$O$504,2,FALSE),"") | E40: =IFERROR(VLOOKUP($D$5&"|"&16,'Base de Costos'!$K$5:$O$504,3,FALSE),"") | F40: =IFERROR(VLOOKUP($D$5&"|"&16,'Base de Costos'!$K$5:$O$504,4,FALSE),"") | G40: =IFERROR(VLOOKUP($D$5&"|"&16,'Base de Costos'!$K$5:$O$504,5,FALSE),"")
D41: =IFERROR(INDEX('Base de Costos'!$D$5:$D$504,MATCH($D$5&"|"&ROWS($D$25:D41),'Base de Costos'!$I$5:$I$504,0)),"") | E41: =IFERROR(INDEX('Base de Costos'!$E$5:$E$504,MATCH($D$5&"|"&ROWS($E$25:E41),'Base de Costos'!$I$5:$I$504,0)),"") | F41: =IFERROR(INDEX('Base de Costos'!$F$5:$F$504,MATCH($D$5&"|"&ROWS($F$25:F41),'Base de Costos'!$I$5:$I$504,0)),"") | G41: =IFERROR(INDEX('Base de Costos'!$H$5:$H$504,MATCH($D$5&"|"&ROWS($G$25:G41),'Base de Costos'!$I$5:$I$504,0)),"")
D42: =IFERROR(INDEX('Base de Costos'!$D$5:$D$504,MATCH($D$5&"|"&ROWS($D$25:D42),'Base de Costos'!$I$5:$I$504,0)),"") | E42: =IFERROR(INDEX('Base de Costos'!$E$5:$E$504,MATCH($D$5&"|"&ROWS($E$25:E42),'Base de Costos'!$I$5:$I$504,0)),"") | F42: =IFERROR(INDEX('Base de Costos'!$F$5:$F$504,MATCH($D$5&"|"&ROWS($F$25:F42),'Base de Costos'!$I$5:$I$504,0)),"") | G42: =IFERROR(INDEX('Base de Costos'!$H$5:$H$504,MATCH($D$5&"|"&ROWS($G$25:G42),'Base de Costos'!$I$5:$I$504,0)),"")

Sheet Resumen Productos
C1: RESUMEN DE PRODUCTOS
C2: Comparación automática de costo, precio sugerido, utilidad y estado por producto.
C4: Producto | D4: Materia prima | E4: Mano obra | F4: CIF | G4: Costo producción | H4: Gastos | I4: % utilidad | J4: Valor total | K4: Precio sugerido | L4: Utilidad | M4: Estado
C5: =IF(Productos!B5="","",Productos!B5) -> Camisa | D5: =IF($C5="","",SUMIFS('Base de Costos'!$H$5:$H$504,'Base de Costos'!$C$5:$C$504,$C5,'Base de Costos'!$D$5:$D$504,"Materia prima")) -> 9100 | E5: =IF($C5="","",SUMIFS('Base de Costos'!$H$5:$H$504,'Base de Costos'!$C$5:$C$504,$C5,'Base de Costos'!$D$5:$D$504,"Mano de obra")) -> 4500 | F5: =IF($C5="","",SUMIFS('Base de Costos'!$H$5:$H$504,'Base de Costos'!$C$5:$C$504,$C5,'Base de Costos'!$D$5:$D$504,"Costo indirecto fabricación")) -> 50 | G5: =IF($C5="","",SUM(D5:F5)) -> 13650 | H5: =IF($C5="","",SUMIFS('Base de Costos'!$H$5:$H$504,'Base de Costos'!$C$5:$C$504,$C5,'Base de Costos'!$D$5:$D$504,"Gasto publicidad")+SUMIFS('Base de Costos'!$H$5:$H$504,'Base de Costos'!$C$5:$C$504,$C5,'Base de Costos'!$D$5:$D$504,"Gasto administrativo")+SUMIFS('Base de Costos'!$H$5:$H$504,'Base de Costos'!$C$5:$C$504,$C5,'Base de Costos'!$D$5:$D$504,"Otro gasto")) -> 440 | I5: =IF($C5="","",IFERROR(VLOOKUP($C5,Productos!$B$5:$H$124,7,FALSE),0)) -> 0.2 | J5: =IF($C5="","",G5+H5) -> 14090 | K5: =IF($C5="","",IFERROR(J5/(1-I5),0)) -> 17612.5 | L5: =IF($C5="","",K5-J5) -> 3522.5 | M5: =IF($C5="","",IF(J5=0,"Sin datos",IF(IFERROR(VLOOKUP($C5,Productos!$B$5:$H$124,4,FALSE),0)=0,"Sin precio cliente",IF(IFERROR(VLOOKUP($C5,Productos!$B$5:$H$124,4,FALSE),0)<J5,"Riesgo: cliente bajo costo",IF(K5>IFERROR(VLOOKUP($C5,Productos!$B$5:$H$124,4,FALSE),0),"Revisar: sugerido sobre cliente",IF(K5>IFERROR(VLOOKUP($C5,Productos!$B$5:$H$124,5,FALSE),0),"Sobre competencia","Competitivo")))))) -> Competitivo | O5: Esta hoja compara todos los productos registrados. Permite revisar rápidamente el costo unitario, precio al cliente, precio competencia, precio sugerido, utilidad y estado de cada producto. Es útil para identificar qué productos son rentables, cuáles están bajo costo y cuáles necesitan revisión de precio.
C6: =IF(Productos!B6="","",Productos!B6) -> Puff | D6: =IF($C6="","",SUMIFS('Base de Costos'!$H$5:$H$504,'Base de Costos'!$C$5:$C$504,$C6,'Base de Costos'!$D$5:$D$504,"Materia prima")) -> 0 | E6: =IF($C6="","",SUMIFS('Base de Costos'!$H$5:$H$504,'Base de Costos'!$C$5:$C$504,$C6,'Base de Costos'!$D$5:$D$504,"Mano de obra")) -> 0 | F6: =IF($C6="","",SUMIFS('Base de Costos'!$H$5:$H$504,'Base de Costos'!$C$5:$C$504,$C6,'Base de Costos'!$D$5:$D$504,"Costo indirecto fabricación")) -> 0 | G6: =IF($C6="","",SUM(D6:F6)) -> 0 | H6: =IF($C6="","",SUMIFS('Base de Costos'!$H$5:$H$504,'Base de Costos'!$C$5:$C$504,$C6,'Base de Costos'!$D$5:$D$504,"Gasto publicidad")+SUMIFS('Base de Costos'!$H$5:$H$504,'Base de Costos'!$C$5:$C$504,$C6,'Base de Costos'!$D$5:$D$504,"Gasto administrativo")+SUMIFS('Base de Costos'!$H$5:$H$504,'Base de Costos'!$C$5:$C$504,$C6,'Base de Costos'!$D$5:$D$504,"Otro gasto")) -> 0 | I6: =IF($C6="","",IFERROR(VLOOKUP($C6,Productos!$B$5:$H$124,7,FALSE),0)) -> 0.3 | J6: =IF($C6="","",G6+H6) -> 0 | K6: =IF($C6="","",IFERROR(J6/(1-I6),0)) -> 0 | L6: =IF($C6="","",K6-J6) -> 0 | M6: =IF($C6="","",IF(J6=0,"Sin datos",IF(IFERROR(VLOOKUP($C6,Productos!$B$5:$H$124,4,FALSE),0)=0,"Sin precio cliente",IF(IFERROR(VLOOKUP($C6,Productos!$B$5:$H$124,4,FALSE),0)<J6,"Riesgo: cliente bajo costo",IF(K6>IFERROR(VLOOKUP($C6,Productos!$B$5:$H$124,4,FALSE),0),"Revisar: sugerido sobre cliente",IF(K6>IFERROR(VLOOKUP($C6,Productos!$B$5:$H$124,5,FALSE),0),"Sobre competencia","Competitivo")))))) -> Sin datos
C7: =IF(Productos!B7="","",Productos!B7) -> Banqueta | D7: =IF($C7="","",SUMIFS('Base de Costos'!$H$5:$H$504,'Base de Costos'!$C$5:$C$504,$C7,'Base de Costos'!$D$5:$D$504,"Materia prima")) -> 0 | E7: =IF($C7="","",SUMIFS('Base de Costos'!$H$5:$H$504,'Base de Costos'!$C$5:$C$504,$C7,'Base de Costos'!$D$5:$D$504,"Mano de obra")) -> 0 | F7: =IF($C7="","",SUMIFS('Base de Costos'!$H$5:$H$504,'Base de Costos'!$C$5:$C$504,$C7,'Base de Costos'!$D$5:$D$504,"Costo indirecto fabricación")) -> 0 | G7: =IF($C7="","",SUM(D7:F7)) -> 0 | H7: =IF($C7="","",SUMIFS('Base de Costos'!$H$5:$H$504,'Base de Costos'!$C$5:$C$504,$C7,'Base de Costos'!$D$5:$D$504,"Gasto publicidad")+SUMIFS('Base de Costos'!$H$5:$H$504,'Base de Costos'!$C$5:$C$504,$C7,'Base de Costos'!$D$5:$D$504,"Gasto administrativo")+SUMIFS('Base de Costos'!$H$5:$H$504,'Base de Costos'!$C$5:$C$504,$C7,'Base de Costos'!$D$5:$D$504,"Otro gasto")) -> 0 | I7: =IF($C7="","",IFERROR(VLOOKUP($C7,Productos!$B$5:$H$124,7,FALSE),0)) -> 0.25 | J7: =IF($C7="","",G7+H7) -> 0 | K7: =IF($C7="","",IFERROR(J7/(1-I7),0)) -> 0 | L7: =IF($C7="","",K7-J7) -> 0 | M7: =IF($C7="","",IF(J7=0,"Sin datos",IF(IFERROR(VLOOKUP($C7,Productos!$B$5:$H$124,4,FALSE),0)=0,"Sin precio cliente",IF(IFERROR(VLOOKUP($C7,Productos!$B$5:$H$124,4,FALSE),0)<J7,"Riesgo: cliente bajo costo",IF(K7>IFERROR(VLOOKUP($C7,Productos!$B$5:$H$124,4,FALSE),0),"Revisar: sugerido sobre cliente",IF(K7>IFERROR(VLOOKUP($C7,Productos!$B$5:$H$124,5,FALSE),0),"Sobre competencia","Competitivo")))))) -> Sin datos
C8: =IF(Productos!B8="","",Productos!B8) -> Servicio diseño | D8: =IF($C8="","",SUMIFS('Base de Costos'!$H$5:$H$504,'Base de Costos'!$C$5:$C$504,$C8,'Base de Costos'!$D$5:$D$504,"Materia prima")) -> 0 | E8: =IF($C8="","",SUMIFS('Base de Costos'!$H$5:$H$504,'Base de Costos'!$C$5:$C$504,$C8,'Base de Costos'!$D$5:$D$504,"Mano de obra")) -> 0 | F8: =IF($C8="","",SUMIFS('Base de Costos'!$H$5:$H$504,'Base de Costos'!$C$5:$C$504,$C8,'Base de Costos'!$D$5:$D$504,"Costo indirecto fabricación")) -> 0 | G8: =IF($C8="","",SUM(D8:F8)) -> 0 | H8: =IF($C8="","",SUMIFS('Base de Costos'!$H$5:$H$504,'Base de Costos'!$C$5:$C$504,$C8,'Base de Costos'!$D$5:$D$504,"Gasto publicidad")+SUMIFS('Base de Costos'!$H$5:$H$504,'Base de Costos'!$C$5:$C$504,$C8,'Base de Costos'!$D$5:$D$504,"Gasto administrativo")+SUMIFS('Base de Costos'!$H$5:$H$504,'Base de Costos'!$C$5:$C$504,$C8,'Base de Costos'!$D$5:$D$504,"Otro gasto")) -> 0 | I8: =IF($C8="","",IFERROR(VLOOKUP($C8,Productos!$B$5:$H$124,7,FALSE),0)) -> 0.35 | J8: =IF($C8="","",G8+H8) -> 0 | K8: =IF($C8="","",IFERROR(J8/(1-I8),0)) -> 0 | L8: =IF($C8="","",K8-J8) -> 0 | M8: =IF($C8="","",IF(J8=0,"Sin datos",IF(IFERROR(VLOOKUP($C8,Productos!$B$5:$H$124,4,FALSE),0)=0,"Sin precio cliente",IF(IFERROR(VLOOKUP($C8,Productos!$B$5:$H$124,4,FALSE),0)<J8,"Riesgo: cliente bajo costo",IF(K8>IFERROR(VLOOKUP($C8,Productos!$B$5:$H$124,4,FALSE),0),"Revisar: sugerido sobre cliente",IF(K8>IFERROR(VLOOKUP($C8,Productos!$B$5:$H$124,5,FALSE),0),"Sobre competencia","Competitivo")))))) -> Sin datos
C9: =IF(Productos!B9="","",Productos!B9) | D9: =IF($C9="","",SUMIFS('Base de Costos'!$H$5:$H$504,'Base de Costos'!$C$5:$C$504,$C9,'Base de Costos'!$D$5:$D$504,"Materia prima")) | E9: =IF($C9="","",SUMIFS('Base de Costos'!$H$5:$H$504,'Base de Costos'!$C$5:$C$504,$C9,'Base de Costos'!$D$5:$D$504,"Mano de obra")) | F9: =IF($C9="","",SUMIFS('Base de Costos'!$H$5:$H$504,'Base de Costos'!$C$5:$C$504,$C9,'Base de Costos'!$D$5:$D$504,"Costo indirecto fabricación")) | G9: =IF($C9="","",SUM(D9:F9)) | H9: =IF($C9="","",SUMIFS('Base de Costos'!$H$5:$H$504,'Base de Costos'!$C$5:$C$504,$C9,'Base de Costos'!$D$5:$D$504,"Gasto publicidad")+SUMIFS('Base de Costos'!$H$5:$H$504,'Base de Costos'!$C$5:$C$504,$C9,'Base de Costos'!$D$5:$D$504,"Gasto administrativo")+SUMIFS('Base de Costos'!$H$5:$H$504,'Base de Costos'!$C$5:$C$504,$C9,'Base de Costos'!$D$5:$D$504,"Otro gasto")) | I9: =IF($C9="","",IFERROR(VLOOKUP($C9,Productos!$B$5:$H$124,7,FALSE),0)) | J9: =IF($C9="","",G9+H9) | K9: =IF($C9="","",IFERROR(J9/(1-I9),0)) | L9: =IF($C9="","",K9-J9) | M9: =IF($C9="","",IF(J9=0,"Sin datos",IF(IFERROR(VLOOKUP($C9,Productos!$B$5:$H$124,4,FALSE),0)=0,"Sin precio cliente",IF(IFERROR(VLOOKUP($C9,Productos!$B$5:$H$124,4,FALSE),0)<J9,"Riesgo: cliente bajo costo",IF(K9>IFERROR(VLOOKUP($C9,Productos!$B$5:$H$124,4,FALSE),0),"Revisar: sugerido sobre cliente",IF(K9>IFERROR(VLOOKUP($C9,Productos!$B$5:$H$124,5,FALSE),0),"Sobre competencia","Competitivo"))))))
C10: =IF(Productos!B10="","",Productos!B10) | D10: =IF($C10="","",SUMIFS('Base de Costos'!$H$5:$H$504,'Base de Costos'!$C$5:$C$504,$C10,'Base de Costos'!$D$5:$D$504,"Materia prima")) | E10: =IF($C10="","",SUMIFS('Base de Costos'!$H$5:$H$504,'Base de Costos'!$C$5:$C$504,$C10,'Base de Costos'!$D$5:$D$504,"Mano de obra")) | F10: =IF($C10="","",SUMIFS('Base de Costos'!$H$5:$H$504,'Base de Costos'!$C$5:$C$504,$C10,'Base de Costos'!$D$5:$D$504,"Costo indirecto fabricación")) | G10: =IF($C10="","",SUM(D10:F10)) | H10: =IF($C10="","",SUMIFS('Base de Costos'!$H$5:$H$504,'Base de Costos'!$C$5:$C$504,$C10,'Base de Costos'!$D$5:$D$504,"Gasto publicidad")+SUMIFS('Base de Costos'!$H$5:$H$504,'Base de Costos'!$C$5:$C$504,$C10,'Base de Costos'!$D$5:$D$504,"Gasto administrativo")+SUMIFS('Base de Costos'!$H$5:$H$504,'Base de Costos'!$C$5:$C$504,$C10,'Base de Costos'!$D$5:$D$504,"Otro gasto")) | I10: =IF($C10="","",IFERROR(VLOOKUP($C10,Productos!$B$5:$H$124,7,FALSE),0)) | J10: =IF($C10="","",G10+H10) | K10: =IF($C10="","",IFERROR(J10/(1-I10),0)) | L10: =IF($C10="","",K10-J10) | M10: =IF($C10="","",IF(J10=0,"Sin datos",IF(IFERROR(VLOOKUP($C10,Productos!$B$5:$H$124,4,FALSE),0)=0,"Sin precio cliente",IF(IFERROR(VLOOKUP($C10,Productos!$B$5:$H$124,4,FALSE),0)<J10,"Riesgo: cliente bajo costo",IF(K10>IFERROR(VLOOKUP($C10,Productos!$B$5:$H$124,4,FALSE),0),"Revisar: sugerido sobre cliente",IF(K10>IFERROR(VLOOKUP($C10,Productos!$B$5:$H$124,5,FALSE),0),"Sobre competencia","Competitivo"))))))
C11: =IF(Productos!B11="","",Productos!B11) | D11: =IF($C11="","",SUMIFS('Base de Costos'!$H$5:$H$504,'Base de Costos'!$C$5:$C$504,$C11,'Base de Costos'!$D$5:$D$504,"Materia prima")) | E11: =IF($C11="","",SUMIFS('Base de Costos'!$H$5:$H$504,'Base de Costos'!$C$5:$C$504,$C11,'Base de Costos'!$D$5:$D$504,"Mano de obra")) | F11: =IF($C11="","",SUMIFS('Base de Costos'!$H$5:$H$504,'Base de Costos'!$C$5:$C$504,$C11,'Base de Costos'!$D$5:$D$504,"Costo indirecto fabricación")) | G11: =IF($C11="","",SUM(D11:F11)) | H11: =IF($C11="","",SUMIFS('Base de Costos'!$H$5:$H$504,'Base de Costos'!$C$5:$C$504,$C11,'Base de Costos'!$D$5:$D$504,"Gasto publicidad")+SUMIFS('Base de Costos'!$H$5:$H$504,'Base de Costos'!$C$5:$C$504,$C11,'Base de Costos'!$D$5:$D$504,"Gasto administrativo")+SUMIFS('Base de Costos'!$H$5:$H$504,'Base de Costos'!$C$5:$C$504,$C11,'Base de Costos'!$D$5:$D$504,"Otro gasto")) | I11: =IF($C11="","",IFERROR(VLOOKUP($C11,Productos!$B$5:$H$124,7,FALSE),0)) | J11: =IF($C11="","",G11+H11) | K11: =IF($C11="","",IFERROR(J11/(1-I11),0)) | L11: =IF($C11="","",K11-J11) | M11: =IF($C11="","",IF(J11=0,"Sin datos",IF(IFERROR(VLOOKUP($C11,Productos!$B$5:$H$124,4,FALSE),0)=0,"Sin precio cliente",IF(IFERROR(VLOOKUP($C11,Productos!$B$5:$H$124,4,FALSE),0)<J11,"Riesgo: cliente bajo costo",IF(K11>IFERROR(VLOOKUP($C11,Productos!$B$5:$H$124,4,FALSE),0),"Revisar: sugerido sobre cliente",IF(K11>IFERROR(VLOOKUP($C11,Productos!$B$5:$H$124,5,FALSE),0),"Sobre competencia","Competitivo"))))))
C12: =IF(Productos!B12="","",Productos!B12) | D12: =IF($C12="","",SUMIFS('Base de Costos'!$H$5:$H$504,'Base de Costos'!$C$5:$C$504,$C12,'Base de Costos'!$D$5:$D$504,"Materia prima")) | E12: =IF($C12="","",SUMIFS('Base de Costos'!$H$5:$H$504,'Base de Costos'!$C$5:$C$504,$C12,'Base de Costos'!$D$5:$D$504,"Mano de obra")) | F12: =IF($C12="","",SUMIFS('Base de Costos'!$H$5:$H$504,'Base de Costos'!$C$5:$C$504,$C12,'Base de Costos'!$D$5:$D$504,"Costo indirecto fabricación")) | G12: =IF($C12="","",SUM(D12:F12)) | H12: =IF($C12="","",SUMIFS('Base de Costos'!$H$5:$H$504,'Base de Costos'!$C$5:$C$504,$C12,'Base de Costos'!$D$5:$D$504,"Gasto publicidad")+SUMIFS('Base de Costos'!$H$5:$H$504,'Base de Costos'!$C$5:$C$504,$C12,'Base de Costos'!$D$5:$D$504,"Gasto administrativo")+SUMIFS('Base de Costos'!$H$5:$H$504,'Base de Costos'!$C$5:$C$504,$C12,'Base de Costos'!$D$5:$D$504,"Otro gasto")) | I12: =IF($C12="","",IFERROR(VLOOKUP($C12,Productos!$B$5:$H$124,7,FALSE),0)) | J12: =IF($C12="","",G12+H12) | K12: =IF($C12="","",IFERROR(J12/(1-I12),0)) | L12: =IF($C12="","",K12-J12) | M12: =IF($C12="","",IF(J12=0,"Sin datos",IF(IFERROR(VLOOKUP($C12,Productos!$B$5:$H$124,4,FALSE),0)=0,"Sin precio cliente",IF(IFERROR(VLOOKUP($C12,Productos!$B$5:$H$124,4,FALSE),0)<J12,"Riesgo: cliente bajo costo",IF(K12>IFERROR(VLOOKUP($C12,Productos!$B$5:$H$124,4,FALSE),0),"Revisar: sugerido sobre cliente",IF(K12>IFERROR(VLOOKUP($C12,Productos!$B$5:$H$124,5,FALSE),0),"Sobre competencia","Competitivo"))))))
C13: =IF(Productos!B13="","",Productos!B13) | D13: =IF($C13="","",SUMIFS('Base de Costos'!$H$5:$H$504,'Base de Costos'!$C$5:$C$504,$C13,'Base de Costos'!$D$5:$D$504,"Materia prima")) | E13: =IF($C13="","",SUMIFS('Base de Costos'!$H$5:$H$504,'Base de Costos'!$C$5:$C$504,$C13,'Base de Costos'!$D$5:$D$504,"Mano de obra")) | F13: =IF($C13="","",SUMIFS('Base de Costos'!$H$5:$H$504,'Base de Costos'!$C$5:$C$504,$C13,'Base de Costos'!$D$5:$D$504,"Costo indirecto fabricación")) | G13: =IF($C13="","",SUM(D13:F13)) | H13: =IF($C13="","",SUMIFS('Base de Costos'!$H$5:$H$504,'Base de Costos'!$C$5:$C$504,$C13,'Base de Costos'!$D$5:$D$504,"Gasto publicidad")+SUMIFS('Base de Costos'!$H$5:$H$504,'Base de Costos'!$C$5:$C$504,$C13,'Base de Costos'!$D$5:$D$504,"Gasto administrativo")+SUMIFS('Base de Costos'!$H$5:$H$504,'Base de Costos'!$C$5:$C$504,$C13,'Base de Costos'!$D$5:$D$504,"Otro gasto")) | I13: =IF($C13="","",IFERROR(VLOOKUP($C13,Productos!$B$5:$H$124,7,FALSE),0)) | J13: =IF($C13="","",G13+H13) | K13: =IF($C13="","",IFERROR(J13/(1-I13),0)) | L13: =IF($C13="","",K13-J13) | M13: =IF($C13="","",IF(J13=0,"Sin datos",IF(IFERROR(VLOOKUP($C13,Productos!$B$5:$H$124,4,FALSE),0)=0,"Sin precio cliente",IF(IFERROR(VLOOKUP($C13,Productos!$B$5:$H$124,4,FALSE),0)<J13,"Riesgo: cliente bajo costo",IF(K13>IFERROR(VLOOKUP($C13,Productos!$B$5:$H$124,4,FALSE),0),"Revisar: sugerido sobre cliente",IF(K13>IFERROR(VLOOKUP($C13,Productos!$B$5:$H$124,5,FALSE),0),"Sobre competencia","Competitivo"))))))
C14: =IF(Productos!B14="","",Productos!B14) | D14: =IF($C14="","",SUMIFS('Base de Costos'!$H$5:$H$504,'Base de Costos'!$C$5:$C$504,$C14,'Base de Costos'!$D$5:$D$504,"Materia prima")) | E14: =IF($C14="","",SUMIFS('Base de Costos'!$H$5:$H$504,'Base de Costos'!$C$5:$C$504,$C14,'Base de Costos'!$D$5:$D$504,"Mano de obra")) | F14: =IF($C14="","",SUMIFS('Base de Costos'!$H$5:$H$504,'Base de Costos'!$C$5:$C$504,$C14,'Base de Costos'!$D$5:$D$504,"Costo indirecto fabricación")) | G14: =IF($C14="","",SUM(D14:F14)) | H14: =IF($C14="","",SUMIFS('Base de Costos'!$H$5:$H$504,'Base de Costos'!$C$5:$C$504,$C14,'Base de Costos'!$D$5:$D$504,"Gasto publicidad")+SUMIFS('Base de Costos'!$H$5:$H$504,'Base de Costos'!$C$5:$C$504,$C14,'Base de Costos'!$D$5:$D$504,"Gasto administrativo")+SUMIFS('Base de Costos'!$H$5:$H$504,'Base de Costos'!$C$5:$C$504,$C14,'Base de Costos'!$D$5:$D$504,"Otro gasto")) | I14: =IF($C14="","",IFERROR(VLOOKUP($C14,Productos!$B$5:$H$124,7,FALSE),0)) | J14: =IF($C14="","",G14+H14) | K14: =IF($C14="","",IFERROR(J14/(1-I14),0)) | L14: =IF($C14="","",K14-J14) | M14: =IF($C14="","",IF(J14=0,"Sin datos",IF(IFERROR(VLOOKUP($C14,Productos!$B$5:$H$124,4,FALSE),0)=0,"Sin precio cliente",IF(IFERROR(VLOOKUP($C14,Productos!$B$5:$H$124,4,FALSE),0)<J14,"Riesgo: cliente bajo costo",IF(K14>IFERROR(VLOOKUP($C14,Productos!$B$5:$H$124,4,FALSE),0),"Revisar: sugerido sobre cliente",IF(K14>IFERROR(VLOOKUP($C14,Productos!$B$5:$H$124,5,FALSE),0),"Sobre competencia","Competitivo"))))))
C15: =IF(Productos!B15="","",Productos!B15) | D15: =IF($C15="","",SUMIFS('Base de Costos'!$H$5:$H$504,'Base de Costos'!$C$5:$C$504,$C15,'Base de Costos'!$D$5:$D$504,"Materia prima")) | E15: =IF($C15="","",SUMIFS('Base de Costos'!$H$5:$H$504,'Base de Costos'!$C$5:$C$504,$C15,'Base de Costos'!$D$5:$D$504,"Mano de obra")) | F15: =IF($C15="","",SUMIFS('Base de Costos'!$H$5:$H$504,'Base de Costos'!$C$5:$C$504,$C15,'Base de Costos'!$D$5:$D$504,"Costo indirecto fabricación")) | G15: =IF($C15="","",SUM(D15:F15)) | H15: =IF($C15="","",SUMIFS('Base de Costos'!$H$5:$H$504,'Base de Costos'!$C$5:$C$504,$C15,'Base de Costos'!$D$5:$D$504,"Gasto publicidad")+SUMIFS('Base de Costos'!$H$5:$H$504,'Base de Costos'!$C$5:$C$504,$C15,'Base de Costos'!$D$5:$D$504,"Gasto administrativo")+SUMIFS('Base de Costos'!$H$5:$H$504,'Base de Costos'!$C$5:$C$504,$C15,'Base de Costos'!$D$5:$D$504,"Otro gasto")) | I15: =IF($C15="","",IFERROR(VLOOKUP($C15,Productos!$B$5:$H$124,7,FALSE),0)) | J15: =IF($C15="","",G15+H15) | K15: =IF($C15="","",IFERROR(J15/(1-I15),0)) | L15: =IF($C15="","",K15-J15) | M15: =IF($C15="","",IF(J15=0,"Sin datos",IF(IFERROR(VLOOKUP($C15,Productos!$B$5:$H$124,4,FALSE),0)=0,"Sin precio cliente",IF(IFERROR(VLOOKUP($C15,Productos!$B$5:$H$124,4,FALSE),0)<J15,"Riesgo: cliente bajo costo",IF(K15>IFERROR(VLOOKUP($C15,Productos!$B$5:$H$124,4,FALSE),0),"Revisar: sugerido sobre cliente",IF(K15>IFERROR(VLOOKUP($C15,Productos!$B$5:$H$124,5,FALSE),0),"Sobre competencia","Competitivo"))))))
C16: =IF(Productos!B16="","",Productos!B16) | D16: =IF($C16="","",SUMIFS('Base de Costos'!$H$5:$H$504,'Base de Costos'!$C$5:$C$504,$C16,'Base de Costos'!$D$5:$D$504,"Materia prima")) | E16: =IF($C16="","",SUMIFS('Base de Costos'!$H$5:$H$504,'Base de Costos'!$C$5:$C$504,$C16,'Base de Costos'!$D$5:$D$504,"Mano de obra")) | F16: =IF($C16="","",SUMIFS('Base de Costos'!$H$5:$H$504,'Base de Costos'!$C$5:$C$504,$C16,'Base de Costos'!$D$5:$D$504,"Costo indirecto fabricación")) | G16: =IF($C16="","",SUM(D16:F16)) | H16: =IF($C16="","",SUMIFS('Base de Costos'!$H$5:$H$504,'Base de Costos'!$C$5:$C$504,$C16,'Base de Costos'!$D$5:$D$504,"Gasto publicidad")+SUMIFS('Base de Costos'!$H$5:$H$504,'Base de Costos'!$C$5:$C$504,$C16,'Base de Costos'!$D$5:$D$504,"Gasto administrativo")+SUMIFS('Base de Costos'!$H$5:$H$504,'Base de Costos'!$C$5:$C$504,$C16,'Base de Costos'!$D$5:$D$504,"Otro gasto")) | I16: =IF($C16="","",IFERROR(VLOOKUP($C16,Productos!$B$5:$H$124,7,FALSE),0)) | J16: =IF($C16="","",G16+H16) | K16: =IF($C16="","",IFERROR(J16/(1-I16),0)) | L16: =IF($C16="","",K16-J16) | M16: =IF($C16="","",IF(J16=0,"Sin datos",IF(IFERROR(VLOOKUP($C16,Productos!$B$5:$H$124,4,FALSE),0)=0,"Sin precio cliente",IF(IFERROR(VLOOKUP($C16,Productos!$B$5:$H$124,4,FALSE),0)<J16,"Riesgo: cliente bajo costo",IF(K16>IFERROR(VLOOKUP($C16,Productos!$B$5:$H$124,4,FALSE),0),"Revisar: sugerido sobre cliente",IF(K16>IFERROR(VLOOKUP($C16,Productos!$B$5:$H$124,5,FALSE),0),"Sobre competencia","Competitivo"))))))
C17: =IF(Productos!B17="","",Productos!B17) | D17: =IF($C17="","",SUMIFS('Base de Costos'!$H$5:$H$504,'Base de Costos'!$C$5:$C$504,$C17,'Base de Costos'!$D$5:$D$504,"Materia prima")) | E17: =IF($C17="","",SUMIFS('Base de Costos'!$H$5:$H$504,'Base de Costos'!$C$5:$C$504,$C17,'Base de Costos'!$D$5:$D$504,"Mano de obra")) | F17: =IF($C17="","",SUMIFS('Base de Costos'!$H$5:$H$504,'Base de Costos'!$C$5:$C$504,$C17,'Base de Costos'!$D$5:$D$504,"Costo indirecto fabricación")) | G17: =IF($C17="","",SUM(D17:F17)) | H17: =IF($C17="","",SUMIFS('Base de Costos'!$H$5:$H$504,'Base de Costos'!$C$5:$C$504,$C17,'Base de Costos'!$D$5:$D$504,"Gasto publicidad")+SUMIFS('Base de Costos'!$H$5:$H$504,'Base de Costos'!$C$5:$C$504,$C17,'Base de Costos'!$D$5:$D$504,"Gasto administrativo")+SUMIFS('Base de Costos'!$H$5:$H$504,'Base de Costos'!$C$5:$C$504,$C17,'Base de Costos'!$D$5:$D$504,"Otro gasto")) | I17: =IF($C17="","",IFERROR(VLOOKUP($C17,Productos!$B$5:$H$124,7,FALSE),0)) | J17: =IF($C17="","",G17+H17) | K17: =IF($C17="","",IFERROR(J17/(1-I17),0)) | L17: =IF($C17="","",K17-J17) | M17: =IF($C17="","",IF(J17=0,"Sin datos",IF(IFERROR(VLOOKUP($C17,Productos!$B$5:$H$124,4,FALSE),0)=0,"Sin precio cliente",IF(IFERROR(VLOOKUP($C17,Productos!$B$5:$H$124,4,FALSE),0)<J17,"Riesgo: cliente bajo costo",IF(K17>IFERROR(VLOOKUP($C17,Productos!$B$5:$H$124,4,FALSE),0),"Revisar: sugerido sobre cliente",IF(K17>IFERROR(VLOOKUP($C17,Productos!$B$5:$H$124,5,FALSE),0),"Sobre competencia","Competitivo"))))))
... C124: =IF(Productos!B124="","",Productos!B124) | D124: =IF($C124="","",SUMIFS('Base de Costos'!$H$5:$H$504,'Base de Costos'!$C$5:$C$504,$C124,'Base de Costos'!$D$5:$D$504,"Materia prima")) | E124: =IF($C124="","",SUMIFS('Base de Costos'!$H$5:$H$504,'Base de Costos'!$C$5:$C$504,$C124,'Base de Costos'!$D$5:$D$504,"Mano de obra")) | F124: =IF($C124="","",SUMIFS('Base de Costos'!$H$5:$H$504,'Base de Costos'!$C$5:$C$504,$C124,'Base de Costos'!$D$5:$D$504,"Costo indirecto fabricación")) | G124: =IF($C124="","",SUM(D124:F124)) | H124: =IF($C124="","",SUMIFS('Base de Costos'!$H$5:$H$504,'Base de Costos'!$C$5:$C$504,$C124,'Base de Costos'!$D$5:$D$504,"Gasto publicidad")+SUMIFS('Base de Costos'!$H$5:$H$504,'Base de Costos'!$C$5:$C$504,$C124,'Base de Costos'!$D$5:$D$504,"Gasto administrativo")+SUMIFS('Base de Costos'!$H$5:$H$504,'Base de Costos'!$C$5:$C$504,$C124,'Base de Costos'!$D$5:$D$504,"Otro gasto")) | I124: =IF($C124="","",IFERROR(VLOOKUP($C124,Productos!$B$5:$H$124,7,FALSE),0)) | J124: =IF($C124="","",G124+H124) | K124: =IF($C124="","",IFERROR(J124/(1-I124),0)) | L124: =IF($C124="","",K124-J124) | M124: =IF($C124="","",IF(J124=0,"Sin datos",IF(IFERROR(VLOOKUP($C124,Productos!$B$5:$H$124,4,FALSE),0)=0,"Sin precio cliente",IF(IFERROR(VLOOKUP($C124,Productos!$B$5:$H$124,4,FALSE),0)<J124,"Riesgo: cliente bajo costo",IF(K124>IFERROR(VLOOKUP($C124,Productos!$B$5:$H$124,4,FALSE),0),"Revisar: sugerido sobre cliente",IF(K124>IFERROR(VLOOKUP($C124,Productos!$B$5:$H$124,5,FALSE),0),"Sobre competencia","Competitivo"))))))
