Workbook

Sheet Inicio
B1: PLANTILLA FLUJO DE CAJA PYME 12 MESES
B2: Proyecta, entiende y controla tu caja mensual sin tocar fórmulas.
B3: Paso | C3: Sección | D3: Descripción
B4: 1 | C4: Completa las hojas verdes | D4: Ventas, inversión, costos, impuestos, inventario y financiamiento.
B5: 2 | C5: El flujo se arma solo | D5: La hoja Flujo de Caja calcula ingresos, egresos, saldos y alertas.
B6: 3 | C6: Revisa el dashboard | D6: Verás saldo final, caja mínima, inversión inicial, meses negativos y punto de equilibrio.
B7: 4 | C7: Evalúa escenarios | D7: Compara una visión conservadora, esperada y optimista antes de tomar decisiones.
B8: Herramienta para anticipar déficits de caja, controlar egresos y saber cuánto capital necesita la PYME para operar durante 12 meses.

Sheet Dashboard
C1: DASHBOARD EJECUTIVO
C2: Vista rápida para decidir: caja final, saldo más bajo, egresos, inversión, reserva y alertas.
C3: Saldo final anual | E3: Saldo más bajo | G3: Ventas totales | I3: Total egresos
C4: ='Flujo de Caja'!N21 -> 2265420.2 | E4: =MIN('Flujo de Caja'!C21:N21) -> 2265420.2 | G4: =SUM('Flujo de Caja'!C6:N6) -> 1500000 | I4: =SUM('Flujo de Caja'!C15:N15) -> 8234579.8
C5: Meses negativos | E5: Punto equilibrio unidades | G5: Inversión inicial | I5: Reserva recomendada
C6: =COUNTIF('Flujo de Caja'!C21:N21,"<0") -> 0 | E6: ='Punto Equilibrio'!C8 -> 1.7 | G6: ='Inversion Inicial'!Q15 -> 7150000 | I6: ='Punto Equilibrio'!C10 -> 20000
C8: Mes | D8: Ingresos | E8: Egresos | F8: Saldo final
C9: Ene | D9: ='Flujo de Caja'!C$6 -> 1500000 | E9: ='Flujo de Caja'!C$15 -> 8115000 | F9: ='Flujo de Caja'!C$21 -> 2385000
C10: Feb | D10: ='Flujo de Caja'!D$6 -> 0 | E10: ='Flujo de Caja'!D$15 -> 119579.83 | F10: ='Flujo de Caja'!D$21 -> 2265420.2
C11: Mar | D11: ='Flujo de Caja'!E$6 -> 0 | E11: ='Flujo de Caja'!E$15 -> 0 | F11: ='Flujo de Caja'!E$21 -> 2265420.2
C12: Abr | D12: ='Flujo de Caja'!F$6 -> 0 | E12: ='Flujo de Caja'!F$15 -> 0 | F12: ='Flujo de Caja'!F$21 -> 2265420.2
C13: May | D13: ='Flujo de Caja'!G$6 -> 0 | E13: ='Flujo de Caja'!G$15 -> 0 | F13: ='Flujo de Caja'!G$21 -> 2265420.2
C14: Jun | D14: ='Flujo de Caja'!H$6 -> 0 | E14: ='Flujo de Caja'!H$15 -> 0 | F14: ='Flujo de Caja'!H$21 -> 2265420.2
C15: Jul | D15: ='Flujo de Caja'!I$6 -> 0 | E15: ='Flujo de Caja'!I$15 -> 0 | F15: ='Flujo de Caja'!I$21 -> 2265420.2
C16: Ago | D16: ='Flujo de Caja'!J$6 -> 0 | E16: ='Flujo de Caja'!J$15 -> 0 | F16: ='Flujo de Caja'!J$21 -> 2265420.2
C17: Sep | D17: ='Flujo de Caja'!K$6 -> 0 | E17: ='Flujo de Caja'!K$15 -> 0 | F17: ='Flujo de Caja'!K$21 -> 2265420.2
C18: Oct | D18: ='Flujo de Caja'!L$6 -> 0 | E18: ='Flujo de Caja'!L$15 -> 0 | F18: ='Flujo de Caja'!L$21 -> 2265420.2
C19: Nov | D19: ='Flujo de Caja'!M$6 -> 0 | E19: ='Flujo de Caja'!M$15 -> 0 | F19: ='Flujo de Caja'!M$21 -> 2265420.2
C20: Dic | D20: ='Flujo de Caja'!N$6 -> 0 | E20: ='Flujo de Caja'!N$15 -> 0 | F20: ='Flujo de Caja'!N$21 -> 2265420.2

Sheet Supuestos
B1: SUPUESTOS GENERALES
B2: Edita estos valores para adaptar la plantilla a cada negocio.
B3: Dato | C3: Valor editable | D3: Uso dentro del modelo
B4: Nombre de la empresa | C4: PYME ejemplo | D4: Se muestra en reportes y dashboard.
B5: Moneda | C5: CLP | D5: Formato visual de los montos.
B6: Año de proyección | C6: 2026 | D6: Referencia general de la plantilla.
B7: IVA | C7: 0.19 | D7: Cálculo simple de IVA ventas/compras.
B8: Impuesto mensual sobre ventas | C8: 0.01 | D8: Estimación mensual de impuesto sobre ventas.
B9: Reserva objetivo en meses de costos fijos | C9: 2 | D9: Reserva sugerida para enfrentar imprevistos.
B10: Capital inicial disponible | C10: 9000000 | D10: Caja disponible al comenzar el flujo.
B11: Stock mínimo deseado | C11: 20 | D11: Alerta básica de inventario.
B12: Crecimiento esperado de ventas | C12: 0.05 | D12: Referencia para escenarios.
B13: Promesa comercial | C13: Proyecta, entiende y controla tu caja mensual sin tocar fórmulas. | D13: Texto visible en Inicio.
C15: Remplaze los valores

Sheet Inversion Inicial
C1: INVERSIÓN INICIAL
C2: Completa los desembolsos necesarios antes o durante el inicio de operaciones.
C3: Categoría | D3: Ítem | E3: Ene | F3: Feb | G3: Mar | H3: Abr | I3: May | J3: Jun | K3: Jul | L3: Ago | M3: Sep | N3: Oct | O3: Nov | P3: Dic | Q3: Total
C4: Equipamiento | D4: Computadores / POS | E4: 850000 | F4: 0 | G4: 0 | H4: 0 | I4: 0 | J4: 0 | K4: 0 | L4: 0 | M4: 0 | N4: 0 | O4: 0 | P4: 0 | Q4: =SUM(E4:P4) -> 850000
C5: Equipamiento | D5: Maquinaria / herramientas | E5: 1200000 | F5: 0 | G5: 0 | H5: 0 | I5: 0 | J5: 0 | K5: 0 | L5: 0 | M5: 0 | N5: 0 | O5: 0 | P5: 0 | Q5: =SUM(E5:P5) -> 1200000
C6: Muebles | D6: Estanterías / escritorios | E6: 650000 | F6: 0 | G6: 0 | H6: 0 | I6: 0 | J6: 0 | K6: 0 | L6: 0 | M6: 0 | N6: 0 | O6: 0 | P6: 0 | Q6: =SUM(E6:P6) -> 650000
C7: Infraestructura | D7: Habilitación del local | E7: 1800000 | F7: 0 | G7: 0 | H7: 0 | I7: 0 | J7: 0 | K7: 0 | L7: 0 | M7: 0 | N7: 0 | O7: 0 | P7: 0 | Q7: =SUM(E7:P7) -> 1800000
C8: Infraestructura | D8: Reparaciones | E8: 500000 | F8: 0 | G8: 0 | H8: 0 | I8: 0 | J8: 0 | K8: 0 | L8: 0 | M8: 0 | N8: 0 | O8: 0 | P8: 0 | Q8: =SUM(E8:P8) -> 500000
C9: Legal | D9: Constitución de empresa | E9: 250000 | F9: 0 | G9: 0 | H9: 0 | I9: 0 | J9: 0 | K9: 0 | L9: 0 | M9: 0 | N9: 0 | O9: 0 | P9: 0 | Q9: =SUM(E9:P9) -> 250000
C10: Legal | D10: Patente / permisos | E10: 300000 | F10: 0 | G10: 0 | H10: 0 | I10: 0 | J10: 0 | K10: 0 | L10: 0 | M10: 0 | N10: 0 | O10: 0 | P10: 0 | Q10: =SUM(E10:P10) -> 300000
C11: Garantías | D11: Garantía de arriendo | E11: 900000 | F11: 0 | G11: 0 | H11: 0 | I11: 0 | J11: 0 | K11: 0 | L11: 0 | M11: 0 | N11: 0 | O11: 0 | P11: 0 | Q11: =SUM(E11:P11) -> 900000
C12: Marketing inicial | D12: Diseño, lanzamiento y publicidad | E12: 400000 | F12: 0 | G12: 0 | H12: 0 | I12: 0 | J12: 0 | K12: 0 | L12: 0 | M12: 0 | N12: 0 | O12: 0 | P12: 0 | Q12: =SUM(E12:P12) -> 400000
C13: Otros | D13: Imprevistos iniciales | E13: 300000 | F13: 0 | G13: 0 | H13: 0 | I13: 0 | J13: 0 | K13: 0 | L13: 0 | M13: 0 | N13: 0 | O13: 0 | P13: 0 | Q13: =SUM(E13:P13) -> 300000
C14: Remplaze con sus categortias y Ítem
C15: TOTAL INVERSIÓN INICIAL | E15: =SUM(E4:E13) -> 7150000 | F15: =SUM(F4:F13) -> 0 | G15: =SUM(G4:G13) -> 0 | H15: =SUM(H4:H13) -> 0 | I15: =SUM(I4:I13) -> 0 | J15: =SUM(J4:J13) -> 0 | K15: =SUM(K4:K13) -> 0 | L15: =SUM(L4:L13) -> 0 | ... Q15: =SUM(Q4:Q13) -> 7150000

Sheet Ventas
B1: VENTAS / INGRESOS
B2: Completa precio promedio y cantidades mensuales vendidas.
B3: Producto / Servicio | C3: Precio prom. | D3: Ene | E3: Feb | F3: Mar | G3: Abr | H3: May | I3: Jun | J3: Jul | K3: Ago | L3: Sep | M3: Oct | N3: Nov | O3: Dic | P3: Total ingresos
B4: Producto / servicio 1 | C4: 15000 | D4: 100 | P4: =C4*SUM(D4:O4) -> 1500000
B5: Producto / servicio 2 | P5: =C5*SUM(D5:O5) -> 0
B6: Producto / servicio 3 | P6: =C6*SUM(D6:O6) -> 0
B7: Servicio recurrente | P7: =C7*SUM(D7:O7) -> 0
B8: Otro ingreso | P8: =C8*SUM(D8:O8) -> 0
B9: Remplaze con sus productos
B10: TOTAL VENTAS NORMALES | D10: =SUMPRODUCT($C$4:$C$8,D$4:D$8) -> 1500000 | E10: =SUMPRODUCT($C$4:$C$8,E$4:E$8) -> 0 | F10: =SUMPRODUCT($C$4:$C$8,F$4:F$8) -> 0 | G10: =SUMPRODUCT($C$4:$C$8,G$4:G$8) -> 0 | H10: =SUMPRODUCT($C$4:$C$8,H$4:H$8) -> 0 | I10: =SUMPRODUCT($C$4:$C$8,I$4:I$8) -> 0 | J10: =SUMPRODUCT($C$4:$C$8,J$4:J$8) -> 0 | K10: =SUMPRODUCT($C$4:$C$8,K$4:K$8) -> 0 | ... O10: =SUMPRODUCT($C$4:$C$8,O$4:O$8) -> 0 | P10: =SUM(P4:P8) -> 1500000
B12: Promociones / descuentos / ingresos extraordinarios
B13: Ingreso por promociones | D13: 0 | E13: 0 | F13: 0 | G13: 0 | H13: 0 | I13: 0 | J13: 0 | K13: 0 | L13: 0 | M13: 0 | N13: 0 | O13: 0 | P13: =SUM(D13:O13) -> 0
B15: TOTAL INGRESOS | D15: =D10+D13 -> 1500000 | E15: =E10+E13 -> 0 | F15: =F10+F13 -> 0 | G15: =G10+G13 -> 0 | H15: =H10+H13 -> 0 | I15: =I10+I13 -> 0 | J15: =J10+J13 -> 0 | K15: =K10+K13 -> 0 | ... P15: =P10+P13 -> 1500000

Sheet Costos Variables
B1: COSTOS VARIABLES / COMPRAS
B2: Costos que cambian según las ventas, compras o producción.
B3: Producto / costo directo | C3: Costo unit. | D3: Ene | E3: Feb | F3: Mar | G3: Abr | H3: May | I3: Jun | J3: Jul | K3: Ago | L3: Sep | M3: Oct | N3: Nov | O3: Dic | P3: Total
B4: Compra producto 1 | C4: 8000 | D4: =Ventas!D4 -> 100 | E4: =Ventas!E4 -> 0 | F4: =Ventas!F4 -> 0 | G4: =Ventas!G4 -> 0 | H4: =Ventas!H4 -> 0 | I4: =Ventas!I4 -> 0 | J4: =Ventas!J4 -> 0 | K4: =Ventas!K4 -> 0 | ... O4: =Ventas!O4 -> 0 | P4: =C4*SUM(D4:O4) -> 800000
B5: Compra producto 2 | C5: 14000 | D5: =Ventas!D5 -> 0 | E5: =Ventas!E5 -> 0 | F5: =Ventas!F5 -> 0 | G5: =Ventas!G5 -> 0 | H5: =Ventas!H5 -> 0 | I5: =Ventas!I5 -> 0 | J5: =Ventas!J5 -> 0 | K5: =Ventas!K5 -> 0 | ... O5: =Ventas!O5 -> 0 | P5: =C5*SUM(D5:O5) -> 0
B6: Compra producto 3 | C6: 21000 | D6: =Ventas!D6 -> 0 | E6: =Ventas!E6 -> 0 | F6: =Ventas!F6 -> 0 | G6: =Ventas!G6 -> 0 | H6: =Ventas!H6 -> 0 | I6: =Ventas!I6 -> 0 | J6: =Ventas!J6 -> 0 | K6: =Ventas!K6 -> 0 | ... O6: =Ventas!O6 -> 0 | P6: =C6*SUM(D6:O6) -> 0
B7: Insumo directo servicio(ejemplo) | C7: 15000 | D7: =Ventas!D7 -> 0 | E7: =Ventas!E7 -> 0 | F7: =Ventas!F7 -> 0 | G7: =Ventas!G7 -> 0 | H7: =Ventas!H7 -> 0 | I7: =Ventas!I7 -> 0 | J7: =Ventas!J7 -> 0 | K7: =Ventas!K7 -> 0 | ... O7: =Ventas!O7 -> 0 | P7: =C7*SUM(D7:O7) -> 0
B8: Otro costo variable | C8: 3000 | D8: =Ventas!D8 -> 0 | E8: =Ventas!E8 -> 0 | F8: =Ventas!F8 -> 0 | G8: =Ventas!G8 -> 0 | H8: =Ventas!H8 -> 0 | I8: =Ventas!I8 -> 0 | J8: =Ventas!J8 -> 0 | K8: =Ventas!K8 -> 0 | ... O8: =Ventas!O8 -> 0 | P8: =C8*SUM(D8:O8) -> 0
G9: No modificar esta tabla
B10: TOTAL COMPRAS / COSTOS DIRECTOS | D10: =SUMPRODUCT($C$4:$C$8,D$4:D$8) -> 800000 | E10: =SUMPRODUCT($C$4:$C$8,E$4:E$8) -> 0 | F10: =SUMPRODUCT($C$4:$C$8,F$4:F$8) -> 0 | G10: =SUMPRODUCT($C$4:$C$8,G$4:G$8) -> 0 | H10: =SUMPRODUCT($C$4:$C$8,H$4:H$8) -> 0 | I10: =SUMPRODUCT($C$4:$C$8,I$4:I$8) -> 0 | J10: =SUMPRODUCT($C$4:$C$8,J$4:J$8) -> 0 | K10: =SUMPRODUCT($C$4:$C$8,K$4:K$8) -> 0 | ... O10: =SUMPRODUCT($C$4:$C$8,O$4:O$8) -> 0 | P10: =SUM(P4:P8) -> 800000
B12: Otros costos variables
B13: Comisión sobre ventas(ejemplo) | C13: 0.03 | D13: =Ventas!D$15*$C$13 -> 45000 | E13: =Ventas!E$15*$C$13 -> 0 | F13: =Ventas!F$15*$C$13 -> 0 | G13: =Ventas!G$15*$C$13 -> 0 | H13: =Ventas!H$15*$C$13 -> 0 | I13: =Ventas!I$15*$C$13 -> 0 | J13: =Ventas!J$15*$C$13 -> 0 | K13: =Ventas!K$15*$C$13 -> 0 | ... O13: =Ventas!O$15*$C$13 -> 0 | P13: =SUM(D13:O13) -> 45000
B14: Embalaje(ejemplo) | D14: 0 | E14: 0 | F14: 0 | G14: 0 | H14: 0 | I14: 0 | J14: 0 | K14: 0 | L14: 0 | M14: 0 | N14: 0 | O14: 0 | P14: =SUM(D14:O14) -> 0
B15: Despacho / delivery (ejemplo) | D15: 0 | E15: 0 | F15: 0 | G15: 0 | H15: 0 | I15: 0 | J15: 0 | K15: 0 | L15: 0 | M15: 0 | N15: 0 | O15: 0 | P15: =SUM(D15:O15) -> 0
B16: Garantías / devoluciones (ejemplo) | D16: 0 | E16: 0 | F16: 0 | G16: 0 | H16: 0 | I16: 0 | J16: 0 | K16: 0 | L16: 0 | M16: 0 | N16: 0 | O16: 0 | P16: =SUM(D16:O16) -> 0
G17: Modificar tabla con valores y variables
B18: TOTAL COSTOS VARIABLES | D18: =D10+SUM(D13:D16) -> 845000 | E18: =E10+SUM(E13:E16) -> 0 | F18: =F10+SUM(F13:F16) -> 0 | G18: =G10+SUM(G13:G16) -> 0 | H18: =H10+SUM(H13:H16) -> 0 | I18: =I10+SUM(I13:I16) -> 0 | J18: =J10+SUM(J13:J16) -> 0 | K18: =K10+SUM(K13:K16) -> 0 | ... P18: =P10+SUM(P13:P16) -> 845000

Sheet Costos Fijos
B1: COSTOS FIJOS Y GASTOS OPERATIVOS
B2: Gastos que se pagan aunque no haya ventas.
B3: Categoría | C3: Ítem | D3: Ene | E3: Feb | F3: Mar | G3: Abr | H3: May | I3: Jun | J3: Jul | K3: Ago | L3: Sep | M3: Oct | N3: Nov | O3: Dic | P3: Total
B4: Administración | C4: Contabilidad | D4: 120000 | P4: =SUM(D4:O4) -> 120000
B5: Administración | C5: Software / sistemas | P5: =SUM(D5:O5) -> 0
B6: Operación | C6: Arriendo | P6: =SUM(D6:O6) -> 0
B7: Operación | C7: Servicios básicos | P7: =SUM(D7:O7) -> 0
B8: Operación | C8: Internet / telefonía | P8: =SUM(D8:O8) -> 0
B9: Operación | C9: Mantenimiento equipos | P9: =SUM(D9:O9) -> 0
B10: Recursos humanos | C10: Sueldos | P10: =SUM(D10:O10) -> 0
B11: Recursos humanos | C11: Cotizaciones | P11: =SUM(D11:O11) -> 0
B12: Legales | C12: Patente comercial | O12: 0 | P12: =SUM(D12:O12) -> 0
B13: Legales | C13: Permisos / licencias | P13: =SUM(D13:O13) -> 0
B14: Seguros | C14: Seguro local / equipos | P14: =SUM(D14:O14) -> 0
B15: Marketing | C15: Publicidad | P15: =SUM(D15:O15) -> 0
B16: Marketing | C16: Patrocinio / alianzas | P16: =SUM(D16:O16) -> 0
B17: Postventa | C17: Garantías fijas | P17: =SUM(D17:O17) -> 0
B18: Otros | C18: Otros gastos fijos | P18: =SUM(D18:O18) -> 0
B19: Remplaze con sus categortias y Ítem | H19: Remplaze con sus valores
B20: TOTAL COSTOS FIJOS | D20: =SUM(D4:D18) -> 120000 | E20: =SUM(E4:E18) -> 0 | F20: =SUM(F4:F18) -> 0 | G20: =SUM(G4:G18) -> 0 | H20: =SUM(H4:H18) -> 0 | I20: =SUM(I4:I18) -> 0 | J20: =SUM(J4:J18) -> 0 | K20: =SUM(K4:K18) -> 0 | ... P20: =SUM(P4:P18) -> 120000

Sheet Impuestos
B1: IMPUESTOS Y OBLIGACIONES
B2: Cálculo con desfase mensual: IVA e impuesto mensual se pagan al mes siguiente. IMPORTANTE: los precios de Ventas y Costos Variables se asumen CON IVA incluido, por eso el IVA se extrae como monto/(1+IVA)*IVA. No dupliques cotizaciones si ya están en Costos Fijos.
B3: Concepto | C3: Ene | D3: Feb | E3: Mar | F3: Abr | G3: May | H3: Jun | I3: Jul | J3: Ago | K3: Sep | L3: Oct | M3: Nov | N3: Dic | O3: Total
B4: IVA ventas generado | C4: =Ventas!D$15/(1+Supuestos!$C$7)*Supuestos!$C$7 -> 239495.8 | D4: =Ventas!E$15/(1+Supuestos!$C$7)*Supuestos!$C$7 -> 0 | E4: =Ventas!F$15/(1+Supuestos!$C$7)*Supuestos!$C$7 -> 0 | F4: =Ventas!G$15/(1+Supuestos!$C$7)*Supuestos!$C$7 -> 0 | G4: =Ventas!H$15/(1+Supuestos!$C$7)*Supuestos!$C$7 -> 0 | H4: =Ventas!I$15/(1+Supuestos!$C$7)*Supuestos!$C$7 -> 0 | I4: =Ventas!J$15/(1+Supuestos!$C$7)*Supuestos!$C$7 -> 0 | J4: =Ventas!K$15/(1+Supuestos!$C$7)*Supuestos!$C$7 -> 0 | ... N4: =Ventas!O$15/(1+Supuestos!$C$7)*Supuestos!$C$7 -> 0 | O4: =SUM(C4:N4) -> 239495.8
B5: IVA compras / crédito generado | C5: ='Costos Variables'!D$18/(1+Supuestos!$C$7)*Supuestos!$C$7 -> 134915.97 | D5: ='Costos Variables'!E$18/(1+Supuestos!$C$7)*Supuestos!$C$7 -> 0 | E5: ='Costos Variables'!F$18/(1+Supuestos!$C$7)*Supuestos!$C$7 -> 0 | F5: ='Costos Variables'!G$18/(1+Supuestos!$C$7)*Supuestos!$C$7 -> 0 | G5: ='Costos Variables'!H$18/(1+Supuestos!$C$7)*Supuestos!$C$7 -> 0 | H5: ='Costos Variables'!I$18/(1+Supuestos!$C$7)*Supuestos!$C$7 -> 0 | I5: ='Costos Variables'!J$18/(1+Supuestos!$C$7)*Supuestos!$C$7 -> 0 | J5: ='Costos Variables'!K$18/(1+Supuestos!$C$7)*Supuestos!$C$7 -> 0 | ... N5: ='Costos Variables'!O$18/(1+Supuestos!$C$7)*Supuestos!$C$7 -> 0 | O5: =SUM(C5:N5) -> 134915.97
B6: IVA a pagar con desfase | C6: 0 | D6: =MAX(0,C$4-C$5) -> 104579.83 | E6: =MAX(0,D$4-D$5) -> 0 | F6: =MAX(0,E$4-E$5) -> 0 | G6: =MAX(0,F$4-F$5) -> 0 | H6: =MAX(0,G$4-G$5) -> 0 | I6: =MAX(0,H$4-H$5) -> 0 | J6: =MAX(0,I$4-I$5) -> 0 | K6: =MAX(0,J$4-J$5) -> 0 | ... N6: =MAX(0,M$4-M$5) -> 0 | O6: =SUM(C6:N6) -> 104579.83
B7: Impuesto mensual sobre ventas con desfase | C7: 0 | D7: =Ventas!D$15*Supuestos!$C$8 -> 15000 | E7: =Ventas!E$15*Supuestos!$C$8 -> 0 | F7: =Ventas!F$15*Supuestos!$C$8 -> 0 | G7: =Ventas!G$15*Supuestos!$C$8 -> 0 | H7: =Ventas!H$15*Supuestos!$C$8 -> 0 | I7: =Ventas!I$15*Supuestos!$C$8 -> 0 | J7: =Ventas!J$15*Supuestos!$C$8 -> 0 | K7: =Ventas!K$15*Supuestos!$C$8 -> 0 | ... N7: =Ventas!N$15*Supuestos!$C$8 -> 0 | O7: =SUM(C7:N7) -> 15000
B8: Cotizaciones adicionales | C8: 0 | D8: 0 | E8: 0 | F8: 0 | G8: 0 | H8: 0 | I8: 0 | J8: 0 | K8: 0 | L8: 0 | M8: 0 | N8: 0 | O8: =SUM(C8:N8) -> 0
B9: Rellenar con sus variables | G9: No modificar valores
B10: TOTAL OBLIGACIONES | C10: =SUM(C6:C8) -> 0 | D10: =SUM(D6:D8) -> 119579.83 | E10: =SUM(E6:E8) -> 0 | F10: =SUM(F6:F8) -> 0 | G10: =SUM(G6:G8) -> 0 | H10: =SUM(H6:H8) -> 0 | I10: =SUM(I6:I8) -> 0 | J10: =SUM(J6:J8) -> 0 | ... O10: =SUM(O6:O8) -> 119579.83

Sheet Inventario
B1: INVENTARIO / STOCK
B2: Control referencial de stock: compras y ventas muestran total anual; stock inicial/final muestran cierre de diciembre. No modifica automáticamente el flujo de caja.
B3: Concepto | C3: Ene | D3: Feb | E3: Mar | F3: Abr | G3: May | H3: Jun | I3: Jul | J3: Ago | K3: Sep | L3: Oct | M3: Nov | N3: Dic | O3: Total / cierre
B4: Stock inicial | C4: 0 | D4: =C7 -> 20 | E4: =D7 -> 20 | F4: =E7 -> 20 | G4: =F7 -> 20 | H4: =G7 -> 20 | I4: =H7 -> 20 | J4: =I7 -> 20 | K4: =J7 -> 20 | ... N4: =M7 -> 20 | O4: =N4 -> 20
B5: Unidades compradas sugeridas | C5: =MAX(0,C6+Supuestos!$C$11-C4) -> 120 | D5: =MAX(0,D6+Supuestos!$C$11-D4) -> 0 | E5: =MAX(0,E6+Supuestos!$C$11-E4) -> 0 | F5: =MAX(0,F6+Supuestos!$C$11-F4) -> 0 | G5: =MAX(0,G6+Supuestos!$C$11-G4) -> 0 | H5: =MAX(0,H6+Supuestos!$C$11-H4) -> 0 | I5: =MAX(0,I6+Supuestos!$C$11-I4) -> 0 | J5: =MAX(0,J6+Supuestos!$C$11-J4) -> 0 | ... N5: =MAX(0,N6+Supuestos!$C$11-N4) -> 0 | O5: =SUM(C5:N5) -> 120
B6: Unidades vendidas | C6: =SUM(Ventas!D4:D8) -> 100 | D6: =SUM(Ventas!E4:E8) -> 0 | E6: =SUM(Ventas!F4:F8) -> 0 | F6: =SUM(Ventas!G4:G8) -> 0 | G6: =SUM(Ventas!H4:H8) -> 0 | H6: =SUM(Ventas!I4:I8) -> 0 | I6: =SUM(Ventas!J4:J8) -> 0 | J6: =SUM(Ventas!K4:K8) -> 0 | ... N6: =SUM(Ventas!O4:O8) -> 0 | O6: =SUM(C6:N6) -> 100
B7: Stock final | C7: =C4+C5-C6 -> 20 | D7: =D4+D5-D6 -> 20 | E7: =E4+E5-E6 -> 20 | F7: =F4+F5-F6 -> 20 | G7: =G4+G5-G6 -> 20 | H7: =H4+H5-H6 -> 20 | I7: =I4+I5-I6 -> 20 | J7: =J4+J5-J6 -> 20 | ... N7: =N4+N5-N6 -> 20 | O7: =N7 -> 20
B8: Alerta de stock | C8: =IF(C7<0,"Falta stock",IF(C7<Supuestos!$C$11,"Stock bajo","OK")) -> OK | D8: =IF(D7<0,"Falta stock",IF(D7<Supuestos!$C$11,"Stock bajo","OK")) -> OK | E8: =IF(E7<0,"Falta stock",IF(E7<Supuestos!$C$11,"Stock bajo","OK")) -> OK | F8: =IF(F7<0,"Falta stock",IF(F7<Supuestos!$C$11,"Stock bajo","OK")) -> OK | G8: =IF(G7<0,"Falta stock",IF(G7<Supuestos!$C$11,"Stock bajo","OK")) -> OK | H8: =IF(H7<0,"Falta stock",IF(H7<Supuestos!$C$11,"Stock bajo","OK")) -> OK | I8: =IF(I7<0,"Falta stock",IF(I7<Supuestos!$C$11,"Stock bajo","OK")) -> OK | J8: =IF(J7<0,"Falta stock",IF(J7<Supuestos!$C$11,"Stock bajo","OK")) -> OK | ... N8: =IF(N7<0,"Falta stock",IF(N7<Supuestos!$C$11,"Stock bajo","OK")) -> OK
F9: No modificar valores, se actualizan automaticamente

Sheet Financiamiento
B1: FINANCIAMIENTO / APORTES
B2: Capital propio, préstamos o aportes para cubrir déficits de caja.
B3: Fuente | C3: Ene | D3: Feb | E3: Mar | F3: Abr | G3: May | H3: Jun | I3: Jul | J3: Ago | K3: Sep | L3: Oct | M3: Nov | N3: Dic | O3: Total
B4: Capital inicial propio | C4: =Supuestos!$C$10 -> 9000000 | D4: 0 | E4: 0 | F4: 0 | G4: 0 | H4: 0 | I4: 0 | J4: 0 | K4: 0 | L4: 0 | M4: 0 | N4: 0 | O4: =SUM(C4:N4) -> 9000000
B5: Aporte adicional socios | C5: 0 | D5: 0 | E5: 0 | F5: 0 | G5: 0 | H5: 0 | I5: 0 | J5: 0 | K5: 0 | L5: 0 | M5: 0 | N5: 0 | O5: =SUM(C5:N5) -> 0
B6: Préstamo recibido | C6: 0 | D6: 0 | E6: 0 | F6: 0 | G6: 0 | H6: 0 | I6: 0 | J6: 0 | K6: 0 | L6: 0 | M6: 0 | N6: 0 | O6: =SUM(C6:N6) -> 0
B7: Pago de préstamo | C7: 0 | D7: 0 | E7: 0 | F7: 0 | G7: 0 | H7: 0 | I7: 0 | J7: 0 | K7: 0 | L7: 0 | M7: 0 | N7: 0 | O7: =SUM(C7:N7) -> 0
B8: Otros aportes | C8: 0 | D8: 0 | E8: 0 | F8: 0 | G8: 0 | H8: 0 | I8: 0 | J8: 0 | K8: 0 | L8: 0 | M8: 0 | N8: 0 | O8: =SUM(C8:N8) -> 0
E9: Modificar tabla según valores y variables propias
B10: FLUJO NETO FINANCIAMIENTO | C10: =C4+C5+C6-C7+C8 -> 9000000 | D10: =D4+D5+D6-D7+D8 -> 0 | E10: =E4+E5+E6-E7+E8 -> 0 | F10: =F4+F5+F6-F7+F8 -> 0 | G10: =G4+G5+G6-G7+G8 -> 0 | H10: =H4+H5+H6-H7+H8 -> 0 | I10: =I4+I5+I6-I7+I8 -> 0 | J10: =J4+J5+J6-J7+J8 -> 0 | ... O10: =O4+O5+O6-O7+O8 -> 9000000

Sheet Flujo de Caja
B1: FLUJO DE CAJA PROYECTADO - 12 MESES
B2: Resumen automático de ingresos, egresos, financiamiento, saldo final y alertas. La reserva es referencial.
B4: Concepto | C4: Ene | D4: Feb | E4: Mar | F4: Abr | G4: May | H4: Jun | I4: Jul | J4: Ago | K4: Sep | L4: Oct | M4: Nov | N4: Dic | O4: Total
B5: INGRESOS
B6: Ventas / ingresos operativos | C6: =Ventas!D$15 -> 1500000 | D6: =Ventas!E$15 -> 0 | E6: =Ventas!F$15 -> 0 | F6: =Ventas!G$15 -> 0 | G6: =Ventas!H$15 -> 0 | H6: =Ventas!I$15 -> 0 | I6: =Ventas!J$15 -> 0 | J6: =Ventas!K$15 -> 0 | ... N6: =Ventas!O$15 -> 0 | O6: =SUM(C6:N6) -> 1500000
B7: Financiamiento / aportes | C7: =Financiamiento!C$10 -> 9000000 | D7: =Financiamiento!D$10 -> 0 | E7: =Financiamiento!E$10 -> 0 | F7: =Financiamiento!F$10 -> 0 | G7: =Financiamiento!G$10 -> 0 | H7: =Financiamiento!H$10 -> 0 | I7: =Financiamiento!I$10 -> 0 | J7: =Financiamiento!J$10 -> 0 | ... N7: =Financiamiento!N$10 -> 0 | O7: =SUM(C7:N7) -> 9000000
B8: TOTAL INGRESOS | C8: =C6+C7 -> 10500000 | D8: =D6+D7 -> 0 | E8: =E6+E7 -> 0 | F8: =F6+F7 -> 0 | G8: =G6+G7 -> 0 | H8: =H6+H7 -> 0 | I8: =I6+I7 -> 0 | J8: =J6+J7 -> 0 | ... N8: =N6+N7 -> 0 | O8: =SUM(C8:N8) -> 10500000
B10: EGRESOS
B11: Inversión inicial | C11: ='Inversion Inicial'!E$15 -> 7150000 | D11: ='Inversion Inicial'!F$15 -> 0 | E11: ='Inversion Inicial'!G$15 -> 0 | F11: ='Inversion Inicial'!H$15 -> 0 | G11: ='Inversion Inicial'!I$15 -> 0 | H11: ='Inversion Inicial'!J$15 -> 0 | I11: ='Inversion Inicial'!K$15 -> 0 | J11: ='Inversion Inicial'!L$15 -> 0 | ... N11: ='Inversion Inicial'!P$15 -> 0 | O11: =SUM(C11:N11) -> 7150000
B12: Costos variables / compras | C12: ='Costos Variables'!D$18 -> 845000 | D12: ='Costos Variables'!E$18 -> 0 | E12: ='Costos Variables'!F$18 -> 0 | F12: ='Costos Variables'!G$18 -> 0 | G12: ='Costos Variables'!H$18 -> 0 | H12: ='Costos Variables'!I$18 -> 0 | I12: ='Costos Variables'!J$18 -> 0 | J12: ='Costos Variables'!K$18 -> 0 | ... N12: ='Costos Variables'!O$18 -> 0 | O12: =SUM(C12:N12) -> 845000
B13: Costos fijos | C13: ='Costos Fijos'!D$20 -> 120000 | D13: ='Costos Fijos'!E$20 -> 0 | E13: ='Costos Fijos'!F$20 -> 0 | F13: ='Costos Fijos'!G$20 -> 0 | G13: ='Costos Fijos'!H$20 -> 0 | H13: ='Costos Fijos'!I$20 -> 0 | I13: ='Costos Fijos'!J$20 -> 0 | J13: ='Costos Fijos'!K$20 -> 0 | ... N13: ='Costos Fijos'!O$20 -> 0 | O13: =SUM(C13:N13) -> 120000
B14: Impuestos y obligaciones | C14: =Impuestos!C$10 -> 0 | D14: =Impuestos!D$10 -> 119579.83 | E14: =Impuestos!E$10 -> 0 | F14: =Impuestos!F$10 -> 0 | G14: =Impuestos!G$10 -> 0 | H14: =Impuestos!H$10 -> 0 | I14: =Impuestos!I$10 -> 0 | J14: =Impuestos!J$10 -> 0 | ... N14: =Impuestos!N$10 -> 0 | O14: =SUM(C14:N14) -> 119579.83
B15: TOTAL EGRESOS | C15: =SUM(C11:C14) -> 8115000 | D15: =SUM(D11:D14) -> 119579.83 | E15: =SUM(E11:E14) -> 0 | F15: =SUM(F11:F14) -> 0 | G15: =SUM(G11:G14) -> 0 | H15: =SUM(H11:H14) -> 0 | I15: =SUM(I11:I14) -> 0 | J15: =SUM(J11:J14) -> 0 | ... N15: =SUM(N11:N14) -> 0 | O15: =SUM(C15:N15) -> 8234579.8
B17: RESULTADO
B18: Flujo neto operativo | C18: =C6-SUM(C11:C14) -> -6615000 | D18: =D6-SUM(D11:D14) -> -119579.83 | E18: =E6-SUM(E11:E14) -> 0 | F18: =F6-SUM(F11:F14) -> 0 | G18: =G6-SUM(G11:G14) -> 0 | H18: =H6-SUM(H11:H14) -> 0 | I18: =I6-SUM(I11:I14) -> 0 | J18: =J6-SUM(J11:J14) -> 0 | ... N18: =N6-SUM(N11:N14) -> 0 | O18: =SUM(C18:N18) -> -6734579.8
B19: Flujo neto total | C19: =C8-C15 -> 2385000 | D19: =D8-D15 -> -119579.83 | E19: =E8-E15 -> 0 | F19: =F8-F15 -> 0 | G19: =G8-G15 -> 0 | H19: =H8-H15 -> 0 | I19: =I8-I15 -> 0 | J19: =J8-J15 -> 0 | ... N19: =N8-N15 -> 0 | O19: =SUM(C19:N19) -> 2265420.2
B20: Saldo inicial | C20: 0 | D20: =C21 -> 2385000 | E20: =D21 -> 2265420.2 | F20: =E21 -> 2265420.2 | G20: =F21 -> 2265420.2 | H20: =G21 -> 2265420.2 | I20: =H21 -> 2265420.2 | J20: =I21 -> 2265420.2 | K20: =J21 -> 2265420.2 | ... N20: =M21 -> 2265420.2 | O20: =N20 -> 2265420.2
B21: Saldo final | C21: =C20+C19 -> 2385000 | D21: =D20+D19 -> 2265420.2 | E21: =E20+E19 -> 2265420.2 | F21: =F20+F19 -> 2265420.2 | G21: =G20+G19 -> 2265420.2 | H21: =H20+H19 -> 2265420.2 | I21: =I20+I19 -> 2265420.2 | J21: =J20+J19 -> 2265420.2 | ... N21: =N20+N19 -> 2265420.2 | O21: =N21 -> 2265420.2
B22: Reserva objetivo (ref.) | C22: ='Punto Equilibrio'!$C$10 -> 20000 | D22: ='Punto Equilibrio'!$C$10 -> 20000 | E22: ='Punto Equilibrio'!$C$10 -> 20000 | F22: ='Punto Equilibrio'!$C$10 -> 20000 | G22: ='Punto Equilibrio'!$C$10 -> 20000 | H22: ='Punto Equilibrio'!$C$10 -> 20000 | I22: ='Punto Equilibrio'!$C$10 -> 20000 | J22: ='Punto Equilibrio'!$C$10 -> 20000 | ... N22: ='Punto Equilibrio'!$C$10 -> 20000 | O22: =N22 -> 20000
B23: Saldo disponible post reserva (ref.) | C23: =C21-C22 -> 2365000 | D23: =D21-D22 -> 2245420.2 | E23: =E21-E22 -> 2245420.2 | F23: =F21-F22 -> 2245420.2 | G23: =G21-G22 -> 2245420.2 | H23: =H21-H22 -> 2245420.2 | I23: =I21-I22 -> 2245420.2 | J23: =J21-J22 -> 2245420.2 | ... N23: =N21-N22 -> 2245420.2 | O23: =N23 -> 2245420.2
B24: Alerta | C24: =IF(C21<0,"NEGATIVO",IF(C21<C22,"BAJO RESERVA","OK")) -> OK | D24: =IF(D21<0,"NEGATIVO",IF(D21<D22,"BAJO RESERVA","OK")) -> OK | E24: =IF(E21<0,"NEGATIVO",IF(E21<E22,"BAJO RESERVA","OK")) -> OK | F24: =IF(F21<0,"NEGATIVO",IF(F21<F22,"BAJO RESERVA","OK")) -> OK | G24: =IF(G21<0,"NEGATIVO",IF(G21<G22,"BAJO RESERVA","OK")) -> OK | H24: =IF(H21<0,"NEGATIVO",IF(H21<H22,"BAJO RESERVA","OK")) -> OK | I24: =IF(I21<0,"NEGATIVO",IF(I21<I22,"BAJO RESERVA","OK")) -> OK | J24: =IF(J21<0,"NEGATIVO",IF(J21<J22,"BAJO RESERVA","OK")) -> OK | ... N24: =IF(N21<0,"NEGATIVO",IF(N21<N22,"BAJO RESERVA","OK")) -> OK

Sheet Punto Equilibrio
B1: PUNTO DE EQUILIBRIO
B2: Calcula cuánto debe vender la PYME para cubrir sus costos.
B3: Concepto | C3: Resultado | D3: Interpretación
B4: Precio promedio de venta | C4: =IFERROR(SUM(Ventas!P4:P8)/SUM(Ventas!D4:O8),0)/(1+Supuestos!$C$7) -> 12605.042 | D4: Ingreso neto de IVA promedio por unidad vendida.
B5: Costo variable unitario promedio | C5: =IFERROR(SUM('Costos Variables'!P4:P8)/SUM('Costos Variables'!D4:O8),0)/(1+Supuestos!$C$7) -> 6722.6891 | D5: Costo directo neto de IVA promedio por unidad.
B6: Margen de contribución | C6: =C4-C5 -> 5882.3529 | D6: Aporte por unidad para cubrir costos fijos.
B7: Costos fijos mensuales promedio | C7: =AVERAGE('Costos Fijos'!D20:O20) -> 10000 | D7: Base mensual promedio de costos fijos.
B8: Punto de equilibrio en unidades | C8: =IFERROR(C7/C6,0) -> 1.7 | D8: Unidades mensuales necesarias para no perder ni ganar.
B9: Punto de equilibrio en ventas | C9: =C8*C4 -> 21428.571 | D9: Venta mensual mínima en dinero.
B10: Reserva recomendada | C10: =C7*Supuestos!$C$9 -> 20000 | D10: Caja sugerida = costo fijo mensual promedio x meses de reserva (Supuestos).

Sheet Escenarios
C1: ESCENARIOS
C2: Compara una visión conservadora, esperada y optimista.
C3: Variable | D3: Conservador | E3: Esperado | F3: Optimista | G3: Descripción
C4: Factor ventas | D4: 0.85 | E4: 1 | F4: 1.15 | G4: Ajusta los ingresos totales.
C5: Factor costos | D5: 1.1 | E5: 1 | F5: 0.95 | G5: Ajusta costos y egresos.
C6: Ventas ajustadas | D6: =SUM('Flujo de Caja'!C6:N6)*D4 -> 1275000 | E6: =SUM('Flujo de Caja'!C6:N6)*E4 -> 1500000 | F6: =SUM('Flujo de Caja'!C6:N6)*F4 -> 1725000 | G6: Ventas bajo cada escenario.
C7: Egresos ajustados | D7: =SUM('Flujo de Caja'!C15:N15)*D5 -> 9058037.8 | E7: =SUM('Flujo de Caja'!C15:N15)*E5 -> 8234579.8 | F7: =SUM('Flujo de Caja'!C15:N15)*F5 -> 7822850.8 | G7: Total egresos bajo cada escenario.
C8: Saldo final escenario | D8: =Supuestos!$C$10+D6-D7 -> 1216962.2 | E8: =Supuestos!$C$10+E6-E7 -> 2265420.2 | F8: =Supuestos!$C$10+F6-F7 -> 2902149.2 | G8: Caja final simulada.
C9: Resultado | D9: =IF(D8<-'Punto Equilibrio'!$C$10,"Crítico",IF(D8<0,"Riesgo alto",IF(D8<'Punto Equilibrio'!$C$10,"Revisar reserva","Viable"))) -> Viable | E9: =IF(E8<-'Punto Equilibrio'!$C$10,"Crítico",IF(E8<0,"Riesgo alto",IF(E8<'Punto Equilibrio'!$C$10,"Revisar reserva","Viable"))) -> Viable | F9: =IF(F8<-'Punto Equilibrio'!$C$10,"Crítico",IF(F8<0,"Riesgo alto",IF(F8<'Punto Equilibrio'!$C$10,"Revisar reserva","Viable"))) -> Viable | G9: Lectura ejecutiva simple.
