Workbook

Sheet Inicio
C1: BALANCE GENERAL PARA PYMES
C2: Completa activos, pasivos, patrimonio y resultado. El balance horizontal se arma automáticamente.
D4: Promesa de la plantilla
D5: Organiza las cuentas de tu PYME y genera automáticamente un Balance General horizontal, simple, visual y adaptable.
D9: Paso | E9: Hoja | F9: Qué hace
D10: 1 | E10: Configuración | F10: Completa nombre de empresa, fecha de corte y moneda. | H10: ¿Cómo usar esta plantilla?
D11: 2 | E11: Activos | F11: Registra todos los activos. El balance los agrupa automáticamente. | H11: Complete primero la hoja Configuración con los datos generales de la empresa. Luego registre la información en las hojas Activos, Pasivos, Patrimonio y Resultado Ejercicio. El Balance General y el Dashboard se completan automáticamente con la información ingresada, por lo que no es necesario escribir datos manualmente en esas hojas.
D12: 3 | E12: Pasivos | F12: Registra las deudas. El balance las separa entre corto y largo plazo.
D13: 4 | E13: Patrimonio | F13: Registra aportes, capital o reservas.
D14: 5 | E14: Resultado Ejercicio | F14: Opcional: registra ingresos, costos y gastos para calcular utilidad o pérdida.
D15: 6 | E15: Balance General | F15: Se autocompleta en formato horizontal.
D16: 7 | E16: Dashboard | F16: Muestra indicadores simples.

Sheet Configuracion
B1: CONFIGURACIÓN
B2: Datos generales que se mostrarán en el Balance General.
C4: Dato | D4: Valor
C5: Nombre de la empresa | D5: Pon el nombre de tu Pyme aquí | F5: Consejo: esta plantilla sirve para ordenar y visualizar la situación financiera de una PYME. Para cierre contable formal, conviene validar los saldos con un contador.
C6: Nombre del estado financiero | D6: Balance General
C7: Fecha de corte | D7: xx-xx-20xx
C8: Moneda | D8: CLP
C9: Preparado por | D9: xxx

Sheet Activos
C1: ACTIVOS
C2: Registra todos los recursos de la empresa. El Balance General se autocompleta con esta información.
C4: Categoría | D4: Cuenta / Ítem | E4: Descripción | F4: Monto | G4: Orden | H4: Nota | I4: Clave automática | K4: Registro de activos
C5: Activo corriente | D5: Caja | E5: Dinero en efectivo disponible | F5: 1200000 | G5: 1 | I5: =IF(C5="","",C5&"|"&COUNTIF($C$5:C5,C5)) | K5: Ingrese aquí todos los bienes y derechos que posee la empresa. Seleccione si corresponde a Activo corriente o Activo no corriente, escriba el nombre de la cuenta y luego ingrese el monto correspondiente. No escriba totales manuales, ya que el archivo los calcula automáticamente y los lleva al Balance General.
C6: Activo corriente | D6: Banco | E6: Saldo en cuenta bancaria | F6: 8500000 | G6: 2 | I6: =IF(C6="","",C6&"|"&COUNTIF($C$5:C6,C6))
C7: Activo corriente | D7: Clientes por cobrar | E7: Ventas pendientes de cobro | F7: 3200000 | G7: 3 | I7: =IF(C7="","",C7&"|"&COUNTIF($C$5:C7,C7))
C8: Activo corriente | D8: Inventario | E8: Mercadería o productos disponibles | F8: 4600000 | G8: 4 | I8: =IF(C8="","",C8&"|"&COUNTIF($C$5:C8,C8))
C9: Activo no corriente | D9: Equipos | E9: Equipos usados en el negocio | F9: 3500000 | G9: 1 | I9: =IF(C9="","",C9&"|"&COUNTIF($C$5:C9,C9))
C10: Activo no corriente | D10: Muebles | E10: Mobiliario de oficina o local | F10: 1800000 | G10: 2 | I10: =IF(C10="","",C10&"|"&COUNTIF($C$5:C10,C10))
C11: Activo no corriente | D11: Maquinaria | E11: Herramientas o maquinaria productiva | F11: 5200000 | G11: 3 | I11: =IF(C11="","",C11&"|"&COUNTIF($C$5:C11,C11))
I12: =IF(C12="","",C12&"|"&COUNTIF($C$5:C12,C12))
I13: =IF(C13="","",C13&"|"&COUNTIF($C$5:C13,C13))
I14: =IF(C14="","",C14&"|"&COUNTIF($C$5:C14,C14)) | K14: Ejemplos: caja, banco, cuentas por cobrar, mercaderías, maquinaria, vehículos, muebles, equipos.
I15: =IF(C15="","",C15&"|"&COUNTIF($C$5:C15,C15))
I16: =IF(C16="","",C16&"|"&COUNTIF($C$5:C16,C16))
I17: =IF(C17="","",C17&"|"&COUNTIF($C$5:C17,C17))
I18: =IF(C18="","",C18&"|"&COUNTIF($C$5:C18,C18))
I19: =IF(C19="","",C19&"|"&COUNTIF($C$5:C19,C19))
I20: =IF(C20="","",C20&"|"&COUNTIF($C$5:C20,C20))
I21: =IF(C21="","",C21&"|"&COUNTIF($C$5:C21,C21))
I22: =IF(C22="","",C22&"|"&COUNTIF($C$5:C22,C22))
I23: =IF(C23="","",C23&"|"&COUNTIF($C$5:C23,C23))
I24: =IF(C24="","",C24&"|"&COUNTIF($C$5:C24,C24))
I25: =IF(C25="","",C25&"|"&COUNTIF($C$5:C25,C25))
I26: =IF(C26="","",C26&"|"&COUNTIF($C$5:C26,C26))
... I504: =IF(C504="","",C504&"|"&COUNTIF($C$5:C504,C504))

Sheet Pasivos
C1: PASIVOS
C2: Registra todas las deudas y obligaciones de la empresa.
C4: Categoría | D4: Cuenta / Ítem | E4: Descripción | F4: Monto | G4: Orden | H4: Nota | I4: Clave automática | K4: Registro de pasivos
C5: Pasivo corriente | D5: Proveedores | E5: Deudas con proveedores | F5: 2500000 | G5: 1 | I5: =IF(C5="","",C5&"|"&COUNTIF($C$5:C5,C5)) | K5: Ingrese aquí todas las deudas y obligaciones de la empresa. Seleccione si corresponde a Pasivo corriente o Pasivo no corriente, escriba el nombre de la cuenta y luego ingrese el monto. Los totales se calculan automáticamente y se conectan con el Balance General.
C6: Pasivo corriente | D6: Impuestos por pagar | E6: Obligaciones tributarias pendientes | F6: 650000 | G6: 2 | I6: =IF(C6="","",C6&"|"&COUNTIF($C$5:C6,C6))
C7: Pasivo corriente | D7: Sueldos por pagar | E7: Remuneraciones pendientes | F7: 900000 | G7: 3 | I7: =IF(C7="","",C7&"|"&COUNTIF($C$5:C7,C7))
C8: Pasivo no corriente | D8: Préstamo bancario | E8: Deuda bancaria de largo plazo | F8: 4200000 | G8: 1 | I8: =IF(C8="","",C8&"|"&COUNTIF($C$5:C8,C8))
I9: =IF(C9="","",C9&"|"&COUNTIF($C$5:C9,C9))
I10: =IF(C10="","",C10&"|"&COUNTIF($C$5:C10,C10))
I11: =IF(C11="","",C11&"|"&COUNTIF($C$5:C11,C11))
I12: =IF(C12="","",C12&"|"&COUNTIF($C$5:C12,C12))
I13: =IF(C13="","",C13&"|"&COUNTIF($C$5:C13,C13))
I14: =IF(C14="","",C14&"|"&COUNTIF($C$5:C14,C14)) | K14: Ejemplos: proveedores, préstamos bancarios, impuestos por pagar, sueldos por pagar, créditos de largo plazo.
I15: =IF(C15="","",C15&"|"&COUNTIF($C$5:C15,C15))
I16: =IF(C16="","",C16&"|"&COUNTIF($C$5:C16,C16))
I17: =IF(C17="","",C17&"|"&COUNTIF($C$5:C17,C17))
I18: =IF(C18="","",C18&"|"&COUNTIF($C$5:C18,C18))
I19: =IF(C19="","",C19&"|"&COUNTIF($C$5:C19,C19))
I20: =IF(C20="","",C20&"|"&COUNTIF($C$5:C20,C20))
I21: =IF(C21="","",C21&"|"&COUNTIF($C$5:C21,C21))
I22: =IF(C22="","",C22&"|"&COUNTIF($C$5:C22,C22))
I23: =IF(C23="","",C23&"|"&COUNTIF($C$5:C23,C23))
I24: =IF(C24="","",C24&"|"&COUNTIF($C$5:C24,C24))
I25: =IF(C25="","",C25&"|"&COUNTIF($C$5:C25,C25))
I26: =IF(C26="","",C26&"|"&COUNTIF($C$5:C26,C26))
... I504: =IF(C504="","",C504&"|"&COUNTIF($C$5:C504,C504))

Sheet Patrimonio
C1: PATRIMONIO
C2: Registra aportes, capital, reservas u otras cuentas propias de la empresa.
C3: Importante: no ingreses manualmente la utilidad o pérdida del ejercicio en esta hoja; se incorpora automáticamente desde Resultado Ejercicio.
C5: Cuenta / Ítem | D5: Descripción | E5: Monto | F5: Orden | G5: Nota | H5: Clave automática | J5: Registro de patrimonio
C6: Capital / aportes | D6: Aportes realizados por dueños o socios | E6: 11650000 | F6: 1 | H6: =IF(C6="","","Patrimonio|"&COUNTIF($C$6:C6,"<>")) | J6: Ingrese aquí los aportes de los dueños, capital, reservas u otros componentes del patrimonio de la empresa. No ingrese manualmente la utilidad o pérdida del ejercicio si ya está registrada en la hoja Resultado Ejercicio, porque el archivo la incorpora automáticamente al total de patrimonio.
C7: Reservas | D7: Fondos retenidos dentro de la empresa | E7: 1200000 | F7: 2 | H7: =IF(C7="","","Patrimonio|"&COUNTIF($C$6:C7,"<>"))
H8: =IF(C8="","","Patrimonio|"&COUNTIF($C$6:C8,"<>"))
H9: =IF(C9="","","Patrimonio|"&COUNTIF($C$6:C9,"<>"))
H10: =IF(C10="","","Patrimonio|"&COUNTIF($C$6:C10,"<>"))
H11: =IF(C11="","","Patrimonio|"&COUNTIF($C$6:C11,"<>"))
H12: =IF(C12="","","Patrimonio|"&COUNTIF($C$6:C12,"<>"))
H13: =IF(C13="","","Patrimonio|"&COUNTIF($C$6:C13,"<>")) | J13: Ejemplos: capital social, aportes de socios, reservas, utilidades acumuladas.
H14: =IF(C14="","","Patrimonio|"&COUNTIF($C$6:C14,"<>"))
H15: =IF(C15="","","Patrimonio|"&COUNTIF($C$6:C15,"<>"))
H16: =IF(C16="","","Patrimonio|"&COUNTIF($C$6:C16,"<>"))
H17: =IF(C17="","","Patrimonio|"&COUNTIF($C$6:C17,"<>"))
H18: =IF(C18="","","Patrimonio|"&COUNTIF($C$6:C18,"<>"))
H19: =IF(C19="","","Patrimonio|"&COUNTIF($C$6:C19,"<>"))
H20: =IF(C20="","","Patrimonio|"&COUNTIF($C$6:C20,"<>"))
H21: =IF(C21="","","Patrimonio|"&COUNTIF($C$6:C21,"<>"))
H22: =IF(C22="","","Patrimonio|"&COUNTIF($C$6:C22,"<>"))
H23: =IF(C23="","","Patrimonio|"&COUNTIF($C$6:C23,"<>"))
H24: =IF(C24="","","Patrimonio|"&COUNTIF($C$6:C24,"<>"))
H25: =IF(C25="","","Patrimonio|"&COUNTIF($C$6:C25,"<>"))
... H505: =IF(C505="","","Patrimonio|"&COUNTIF($C$6:C505,"<>"))

Sheet Resultado Ejercicio
C1: RESULTADO DEL EJERCICIO
C2: Opcional: registra ingresos, costos y gastos para incorporar utilidad o pérdida al patrimonio.
D4: Resumen | E4: Monto
D5: Ingresos | E5: =SUMIF(C11:C510,"Ingreso",F11:F510)
D6: Costos | E6: =SUMIF(C11:C510,"Costo",F11:F510)
D7: Gastos | E7: =SUMIF(C11:C510,"Gasto",F11:F510)
D8: Resultado del ejercicio | E8: =E5-E6-E7
C10: Tipo | D10: Cuenta / Concepto | E10: Descripción | F10: Monto | G10: Nota | I10: Ingresos, costos y gastos del período
C11: Ingreso | D11: Ventas | E11: Ingresos por ventas del periodo | F11: 15000000 | I11: Registre aquí los movimientos que permiten calcular el resultado del ejercicio. Seleccione el tipo de movimiento: Ingreso, Costo o Gasto, escriba una descripción y luego ingrese el monto. El archivo calcula automáticamente la utilidad o pérdida del período y la lleva al patrimonio dentro del Balance General.
C12: Ingreso | D12: Otros ingresos | E12: Otros ingresos operacionales | F12: 500000
C13: Costo | D13: Costo de ventas | E13: Costo directo de productos o servicios vendidos | F13: 6200000
C14: Gasto | D14: Gastos administrativos | E14: Gastos generales del negocio | F14: 2100000
C15: Gasto | D15: Gastos financieros | E15: Intereses o cargos bancarios | F15: 300000
I19: Ejemplos de ingresos: ventas, servicios prestados.
I20: Ejemplos de costos: costo de mercadería, materias primas.
I21: Ejemplos de gastos: arriendo, sueldos, luz, agua, internet, publicidad.

Sheet Balance General
C1: BALANCE GENERAL HORIZONTAL
C2: Formato horizontal automático: activos a la izquierda y patrimonio + pasivos a la derecha.
D4: =Configuracion!D5 | L4: Esta hoja se completa automáticamente con la información ingresada en Activos, Pasivos, Patrimonio y Resultado Ejercicio. No es necesario escribir datos directamente aquí. Revise que el Total Activo sea igual al Total Pasivo + Patrimonio. Si aparece una diferencia, significa que falta registrar información o que algún monto fue ingresado en una categoría incorrecta.
D5: =Configuracion!D6
D6: ="Fecha de corte: "&TEXT(Configuracion!D7,"dd-mm-yyyy")
D8: ACTIVO | H8: PATRIMONIO NETO Y PASIVO
D9: A) ACTIVO CORRIENTE | E9: Monto | H9: A) PATRIMONIO NETO | I9: Monto
D10: =IFERROR(INDEX(Activos!$D$5:$D$504,MATCH("Activo corriente|1",Activos!$I$5:$I$504,0)),"") | E10: =IFERROR(INDEX(Activos!$F$5:$F$504,MATCH("Activo corriente|1",Activos!$I$5:$I$504,0)),"") | H10: =IFERROR(INDEX(Patrimonio!$C$6:$C$505,MATCH("Patrimonio|1",Patrimonio!$H$6:$H$505,0)),"") | I10: =IFERROR(INDEX(Patrimonio!$E$6:$E$505,MATCH("Patrimonio|1",Patrimonio!$H$6:$H$505,0)),"")
D11: =IFERROR(INDEX(Activos!$D$5:$D$504,MATCH("Activo corriente|2",Activos!$I$5:$I$504,0)),"") | E11: =IFERROR(INDEX(Activos!$F$5:$F$504,MATCH("Activo corriente|2",Activos!$I$5:$I$504,0)),"") | H11: =IFERROR(INDEX(Patrimonio!$C$6:$C$505,MATCH("Patrimonio|2",Patrimonio!$H$6:$H$505,0)),"") | I11: =IFERROR(INDEX(Patrimonio!$E$6:$E$505,MATCH("Patrimonio|2",Patrimonio!$H$6:$H$505,0)),"")
D12: =IFERROR(INDEX(Activos!$D$5:$D$504,MATCH("Activo corriente|3",Activos!$I$5:$I$504,0)),"") | E12: =IFERROR(INDEX(Activos!$F$5:$F$504,MATCH("Activo corriente|3",Activos!$I$5:$I$504,0)),"") | H12: =IFERROR(INDEX(Patrimonio!$C$6:$C$505,MATCH("Patrimonio|3",Patrimonio!$H$6:$H$505,0)),"") | I12: =IFERROR(INDEX(Patrimonio!$E$6:$E$505,MATCH("Patrimonio|3",Patrimonio!$H$6:$H$505,0)),"")
D13: =IFERROR(INDEX(Activos!$D$5:$D$504,MATCH("Activo corriente|4",Activos!$I$5:$I$504,0)),"") | E13: =IFERROR(INDEX(Activos!$F$5:$F$504,MATCH("Activo corriente|4",Activos!$I$5:$I$504,0)),"") | H13: =IFERROR(INDEX(Patrimonio!$C$6:$C$505,MATCH("Patrimonio|4",Patrimonio!$H$6:$H$505,0)),"") | I13: =IFERROR(INDEX(Patrimonio!$E$6:$E$505,MATCH("Patrimonio|4",Patrimonio!$H$6:$H$505,0)),"") | O13: TOTAL PASIVO | P13: =I79+I117
D14: =IFERROR(INDEX(Activos!$D$5:$D$504,MATCH("Activo corriente|5",Activos!$I$5:$I$504,0)),"") | E14: =IFERROR(INDEX(Activos!$F$5:$F$504,MATCH("Activo corriente|5",Activos!$I$5:$I$504,0)),"") | H14: =IFERROR(INDEX(Patrimonio!$C$6:$C$505,MATCH("Patrimonio|5",Patrimonio!$H$6:$H$505,0)),"") | I14: =IFERROR(INDEX(Patrimonio!$E$6:$E$505,MATCH("Patrimonio|5",Patrimonio!$H$6:$H$505,0)),"") | L14: TOTAL ACTIVO | M14: =P19
D15: =IFERROR(INDEX(Activos!$D$5:$D$504,MATCH("Activo corriente|6",Activos!$I$5:$I$504,0)),"") | E15: =IFERROR(INDEX(Activos!$F$5:$F$504,MATCH("Activo corriente|6",Activos!$I$5:$I$504,0)),"") | H15: =IFERROR(INDEX(Patrimonio!$C$6:$C$505,MATCH("Patrimonio|6",Patrimonio!$H$6:$H$505,0)),"") | I15: =IFERROR(INDEX(Patrimonio!$E$6:$E$505,MATCH("Patrimonio|6",Patrimonio!$H$6:$H$505,0)),"") | O15: TOTAL PASIVO + PATRIMONIO | P15: =P13+I41
D16: =IFERROR(INDEX(Activos!$D$5:$D$504,MATCH("Activo corriente|7",Activos!$I$5:$I$504,0)),"") | E16: =IFERROR(INDEX(Activos!$F$5:$F$504,MATCH("Activo corriente|7",Activos!$I$5:$I$504,0)),"") | H16: =IFERROR(INDEX(Patrimonio!$C$6:$C$505,MATCH("Patrimonio|7",Patrimonio!$H$6:$H$505,0)),"") | I16: =IFERROR(INDEX(Patrimonio!$E$6:$E$505,MATCH("Patrimonio|7",Patrimonio!$H$6:$H$505,0)),"") | L16: DIFERENCIA | M16: =M14-P15
D17: =IFERROR(INDEX(Activos!$D$5:$D$504,MATCH("Activo corriente|8",Activos!$I$5:$I$504,0)),"") | E17: =IFERROR(INDEX(Activos!$F$5:$F$504,MATCH("Activo corriente|8",Activos!$I$5:$I$504,0)),"") | H17: =IFERROR(INDEX(Patrimonio!$C$6:$C$505,MATCH("Patrimonio|8",Patrimonio!$H$6:$H$505,0)),"") | I17: =IFERROR(INDEX(Patrimonio!$E$6:$E$505,MATCH("Patrimonio|8",Patrimonio!$H$6:$H$505,0)),"") | O17: ESTADO DEL BALANCE | P17: =IF(ABS(M16)<1,"Balance cuadrado","Revisar diferencia")
D18: =IFERROR(INDEX(Activos!$D$5:$D$504,MATCH("Activo corriente|9",Activos!$I$5:$I$504,0)),"") | E18: =IFERROR(INDEX(Activos!$F$5:$F$504,MATCH("Activo corriente|9",Activos!$I$5:$I$504,0)),"") | H18: =IFERROR(INDEX(Patrimonio!$C$6:$C$505,MATCH("Patrimonio|9",Patrimonio!$H$6:$H$505,0)),"") | I18: =IFERROR(INDEX(Patrimonio!$E$6:$E$505,MATCH("Patrimonio|9",Patrimonio!$H$6:$H$505,0)),"")
D19: =IFERROR(INDEX(Activos!$D$5:$D$504,MATCH("Activo corriente|10",Activos!$I$5:$I$504,0)),"") | E19: =IFERROR(INDEX(Activos!$F$5:$F$504,MATCH("Activo corriente|10",Activos!$I$5:$I$504,0)),"") | H19: =IFERROR(INDEX(Patrimonio!$C$6:$C$505,MATCH("Patrimonio|10",Patrimonio!$H$6:$H$505,0)),"") | I19: =IFERROR(INDEX(Patrimonio!$E$6:$E$505,MATCH("Patrimonio|10",Patrimonio!$H$6:$H$505,0)),"") | O19: TOTAL ACTIVO | P19: =E45+E83+E101
D20: =IFERROR(INDEX(Activos!$D$5:$D$504,MATCH("Activo corriente|11",Activos!$I$5:$I$504,0)),"") | E20: =IFERROR(INDEX(Activos!$F$5:$F$504,MATCH("Activo corriente|11",Activos!$I$5:$I$504,0)),"") | H20: =IFERROR(INDEX(Patrimonio!$C$6:$C$505,MATCH("Patrimonio|11",Patrimonio!$H$6:$H$505,0)),"") | I20: =IFERROR(INDEX(Patrimonio!$E$6:$E$505,MATCH("Patrimonio|11",Patrimonio!$H$6:$H$505,0)),"")
D21: =IFERROR(INDEX(Activos!$D$5:$D$504,MATCH("Activo corriente|12",Activos!$I$5:$I$504,0)),"") | E21: =IFERROR(INDEX(Activos!$F$5:$F$504,MATCH("Activo corriente|12",Activos!$I$5:$I$504,0)),"") | H21: =IFERROR(INDEX(Patrimonio!$C$6:$C$505,MATCH("Patrimonio|12",Patrimonio!$H$6:$H$505,0)),"") | I21: =IFERROR(INDEX(Patrimonio!$E$6:$E$505,MATCH("Patrimonio|12",Patrimonio!$H$6:$H$505,0)),"")
D22: =IFERROR(INDEX(Activos!$D$5:$D$504,MATCH("Activo corriente|13",Activos!$I$5:$I$504,0)),"") | E22: =IFERROR(INDEX(Activos!$F$5:$F$504,MATCH("Activo corriente|13",Activos!$I$5:$I$504,0)),"") | H22: =IFERROR(INDEX(Patrimonio!$C$6:$C$505,MATCH("Patrimonio|13",Patrimonio!$H$6:$H$505,0)),"") | I22: =IFERROR(INDEX(Patrimonio!$E$6:$E$505,MATCH("Patrimonio|13",Patrimonio!$H$6:$H$505,0)),"")
D23: =IFERROR(INDEX(Activos!$D$5:$D$504,MATCH("Activo corriente|14",Activos!$I$5:$I$504,0)),"") | E23: =IFERROR(INDEX(Activos!$F$5:$F$504,MATCH("Activo corriente|14",Activos!$I$5:$I$504,0)),"") | H23: =IFERROR(INDEX(Patrimonio!$C$6:$C$505,MATCH("Patrimonio|14",Patrimonio!$H$6:$H$505,0)),"") | I23: =IFERROR(INDEX(Patrimonio!$E$6:$E$505,MATCH("Patrimonio|14",Patrimonio!$H$6:$H$505,0)),"")
D24: =IFERROR(INDEX(Activos!$D$5:$D$504,MATCH("Activo corriente|15",Activos!$I$5:$I$504,0)),"") | E24: =IFERROR(INDEX(Activos!$F$5:$F$504,MATCH("Activo corriente|15",Activos!$I$5:$I$504,0)),"") | H24: =IFERROR(INDEX(Patrimonio!$C$6:$C$505,MATCH("Patrimonio|15",Patrimonio!$H$6:$H$505,0)),"") | I24: =IFERROR(INDEX(Patrimonio!$E$6:$E$505,MATCH("Patrimonio|15",Patrimonio!$H$6:$H$505,0)),"")
D25: =IFERROR(INDEX(Activos!$D$5:$D$504,MATCH("Activo corriente|16",Activos!$I$5:$I$504,0)),"") | E25: =IFERROR(INDEX(Activos!$F$5:$F$504,MATCH("Activo corriente|16",Activos!$I$5:$I$504,0)),"") | H25: =IFERROR(INDEX(Patrimonio!$C$6:$C$505,MATCH("Patrimonio|16",Patrimonio!$H$6:$H$505,0)),"") | I25: =IFERROR(INDEX(Patrimonio!$E$6:$E$505,MATCH("Patrimonio|16",Patrimonio!$H$6:$H$505,0)),"")
D26: =IFERROR(INDEX(Activos!$D$5:$D$504,MATCH("Activo corriente|17",Activos!$I$5:$I$504,0)),"") | E26: =IFERROR(INDEX(Activos!$F$5:$F$504,MATCH("Activo corriente|17",Activos!$I$5:$I$504,0)),"") | H26: =IFERROR(INDEX(Patrimonio!$C$6:$C$505,MATCH("Patrimonio|17",Patrimonio!$H$6:$H$505,0)),"") | I26: =IFERROR(INDEX(Patrimonio!$E$6:$E$505,MATCH("Patrimonio|17",Patrimonio!$H$6:$H$505,0)),"")
D27: =IFERROR(INDEX(Activos!$D$5:$D$504,MATCH("Activo corriente|18",Activos!$I$5:$I$504,0)),"") | E27: =IFERROR(INDEX(Activos!$F$5:$F$504,MATCH("Activo corriente|18",Activos!$I$5:$I$504,0)),"") | H27: =IFERROR(INDEX(Patrimonio!$C$6:$C$505,MATCH("Patrimonio|18",Patrimonio!$H$6:$H$505,0)),"") | I27: =IFERROR(INDEX(Patrimonio!$E$6:$E$505,MATCH("Patrimonio|18",Patrimonio!$H$6:$H$505,0)),"")
D28: =IFERROR(INDEX(Activos!$D$5:$D$504,MATCH("Activo corriente|19",Activos!$I$5:$I$504,0)),"") | E28: =IFERROR(INDEX(Activos!$F$5:$F$504,MATCH("Activo corriente|19",Activos!$I$5:$I$504,0)),"") | H28: =IFERROR(INDEX(Patrimonio!$C$6:$C$505,MATCH("Patrimonio|19",Patrimonio!$H$6:$H$505,0)),"") | I28: =IFERROR(INDEX(Patrimonio!$E$6:$E$505,MATCH("Patrimonio|19",Patrimonio!$H$6:$H$505,0)),"")
D29: =IFERROR(INDEX(Activos!$D$5:$D$504,MATCH("Activo corriente|20",Activos!$I$5:$I$504,0)),"") | E29: =IFERROR(INDEX(Activos!$F$5:$F$504,MATCH("Activo corriente|20",Activos!$I$5:$I$504,0)),"") | H29: =IFERROR(INDEX(Patrimonio!$C$6:$C$505,MATCH("Patrimonio|20",Patrimonio!$H$6:$H$505,0)),"") | I29: =IFERROR(INDEX(Patrimonio!$E$6:$E$505,MATCH("Patrimonio|20",Patrimonio!$H$6:$H$505,0)),"")
D30: =IFERROR(INDEX(Activos!$D$5:$D$504,MATCH("Activo corriente|21",Activos!$I$5:$I$504,0)),"") | E30: =IFERROR(INDEX(Activos!$F$5:$F$504,MATCH("Activo corriente|21",Activos!$I$5:$I$504,0)),"") | H30: =IFERROR(INDEX(Patrimonio!$C$6:$C$505,MATCH("Patrimonio|21",Patrimonio!$H$6:$H$505,0)),"") | I30: =IFERROR(INDEX(Patrimonio!$E$6:$E$505,MATCH("Patrimonio|21",Patrimonio!$H$6:$H$505,0)),"")
D31: =IFERROR(INDEX(Activos!$D$5:$D$504,MATCH("Activo corriente|22",Activos!$I$5:$I$504,0)),"") | E31: =IFERROR(INDEX(Activos!$F$5:$F$504,MATCH("Activo corriente|22",Activos!$I$5:$I$504,0)),"") | H31: =IFERROR(INDEX(Patrimonio!$C$6:$C$505,MATCH("Patrimonio|22",Patrimonio!$H$6:$H$505,0)),"") | I31: =IFERROR(INDEX(Patrimonio!$E$6:$E$505,MATCH("Patrimonio|22",Patrimonio!$H$6:$H$505,0)),"")
D32: =IFERROR(INDEX(Activos!$D$5:$D$504,MATCH("Activo corriente|23",Activos!$I$5:$I$504,0)),"") | E32: =IFERROR(INDEX(Activos!$F$5:$F$504,MATCH("Activo corriente|23",Activos!$I$5:$I$504,0)),"") | H32: =IFERROR(INDEX(Patrimonio!$C$6:$C$505,MATCH("Patrimonio|23",Patrimonio!$H$6:$H$505,0)),"") | I32: =IFERROR(INDEX(Patrimonio!$E$6:$E$505,MATCH("Patrimonio|23",Patrimonio!$H$6:$H$505,0)),"")
D33: =IFERROR(INDEX(Activos!$D$5:$D$504,MATCH("Activo corriente|24",Activos!$I$5:$I$504,0)),"") | E33: =IFERROR(INDEX(Activos!$F$5:$F$504,MATCH("Activo corriente|24",Activos!$I$5:$I$504,0)),"") | H33: =IFERROR(INDEX(Patrimonio!$C$6:$C$505,MATCH("Patrimonio|24",Patrimonio!$H$6:$H$505,0)),"") | I33: =IFERROR(INDEX(Patrimonio!$E$6:$E$505,MATCH("Patrimonio|24",Patrimonio!$H$6:$H$505,0)),"")
D34: =IFERROR(INDEX(Activos!$D$5:$D$504,MATCH("Activo corriente|25",Activos!$I$5:$I$504,0)),"") | E34: =IFERROR(INDEX(Activos!$F$5:$F$504,MATCH("Activo corriente|25",Activos!$I$5:$I$504,0)),"") | H34: =IFERROR(INDEX(Patrimonio!$C$6:$C$505,MATCH("Patrimonio|25",Patrimonio!$H$6:$H$505,0)),"") | I34: =IFERROR(INDEX(Patrimonio!$E$6:$E$505,MATCH("Patrimonio|25",Patrimonio!$H$6:$H$505,0)),"")
D35: =IFERROR(INDEX(Activos!$D$5:$D$504,MATCH("Activo corriente|26",Activos!$I$5:$I$504,0)),"") | E35: =IFERROR(INDEX(Activos!$F$5:$F$504,MATCH("Activo corriente|26",Activos!$I$5:$I$504,0)),"") | H35: =IFERROR(INDEX(Patrimonio!$C$6:$C$505,MATCH("Patrimonio|26",Patrimonio!$H$6:$H$505,0)),"") | I35: =IFERROR(INDEX(Patrimonio!$E$6:$E$505,MATCH("Patrimonio|26",Patrimonio!$H$6:$H$505,0)),"")
D36: =IFERROR(INDEX(Activos!$D$5:$D$504,MATCH("Activo corriente|27",Activos!$I$5:$I$504,0)),"") | E36: =IFERROR(INDEX(Activos!$F$5:$F$504,MATCH("Activo corriente|27",Activos!$I$5:$I$504,0)),"") | H36: =IFERROR(INDEX(Patrimonio!$C$6:$C$505,MATCH("Patrimonio|27",Patrimonio!$H$6:$H$505,0)),"") | I36: =IFERROR(INDEX(Patrimonio!$E$6:$E$505,MATCH("Patrimonio|27",Patrimonio!$H$6:$H$505,0)),"")
D37: =IFERROR(INDEX(Activos!$D$5:$D$504,MATCH("Activo corriente|28",Activos!$I$5:$I$504,0)),"") | E37: =IFERROR(INDEX(Activos!$F$5:$F$504,MATCH("Activo corriente|28",Activos!$I$5:$I$504,0)),"") | H37: =IFERROR(INDEX(Patrimonio!$C$6:$C$505,MATCH("Patrimonio|28",Patrimonio!$H$6:$H$505,0)),"") | I37: =IFERROR(INDEX(Patrimonio!$E$6:$E$505,MATCH("Patrimonio|28",Patrimonio!$H$6:$H$505,0)),"")
D38: =IFERROR(INDEX(Activos!$D$5:$D$504,MATCH("Activo corriente|29",Activos!$I$5:$I$504,0)),"") | E38: =IFERROR(INDEX(Activos!$F$5:$F$504,MATCH("Activo corriente|29",Activos!$I$5:$I$504,0)),"") | H38: =IFERROR(INDEX(Patrimonio!$C$6:$C$505,MATCH("Patrimonio|29",Patrimonio!$H$6:$H$505,0)),"") | I38: =IFERROR(INDEX(Patrimonio!$E$6:$E$505,MATCH("Patrimonio|29",Patrimonio!$H$6:$H$505,0)),"")
D39: =IFERROR(INDEX(Activos!$D$5:$D$504,MATCH("Activo corriente|30",Activos!$I$5:$I$504,0)),"") | E39: =IFERROR(INDEX(Activos!$F$5:$F$504,MATCH("Activo corriente|30",Activos!$I$5:$I$504,0)),"") | H39: =IFERROR(INDEX(Patrimonio!$C$6:$C$505,MATCH("Patrimonio|30",Patrimonio!$H$6:$H$505,0)),"") | I39: =IFERROR(INDEX(Patrimonio!$E$6:$E$505,MATCH("Patrimonio|30",Patrimonio!$H$6:$H$505,0)),"")
D40: =IFERROR(INDEX(Activos!$D$5:$D$504,MATCH("Activo corriente|31",Activos!$I$5:$I$504,0)),"") | E40: =IFERROR(INDEX(Activos!$F$5:$F$504,MATCH("Activo corriente|31",Activos!$I$5:$I$504,0)),"") | H40: Resultado del ejercicio | I40: ='Resultado Ejercicio'!E8
D41: =IFERROR(INDEX(Activos!$D$5:$D$504,MATCH("Activo corriente|32",Activos!$I$5:$I$504,0)),"") | E41: =IFERROR(INDEX(Activos!$F$5:$F$504,MATCH("Activo corriente|32",Activos!$I$5:$I$504,0)),"") | H41: TOTAL PATRIMONIO | I41: =SUM(Patrimonio!$E$6:$E$505)+I40
D42: =IFERROR(INDEX(Activos!$D$5:$D$504,MATCH("Activo corriente|33",Activos!$I$5:$I$504,0)),"") | E42: =IFERROR(INDEX(Activos!$F$5:$F$504,MATCH("Activo corriente|33",Activos!$I$5:$I$504,0)),"")
D43: =IFERROR(INDEX(Activos!$D$5:$D$504,MATCH("Activo corriente|34",Activos!$I$5:$I$504,0)),"") | E43: =IFERROR(INDEX(Activos!$F$5:$F$504,MATCH("Activo corriente|34",Activos!$I$5:$I$504,0)),"") | H43: B) PASIVO CORRIENTE | I43: Monto
D44: =IFERROR(INDEX(Activos!$D$5:$D$504,MATCH("Activo corriente|35",Activos!$I$5:$I$504,0)),"") | E44: =IFERROR(INDEX(Activos!$F$5:$F$504,MATCH("Activo corriente|35",Activos!$I$5:$I$504,0)),"") | H44: =IFERROR(INDEX(Pasivos!$D$5:$D$504,MATCH("Pasivo corriente|1",Pasivos!$I$5:$I$504,0)),"") | I44: =IFERROR(INDEX(Pasivos!$F$5:$F$504,MATCH("Pasivo corriente|1",Pasivos!$I$5:$I$504,0)),"")
D45: TOTAL ACTIVO CORRIENTE | E45: =SUMIF(Activos!$C$5:$C$504,"Activo corriente",Activos!$F$5:$F$504) | H45: =IFERROR(INDEX(Pasivos!$D$5:$D$504,MATCH("Pasivo corriente|2",Pasivos!$I$5:$I$504,0)),"") | I45: =IFERROR(INDEX(Pasivos!$F$5:$F$504,MATCH("Pasivo corriente|2",Pasivos!$I$5:$I$504,0)),"")
H46: =IFERROR(INDEX(Pasivos!$D$5:$D$504,MATCH("Pasivo corriente|3",Pasivos!$I$5:$I$504,0)),"") | I46: =IFERROR(INDEX(Pasivos!$F$5:$F$504,MATCH("Pasivo corriente|3",Pasivos!$I$5:$I$504,0)),"")
D47: B) ACTIVO NO CORRIENTE | E47: Monto | H47: =IFERROR(INDEX(Pasivos!$D$5:$D$504,MATCH("Pasivo corriente|4",Pasivos!$I$5:$I$504,0)),"") | I47: =IFERROR(INDEX(Pasivos!$F$5:$F$504,MATCH("Pasivo corriente|4",Pasivos!$I$5:$I$504,0)),"")
D48: =IFERROR(INDEX(Activos!$D$5:$D$504,MATCH("Activo no corriente|1",Activos!$I$5:$I$504,0)),"") | E48: =IFERROR(INDEX(Activos!$F$5:$F$504,MATCH("Activo no corriente|1",Activos!$I$5:$I$504,0)),"") | H48: =IFERROR(INDEX(Pasivos!$D$5:$D$504,MATCH("Pasivo corriente|5",Pasivos!$I$5:$I$504,0)),"") | I48: =IFERROR(INDEX(Pasivos!$F$5:$F$504,MATCH("Pasivo corriente|5",Pasivos!$I$5:$I$504,0)),"")
D49: =IFERROR(INDEX(Activos!$D$5:$D$504,MATCH("Activo no corriente|2",Activos!$I$5:$I$504,0)),"") | E49: =IFERROR(INDEX(Activos!$F$5:$F$504,MATCH("Activo no corriente|2",Activos!$I$5:$I$504,0)),"") | H49: =IFERROR(INDEX(Pasivos!$D$5:$D$504,MATCH("Pasivo corriente|6",Pasivos!$I$5:$I$504,0)),"") | I49: =IFERROR(INDEX(Pasivos!$F$5:$F$504,MATCH("Pasivo corriente|6",Pasivos!$I$5:$I$504,0)),"")
D50: =IFERROR(INDEX(Activos!$D$5:$D$504,MATCH("Activo no corriente|3",Activos!$I$5:$I$504,0)),"") | E50: =IFERROR(INDEX(Activos!$F$5:$F$504,MATCH("Activo no corriente|3",Activos!$I$5:$I$504,0)),"") | H50: =IFERROR(INDEX(Pasivos!$D$5:$D$504,MATCH("Pasivo corriente|7",Pasivos!$I$5:$I$504,0)),"") | I50: =IFERROR(INDEX(Pasivos!$F$5:$F$504,MATCH("Pasivo corriente|7",Pasivos!$I$5:$I$504,0)),"")
D51: =IFERROR(INDEX(Activos!$D$5:$D$504,MATCH("Activo no corriente|4",Activos!$I$5:$I$504,0)),"") | E51: =IFERROR(INDEX(Activos!$F$5:$F$504,MATCH("Activo no corriente|4",Activos!$I$5:$I$504,0)),"") | H51: =IFERROR(INDEX(Pasivos!$D$5:$D$504,MATCH("Pasivo corriente|8",Pasivos!$I$5:$I$504,0)),"") | I51: =IFERROR(INDEX(Pasivos!$F$5:$F$504,MATCH("Pasivo corriente|8",Pasivos!$I$5:$I$504,0)),"")
D52: =IFERROR(INDEX(Activos!$D$5:$D$504,MATCH("Activo no corriente|5",Activos!$I$5:$I$504,0)),"") | E52: =IFERROR(INDEX(Activos!$F$5:$F$504,MATCH("Activo no corriente|5",Activos!$I$5:$I$504,0)),"") | H52: =IFERROR(INDEX(Pasivos!$D$5:$D$504,MATCH("Pasivo corriente|9",Pasivos!$I$5:$I$504,0)),"") | I52: =IFERROR(INDEX(Pasivos!$F$5:$F$504,MATCH("Pasivo corriente|9",Pasivos!$I$5:$I$504,0)),"")
D53: =IFERROR(INDEX(Activos!$D$5:$D$504,MATCH("Activo no corriente|6",Activos!$I$5:$I$504,0)),"") | E53: =IFERROR(INDEX(Activos!$F$5:$F$504,MATCH("Activo no corriente|6",Activos!$I$5:$I$504,0)),"") | H53: =IFERROR(INDEX(Pasivos!$D$5:$D$504,MATCH("Pasivo corriente|10",Pasivos!$I$5:$I$504,0)),"") | I53: =IFERROR(INDEX(Pasivos!$F$5:$F$504,MATCH("Pasivo corriente|10",Pasivos!$I$5:$I$504,0)),"")
D54: =IFERROR(INDEX(Activos!$D$5:$D$504,MATCH("Activo no corriente|7",Activos!$I$5:$I$504,0)),"") | E54: =IFERROR(INDEX(Activos!$F$5:$F$504,MATCH("Activo no corriente|7",Activos!$I$5:$I$504,0)),"") | H54: =IFERROR(INDEX(Pasivos!$D$5:$D$504,MATCH("Pasivo corriente|11",Pasivos!$I$5:$I$504,0)),"") | I54: =IFERROR(INDEX(Pasivos!$F$5:$F$504,MATCH("Pasivo corriente|11",Pasivos!$I$5:$I$504,0)),"")
D55: =IFERROR(INDEX(Activos!$D$5:$D$504,MATCH("Activo no corriente|8",Activos!$I$5:$I$504,0)),"") | E55: =IFERROR(INDEX(Activos!$F$5:$F$504,MATCH("Activo no corriente|8",Activos!$I$5:$I$504,0)),"") | H55: =IFERROR(INDEX(Pasivos!$D$5:$D$504,MATCH("Pasivo corriente|12",Pasivos!$I$5:$I$504,0)),"") | I55: =IFERROR(INDEX(Pasivos!$F$5:$F$504,MATCH("Pasivo corriente|12",Pasivos!$I$5:$I$504,0)),"")
D56: =IFERROR(INDEX(Activos!$D$5:$D$504,MATCH("Activo no corriente|9",Activos!$I$5:$I$504,0)),"") | E56: =IFERROR(INDEX(Activos!$F$5:$F$504,MATCH("Activo no corriente|9",Activos!$I$5:$I$504,0)),"") | H56: =IFERROR(INDEX(Pasivos!$D$5:$D$504,MATCH("Pasivo corriente|13",Pasivos!$I$5:$I$504,0)),"") | I56: =IFERROR(INDEX(Pasivos!$F$5:$F$504,MATCH("Pasivo corriente|13",Pasivos!$I$5:$I$504,0)),"")
D57: =IFERROR(INDEX(Activos!$D$5:$D$504,MATCH("Activo no corriente|10",Activos!$I$5:$I$504,0)),"") | E57: =IFERROR(INDEX(Activos!$F$5:$F$504,MATCH("Activo no corriente|10",Activos!$I$5:$I$504,0)),"") | H57: =IFERROR(INDEX(Pasivos!$D$5:$D$504,MATCH("Pasivo corriente|14",Pasivos!$I$5:$I$504,0)),"") | I57: =IFERROR(INDEX(Pasivos!$F$5:$F$504,MATCH("Pasivo corriente|14",Pasivos!$I$5:$I$504,0)),"")
D58: =IFERROR(INDEX(Activos!$D$5:$D$504,MATCH("Activo no corriente|11",Activos!$I$5:$I$504,0)),"") | E58: =IFERROR(INDEX(Activos!$F$5:$F$504,MATCH("Activo no corriente|11",Activos!$I$5:$I$504,0)),"") | H58: =IFERROR(INDEX(Pasivos!$D$5:$D$504,MATCH("Pasivo corriente|15",Pasivos!$I$5:$I$504,0)),"") | I58: =IFERROR(INDEX(Pasivos!$F$5:$F$504,MATCH("Pasivo corriente|15",Pasivos!$I$5:$I$504,0)),"")
D59: =IFERROR(INDEX(Activos!$D$5:$D$504,MATCH("Activo no corriente|12",Activos!$I$5:$I$504,0)),"") | E59: =IFERROR(INDEX(Activos!$F$5:$F$504,MATCH("Activo no corriente|12",Activos!$I$5:$I$504,0)),"") | H59: =IFERROR(INDEX(Pasivos!$D$5:$D$504,MATCH("Pasivo corriente|16",Pasivos!$I$5:$I$504,0)),"") | I59: =IFERROR(INDEX(Pasivos!$F$5:$F$504,MATCH("Pasivo corriente|16",Pasivos!$I$5:$I$504,0)),"")
D60: =IFERROR(INDEX(Activos!$D$5:$D$504,MATCH("Activo no corriente|13",Activos!$I$5:$I$504,0)),"") | E60: =IFERROR(INDEX(Activos!$F$5:$F$504,MATCH("Activo no corriente|13",Activos!$I$5:$I$504,0)),"") | H60: =IFERROR(INDEX(Pasivos!$D$5:$D$504,MATCH("Pasivo corriente|17",Pasivos!$I$5:$I$504,0)),"") | I60: =IFERROR(INDEX(Pasivos!$F$5:$F$504,MATCH("Pasivo corriente|17",Pasivos!$I$5:$I$504,0)),"")
D61: =IFERROR(INDEX(Activos!$D$5:$D$504,MATCH("Activo no corriente|14",Activos!$I$5:$I$504,0)),"") | E61: =IFERROR(INDEX(Activos!$F$5:$F$504,MATCH("Activo no corriente|14",Activos!$I$5:$I$504,0)),"") | H61: =IFERROR(INDEX(Pasivos!$D$5:$D$504,MATCH("Pasivo corriente|18",Pasivos!$I$5:$I$504,0)),"") | I61: =IFERROR(INDEX(Pasivos!$F$5:$F$504,MATCH("Pasivo corriente|18",Pasivos!$I$5:$I$504,0)),"")
D62: =IFERROR(INDEX(Activos!$D$5:$D$504,MATCH("Activo no corriente|15",Activos!$I$5:$I$504,0)),"") | E62: =IFERROR(INDEX(Activos!$F$5:$F$504,MATCH("Activo no corriente|15",Activos!$I$5:$I$504,0)),"") | H62: =IFERROR(INDEX(Pasivos!$D$5:$D$504,MATCH("Pasivo corriente|19",Pasivos!$I$5:$I$504,0)),"") | I62: =IFERROR(INDEX(Pasivos!$F$5:$F$504,MATCH("Pasivo corriente|19",Pasivos!$I$5:$I$504,0)),"")
D63: =IFERROR(INDEX(Activos!$D$5:$D$504,MATCH("Activo no corriente|16",Activos!$I$5:$I$504,0)),"") | E63: =IFERROR(INDEX(Activos!$F$5:$F$504,MATCH("Activo no corriente|16",Activos!$I$5:$I$504,0)),"") | H63: =IFERROR(INDEX(Pasivos!$D$5:$D$504,MATCH("Pasivo corriente|20",Pasivos!$I$5:$I$504,0)),"") | I63: =IFERROR(INDEX(Pasivos!$F$5:$F$504,MATCH("Pasivo corriente|20",Pasivos!$I$5:$I$504,0)),"")
D64: =IFERROR(INDEX(Activos!$D$5:$D$504,MATCH("Activo no corriente|17",Activos!$I$5:$I$504,0)),"") | E64: =IFERROR(INDEX(Activos!$F$5:$F$504,MATCH("Activo no corriente|17",Activos!$I$5:$I$504,0)),"") | H64: =IFERROR(INDEX(Pasivos!$D$5:$D$504,MATCH("Pasivo corriente|21",Pasivos!$I$5:$I$504,0)),"") | I64: =IFERROR(INDEX(Pasivos!$F$5:$F$504,MATCH("Pasivo corriente|21",Pasivos!$I$5:$I$504,0)),"")
D65: =IFERROR(INDEX(Activos!$D$5:$D$504,MATCH("Activo no corriente|18",Activos!$I$5:$I$504,0)),"") | E65: =IFERROR(INDEX(Activos!$F$5:$F$504,MATCH("Activo no corriente|18",Activos!$I$5:$I$504,0)),"") | H65: =IFERROR(INDEX(Pasivos!$D$5:$D$504,MATCH("Pasivo corriente|22",Pasivos!$I$5:$I$504,0)),"") | I65: =IFERROR(INDEX(Pasivos!$F$5:$F$504,MATCH("Pasivo corriente|22",Pasivos!$I$5:$I$504,0)),"")
D66: =IFERROR(INDEX(Activos!$D$5:$D$504,MATCH("Activo no corriente|19",Activos!$I$5:$I$504,0)),"") | E66: =IFERROR(INDEX(Activos!$F$5:$F$504,MATCH("Activo no corriente|19",Activos!$I$5:$I$504,0)),"") | H66: =IFERROR(INDEX(Pasivos!$D$5:$D$504,MATCH("Pasivo corriente|23",Pasivos!$I$5:$I$504,0)),"") | I66: =IFERROR(INDEX(Pasivos!$F$5:$F$504,MATCH("Pasivo corriente|23",Pasivos!$I$5:$I$504,0)),"")
D67: =IFERROR(INDEX(Activos!$D$5:$D$504,MATCH("Activo no corriente|20",Activos!$I$5:$I$504,0)),"") | E67: =IFERROR(INDEX(Activos!$F$5:$F$504,MATCH("Activo no corriente|20",Activos!$I$5:$I$504,0)),"") | H67: =IFERROR(INDEX(Pasivos!$D$5:$D$504,MATCH("Pasivo corriente|24",Pasivos!$I$5:$I$504,0)),"") | I67: =IFERROR(INDEX(Pasivos!$F$5:$F$504,MATCH("Pasivo corriente|24",Pasivos!$I$5:$I$504,0)),"")
D68: =IFERROR(INDEX(Activos!$D$5:$D$504,MATCH("Activo no corriente|21",Activos!$I$5:$I$504,0)),"") | E68: =IFERROR(INDEX(Activos!$F$5:$F$504,MATCH("Activo no corriente|21",Activos!$I$5:$I$504,0)),"") | H68: =IFERROR(INDEX(Pasivos!$D$5:$D$504,MATCH("Pasivo corriente|25",Pasivos!$I$5:$I$504,0)),"") | I68: =IFERROR(INDEX(Pasivos!$F$5:$F$504,MATCH("Pasivo corriente|25",Pasivos!$I$5:$I$504,0)),"")
D69: =IFERROR(INDEX(Activos!$D$5:$D$504,MATCH("Activo no corriente|22",Activos!$I$5:$I$504,0)),"") | E69: =IFERROR(INDEX(Activos!$F$5:$F$504,MATCH("Activo no corriente|22",Activos!$I$5:$I$504,0)),"") | H69: =IFERROR(INDEX(Pasivos!$D$5:$D$504,MATCH("Pasivo corriente|26",Pasivos!$I$5:$I$504,0)),"") | I69: =IFERROR(INDEX(Pasivos!$F$5:$F$504,MATCH("Pasivo corriente|26",Pasivos!$I$5:$I$504,0)),"")
D70: =IFERROR(INDEX(Activos!$D$5:$D$504,MATCH("Activo no corriente|23",Activos!$I$5:$I$504,0)),"") | E70: =IFERROR(INDEX(Activos!$F$5:$F$504,MATCH("Activo no corriente|23",Activos!$I$5:$I$504,0)),"") | H70: =IFERROR(INDEX(Pasivos!$D$5:$D$504,MATCH("Pasivo corriente|27",Pasivos!$I$5:$I$504,0)),"") | I70: =IFERROR(INDEX(Pasivos!$F$5:$F$504,MATCH("Pasivo corriente|27",Pasivos!$I$5:$I$504,0)),"")
D71: =IFERROR(INDEX(Activos!$D$5:$D$504,MATCH("Activo no corriente|24",Activos!$I$5:$I$504,0)),"") | E71: =IFERROR(INDEX(Activos!$F$5:$F$504,MATCH("Activo no corriente|24",Activos!$I$5:$I$504,0)),"") | H71: =IFERROR(INDEX(Pasivos!$D$5:$D$504,MATCH("Pasivo corriente|28",Pasivos!$I$5:$I$504,0)),"") | I71: =IFERROR(INDEX(Pasivos!$F$5:$F$504,MATCH("Pasivo corriente|28",Pasivos!$I$5:$I$504,0)),"")
D72: =IFERROR(INDEX(Activos!$D$5:$D$504,MATCH("Activo no corriente|25",Activos!$I$5:$I$504,0)),"") | E72: =IFERROR(INDEX(Activos!$F$5:$F$504,MATCH("Activo no corriente|25",Activos!$I$5:$I$504,0)),"") | H72: =IFERROR(INDEX(Pasivos!$D$5:$D$504,MATCH("Pasivo corriente|29",Pasivos!$I$5:$I$504,0)),"") | I72: =IFERROR(INDEX(Pasivos!$F$5:$F$504,MATCH("Pasivo corriente|29",Pasivos!$I$5:$I$504,0)),"")
D73: =IFERROR(INDEX(Activos!$D$5:$D$504,MATCH("Activo no corriente|26",Activos!$I$5:$I$504,0)),"") | E73: =IFERROR(INDEX(Activos!$F$5:$F$504,MATCH("Activo no corriente|26",Activos!$I$5:$I$504,0)),"") | H73: =IFERROR(INDEX(Pasivos!$D$5:$D$504,MATCH("Pasivo corriente|30",Pasivos!$I$5:$I$504,0)),"") | I73: =IFERROR(INDEX(Pasivos!$F$5:$F$504,MATCH("Pasivo corriente|30",Pasivos!$I$5:$I$504,0)),"")
D74: =IFERROR(INDEX(Activos!$D$5:$D$504,MATCH("Activo no corriente|27",Activos!$I$5:$I$504,0)),"") | E74: =IFERROR(INDEX(Activos!$F$5:$F$504,MATCH("Activo no corriente|27",Activos!$I$5:$I$504,0)),"") | H74: =IFERROR(INDEX(Pasivos!$D$5:$D$504,MATCH("Pasivo corriente|31",Pasivos!$I$5:$I$504,0)),"") | I74: =IFERROR(INDEX(Pasivos!$F$5:$F$504,MATCH("Pasivo corriente|31",Pasivos!$I$5:$I$504,0)),"")
D75: =IFERROR(INDEX(Activos!$D$5:$D$504,MATCH("Activo no corriente|28",Activos!$I$5:$I$504,0)),"") | E75: =IFERROR(INDEX(Activos!$F$5:$F$504,MATCH("Activo no corriente|28",Activos!$I$5:$I$504,0)),"") | H75: =IFERROR(INDEX(Pasivos!$D$5:$D$504,MATCH("Pasivo corriente|32",Pasivos!$I$5:$I$504,0)),"") | I75: =IFERROR(INDEX(Pasivos!$F$5:$F$504,MATCH("Pasivo corriente|32",Pasivos!$I$5:$I$504,0)),"")
D76: =IFERROR(INDEX(Activos!$D$5:$D$504,MATCH("Activo no corriente|29",Activos!$I$5:$I$504,0)),"") | E76: =IFERROR(INDEX(Activos!$F$5:$F$504,MATCH("Activo no corriente|29",Activos!$I$5:$I$504,0)),"") | H76: =IFERROR(INDEX(Pasivos!$D$5:$D$504,MATCH("Pasivo corriente|33",Pasivos!$I$5:$I$504,0)),"") | I76: =IFERROR(INDEX(Pasivos!$F$5:$F$504,MATCH("Pasivo corriente|33",Pasivos!$I$5:$I$504,0)),"")
D77: =IFERROR(INDEX(Activos!$D$5:$D$504,MATCH("Activo no corriente|30",Activos!$I$5:$I$504,0)),"") | E77: =IFERROR(INDEX(Activos!$F$5:$F$504,MATCH("Activo no corriente|30",Activos!$I$5:$I$504,0)),"") | H77: =IFERROR(INDEX(Pasivos!$D$5:$D$504,MATCH("Pasivo corriente|34",Pasivos!$I$5:$I$504,0)),"") | I77: =IFERROR(INDEX(Pasivos!$F$5:$F$504,MATCH("Pasivo corriente|34",Pasivos!$I$5:$I$504,0)),"")
D78: =IFERROR(INDEX(Activos!$D$5:$D$504,MATCH("Activo no corriente|31",Activos!$I$5:$I$504,0)),"") | E78: =IFERROR(INDEX(Activos!$F$5:$F$504,MATCH("Activo no corriente|31",Activos!$I$5:$I$504,0)),"") | H78: =IFERROR(INDEX(Pasivos!$D$5:$D$504,MATCH("Pasivo corriente|35",Pasivos!$I$5:$I$504,0)),"") | I78: =IFERROR(INDEX(Pasivos!$F$5:$F$504,MATCH("Pasivo corriente|35",Pasivos!$I$5:$I$504,0)),"")
D79: =IFERROR(INDEX(Activos!$D$5:$D$504,MATCH("Activo no corriente|32",Activos!$I$5:$I$504,0)),"") | E79: =IFERROR(INDEX(Activos!$F$5:$F$504,MATCH("Activo no corriente|32",Activos!$I$5:$I$504,0)),"") | H79: TOTAL PASIVO CORRIENTE | I79: =SUMIF(Pasivos!$C$5:$C$504,"Pasivo corriente",Pasivos!$F$5:$F$504)
D80: =IFERROR(INDEX(Activos!$D$5:$D$504,MATCH("Activo no corriente|33",Activos!$I$5:$I$504,0)),"") | E80: =IFERROR(INDEX(Activos!$F$5:$F$504,MATCH("Activo no corriente|33",Activos!$I$5:$I$504,0)),"")
D81: =IFERROR(INDEX(Activos!$D$5:$D$504,MATCH("Activo no corriente|34",Activos!$I$5:$I$504,0)),"") | E81: =IFERROR(INDEX(Activos!$F$5:$F$504,MATCH("Activo no corriente|34",Activos!$I$5:$I$504,0)),"") | H81: C) PASIVO NO CORRIENTE | I81: Monto
D82: =IFERROR(INDEX(Activos!$D$5:$D$504,MATCH("Activo no corriente|35",Activos!$I$5:$I$504,0)),"") | E82: =IFERROR(INDEX(Activos!$F$5:$F$504,MATCH("Activo no corriente|35",Activos!$I$5:$I$504,0)),"") | H82: =IFERROR(INDEX(Pasivos!$D$5:$D$504,MATCH("Pasivo no corriente|1",Pasivos!$I$5:$I$504,0)),"") | I82: =IFERROR(INDEX(Pasivos!$F$5:$F$504,MATCH("Pasivo no corriente|1",Pasivos!$I$5:$I$504,0)),"")
D83: TOTAL ACTIVO NO CORRIENTE | E83: =SUMIF(Activos!$C$5:$C$504,"Activo no corriente",Activos!$F$5:$F$504) | H83: =IFERROR(INDEX(Pasivos!$D$5:$D$504,MATCH("Pasivo no corriente|2",Pasivos!$I$5:$I$504,0)),"") | I83: =IFERROR(INDEX(Pasivos!$F$5:$F$504,MATCH("Pasivo no corriente|2",Pasivos!$I$5:$I$504,0)),"")
H84: =IFERROR(INDEX(Pasivos!$D$5:$D$504,MATCH("Pasivo no corriente|3",Pasivos!$I$5:$I$504,0)),"") | I84: =IFERROR(INDEX(Pasivos!$F$5:$F$504,MATCH("Pasivo no corriente|3",Pasivos!$I$5:$I$504,0)),"")
D85: C) OTROS ACTIVOS | E85: Monto | H85: =IFERROR(INDEX(Pasivos!$D$5:$D$504,MATCH("Pasivo no corriente|4",Pasivos!$I$5:$I$504,0)),"") | I85: =IFERROR(INDEX(Pasivos!$F$5:$F$504,MATCH("Pasivo no corriente|4",Pasivos!$I$5:$I$504,0)),"")
D86: =IFERROR(INDEX(Activos!$D$5:$D$504,MATCH("Otros activos|1",Activos!$I$5:$I$504,0)),"") | E86: =IFERROR(INDEX(Activos!$F$5:$F$504,MATCH("Otros activos|1",Activos!$I$5:$I$504,0)),"") | H86: =IFERROR(INDEX(Pasivos!$D$5:$D$504,MATCH("Pasivo no corriente|5",Pasivos!$I$5:$I$504,0)),"") | I86: =IFERROR(INDEX(Pasivos!$F$5:$F$504,MATCH("Pasivo no corriente|5",Pasivos!$I$5:$I$504,0)),"")
D87: =IFERROR(INDEX(Activos!$D$5:$D$504,MATCH("Otros activos|2",Activos!$I$5:$I$504,0)),"") | E87: =IFERROR(INDEX(Activos!$F$5:$F$504,MATCH("Otros activos|2",Activos!$I$5:$I$504,0)),"") | H87: =IFERROR(INDEX(Pasivos!$D$5:$D$504,MATCH("Pasivo no corriente|6",Pasivos!$I$5:$I$504,0)),"") | I87: =IFERROR(INDEX(Pasivos!$F$5:$F$504,MATCH("Pasivo no corriente|6",Pasivos!$I$5:$I$504,0)),"")
D88: =IFERROR(INDEX(Activos!$D$5:$D$504,MATCH("Otros activos|3",Activos!$I$5:$I$504,0)),"") | E88: =IFERROR(INDEX(Activos!$F$5:$F$504,MATCH("Otros activos|3",Activos!$I$5:$I$504,0)),"") | H88: =IFERROR(INDEX(Pasivos!$D$5:$D$504,MATCH("Pasivo no corriente|7",Pasivos!$I$5:$I$504,0)),"") | I88: =IFERROR(INDEX(Pasivos!$F$5:$F$504,MATCH("Pasivo no corriente|7",Pasivos!$I$5:$I$504,0)),"")
D89: =IFERROR(INDEX(Activos!$D$5:$D$504,MATCH("Otros activos|4",Activos!$I$5:$I$504,0)),"") | E89: =IFERROR(INDEX(Activos!$F$5:$F$504,MATCH("Otros activos|4",Activos!$I$5:$I$504,0)),"") | H89: =IFERROR(INDEX(Pasivos!$D$5:$D$504,MATCH("Pasivo no corriente|8",Pasivos!$I$5:$I$504,0)),"") | I89: =IFERROR(INDEX(Pasivos!$F$5:$F$504,MATCH("Pasivo no corriente|8",Pasivos!$I$5:$I$504,0)),"")
D90: =IFERROR(INDEX(Activos!$D$5:$D$504,MATCH("Otros activos|5",Activos!$I$5:$I$504,0)),"") | E90: =IFERROR(INDEX(Activos!$F$5:$F$504,MATCH("Otros activos|5",Activos!$I$5:$I$504,0)),"") | H90: =IFERROR(INDEX(Pasivos!$D$5:$D$504,MATCH("Pasivo no corriente|9",Pasivos!$I$5:$I$504,0)),"") | I90: =IFERROR(INDEX(Pasivos!$F$5:$F$504,MATCH("Pasivo no corriente|9",Pasivos!$I$5:$I$504,0)),"")
D91: =IFERROR(INDEX(Activos!$D$5:$D$504,MATCH("Otros activos|6",Activos!$I$5:$I$504,0)),"") | E91: =IFERROR(INDEX(Activos!$F$5:$F$504,MATCH("Otros activos|6",Activos!$I$5:$I$504,0)),"") | H91: =IFERROR(INDEX(Pasivos!$D$5:$D$504,MATCH("Pasivo no corriente|10",Pasivos!$I$5:$I$504,0)),"") | I91: =IFERROR(INDEX(Pasivos!$F$5:$F$504,MATCH("Pasivo no corriente|10",Pasivos!$I$5:$I$504,0)),"")
D92: =IFERROR(INDEX(Activos!$D$5:$D$504,MATCH("Otros activos|7",Activos!$I$5:$I$504,0)),"") | E92: =IFERROR(INDEX(Activos!$F$5:$F$504,MATCH("Otros activos|7",Activos!$I$5:$I$504,0)),"") | H92: =IFERROR(INDEX(Pasivos!$D$5:$D$504,MATCH("Pasivo no corriente|11",Pasivos!$I$5:$I$504,0)),"") | I92: =IFERROR(INDEX(Pasivos!$F$5:$F$504,MATCH("Pasivo no corriente|11",Pasivos!$I$5:$I$504,0)),"")
D93: =IFERROR(INDEX(Activos!$D$5:$D$504,MATCH("Otros activos|8",Activos!$I$5:$I$504,0)),"") | E93: =IFERROR(INDEX(Activos!$F$5:$F$504,MATCH("Otros activos|8",Activos!$I$5:$I$504,0)),"") | H93: =IFERROR(INDEX(Pasivos!$D$5:$D$504,MATCH("Pasivo no corriente|12",Pasivos!$I$5:$I$504,0)),"") | I93: =IFERROR(INDEX(Pasivos!$F$5:$F$504,MATCH("Pasivo no corriente|12",Pasivos!$I$5:$I$504,0)),"")
D94: =IFERROR(INDEX(Activos!$D$5:$D$504,MATCH("Otros activos|9",Activos!$I$5:$I$504,0)),"") | E94: =IFERROR(INDEX(Activos!$F$5:$F$504,MATCH("Otros activos|9",Activos!$I$5:$I$504,0)),"") | H94: =IFERROR(INDEX(Pasivos!$D$5:$D$504,MATCH("Pasivo no corriente|13",Pasivos!$I$5:$I$504,0)),"") | I94: =IFERROR(INDEX(Pasivos!$F$5:$F$504,MATCH("Pasivo no corriente|13",Pasivos!$I$5:$I$504,0)),"")
D95: =IFERROR(INDEX(Activos!$D$5:$D$504,MATCH("Otros activos|10",Activos!$I$5:$I$504,0)),"") | E95: =IFERROR(INDEX(Activos!$F$5:$F$504,MATCH("Otros activos|10",Activos!$I$5:$I$504,0)),"") | H95: =IFERROR(INDEX(Pasivos!$D$5:$D$504,MATCH("Pasivo no corriente|14",Pasivos!$I$5:$I$504,0)),"") | I95: =IFERROR(INDEX(Pasivos!$F$5:$F$504,MATCH("Pasivo no corriente|14",Pasivos!$I$5:$I$504,0)),"")
D96: =IFERROR(INDEX(Activos!$D$5:$D$504,MATCH("Otros activos|11",Activos!$I$5:$I$504,0)),"") | E96: =IFERROR(INDEX(Activos!$F$5:$F$504,MATCH("Otros activos|11",Activos!$I$5:$I$504,0)),"") | H96: =IFERROR(INDEX(Pasivos!$D$5:$D$504,MATCH("Pasivo no corriente|15",Pasivos!$I$5:$I$504,0)),"") | I96: =IFERROR(INDEX(Pasivos!$F$5:$F$504,MATCH("Pasivo no corriente|15",Pasivos!$I$5:$I$504,0)),"")
D97: =IFERROR(INDEX(Activos!$D$5:$D$504,MATCH("Otros activos|12",Activos!$I$5:$I$504,0)),"") | E97: =IFERROR(INDEX(Activos!$F$5:$F$504,MATCH("Otros activos|12",Activos!$I$5:$I$504,0)),"") | H97: =IFERROR(INDEX(Pasivos!$D$5:$D$504,MATCH("Pasivo no corriente|16",Pasivos!$I$5:$I$504,0)),"") | I97: =IFERROR(INDEX(Pasivos!$F$5:$F$504,MATCH("Pasivo no corriente|16",Pasivos!$I$5:$I$504,0)),"")
D98: =IFERROR(INDEX(Activos!$D$5:$D$504,MATCH("Otros activos|13",Activos!$I$5:$I$504,0)),"") | E98: =IFERROR(INDEX(Activos!$F$5:$F$504,MATCH("Otros activos|13",Activos!$I$5:$I$504,0)),"") | H98: =IFERROR(INDEX(Pasivos!$D$5:$D$504,MATCH("Pasivo no corriente|17",Pasivos!$I$5:$I$504,0)),"") | I98: =IFERROR(INDEX(Pasivos!$F$5:$F$504,MATCH("Pasivo no corriente|17",Pasivos!$I$5:$I$504,0)),"")
D99: =IFERROR(INDEX(Activos!$D$5:$D$504,MATCH("Otros activos|14",Activos!$I$5:$I$504,0)),"") | E99: =IFERROR(INDEX(Activos!$F$5:$F$504,MATCH("Otros activos|14",Activos!$I$5:$I$504,0)),"") | H99: =IFERROR(INDEX(Pasivos!$D$5:$D$504,MATCH("Pasivo no corriente|18",Pasivos!$I$5:$I$504,0)),"") | I99: =IFERROR(INDEX(Pasivos!$F$5:$F$504,MATCH("Pasivo no corriente|18",Pasivos!$I$5:$I$504,0)),"")
D100: =IFERROR(INDEX(Activos!$D$5:$D$504,MATCH("Otros activos|15",Activos!$I$5:$I$504,0)),"") | E100: =IFERROR(INDEX(Activos!$F$5:$F$504,MATCH("Otros activos|15",Activos!$I$5:$I$504,0)),"") | H100: =IFERROR(INDEX(Pasivos!$D$5:$D$504,MATCH("Pasivo no corriente|19",Pasivos!$I$5:$I$504,0)),"") | I100: =IFERROR(INDEX(Pasivos!$F$5:$F$504,MATCH("Pasivo no corriente|19",Pasivos!$I$5:$I$504,0)),"")
D101: TOTAL OTROS ACTIVOS | E101: =SUMIF(Activos!$C$5:$C$504,"Otros activos",Activos!$F$5:$F$504) | H101: =IFERROR(INDEX(Pasivos!$D$5:$D$504,MATCH("Pasivo no corriente|20",Pasivos!$I$5:$I$504,0)),"") | I101: =IFERROR(INDEX(Pasivos!$F$5:$F$504,MATCH("Pasivo no corriente|20",Pasivos!$I$5:$I$504,0)),"")
H102: =IFERROR(INDEX(Pasivos!$D$5:$D$504,MATCH("Pasivo no corriente|21",Pasivos!$I$5:$I$504,0)),"") | I102: =IFERROR(INDEX(Pasivos!$F$5:$F$504,MATCH("Pasivo no corriente|21",Pasivos!$I$5:$I$504,0)),"")
...

Sheet Dashboard
B1: DASHBOARD BALANCE GENERAL PYME
B2: Indicadores simples para revisar activos, deuda, patrimonio y equilibrio del balance.
B4: Total activos | E4: Total pasivos | H4: Total patrimonio | K4: Diferencia | O4: En esta hoja no se debe modificar, es el resultado de los valores y resultados de las paginas siguientes
B5: ='Balance General'!M14 | E5: ='Balance General'!P13 | H5: ='Balance General'!I41 | K5: ='Balance General'!M16
B8: Capital de trabajo | E8: Razón corriente | H8: Endeudamiento | K8: Estado
B9: ='Balance General'!E45-'Balance General'!I79 | E9: =IFERROR('Balance General'!E45/'Balance General'!I79,0) | H9: =IFERROR('Balance General'!P13/'Balance General'!M14,0) | K9: ='Balance General'!P17
B12: Composición activos | C12: Monto | E12: Financiamiento | F12: Monto
B13: Activo corriente | C13: ='Balance General'!E45 | E13: Pasivos | F13: ='Balance General'!P13
B14: Activo no corriente | C14: ='Balance General'!E83 | E14: Patrimonio | F14: ='Balance General'!I41
B15: Otros activos | C15: ='Balance General'!E101
B17: Resultado ejercicio | C17: Monto
B18: Ingresos | C18: ='Resultado Ejercicio'!E5
B19: Costos | C19: ='Resultado Ejercicio'!E6
B20: Gastos | C20: ='Resultado Ejercicio'!E7
B21: Resultado | C21: ='Resultado Ejercicio'!E8
E22: Lectura rápida
E23: El gráfico izquierdo muestra cómo se componen los activos. El gráfico derecho muestra cómo se financia la empresa entre pasivos y patrimonio. Si el balance no cuadra, revisa activos, pasivos, patrimonio y resultado del ejercicio.
