Workbook

Sheet Inicio
B1: CONTROL PYME: INGRESOS, GASTOS Y GANANCIA
B2: Registra movimientos diarios y revisa automáticamente cuánto gana o pierde tu negocio cada mes.
B4: Promesa de la plantilla
B5: Anota cada ingreso, gasto o ahorro del mes y el Excel calcula automáticamente el resumen, la ganancia y los gráficos.
C8: Paso | D8: Acción | E8: Resultado | G8: Color | H8: Significado | J8: Uso rápido
C9: 1 | D9: Configura categorías | E9: Edita la hoja Categorias según tu negocio. | G9: Pastel | H9: Celdas para rellenar | J9: 1) Ajusta categorías. 2) Registra fecha, categoría, descripción y monto. 3) Revisa Resumen Mensual y Dashboard. No borres las columnas automáticas: Mes, Tipo, Ingreso auto, Gasto auto y Reserva auto.
C10: 2 | D10: Registra movimientos | E10: Anota cada venta, gasto o ahorro en Registro Mensual. | G10: Gris perla | H10: Celdas automáticas
C11: 3 | D11: Revisa resultados | E11: El Resumen Mensual calcula ingresos, gastos, reserva y ganancia. | G11: Dorado | H11: Totales importantes
C12: 4 | D12: Mira el dashboard | E12: Visualiza gráficos y alertas para tomar mejores decisiones. | G12: Rojo vino | H12: Subtítulos y alertas
G13: Negro | H13: Encabezados

Sheet Registro Mensual
B1: REGISTRO MENSUAL
B2: Anota aquí cada ingreso, gasto o ahorro. El resumen y dashboard se actualizan solos.
B4: Mes a revisar | D4: Ingresos mes | F4: Gastos mes | H4: Reserva / ahorro mes | J4: Ganancia disponible | M4: ¿Qué se hace en esta hoja?
A5: Filtro, selecciona el mes en el que te encuentras→ | B5: =Dashboard!$B$5 -> Enero | D5: =SUMIFS($H$9:$H$1008,$C$9:$C$1008,$B$5) -> 1450000 | F5: =SUMIFS($I$9:$I$1008,$C$9:$C$1008,$B$5) -> 2330000 | H5: =SUMIFS($J$9:$J$1008,$C$9:$C$1008,$B$5) -> 0 | J5: =D5-F5-H5 -> -880000 | M5: Esta es la hoja que más se rellena. Escribe la Fecha, la Categoría, la Descripción y el Monto. El Mes, el Tipo, el Ingreso auto, el Gasto auto y la Reserva auto se calculan solos. El resumen superior usa el mismo mes seleccionado en Dashboard K5.
B8: Fecha | C8: Mes | D8: Categoría | E8: Tipo | F8: Descripción | G8: Monto | H8: Ingreso auto | I8: Gasto auto | J8: Reserva auto | K8: Nota
B9: 46027 | C9: =IF(B9="","",CHOOSE(MONTH(B9),"Enero","Febrero","Marzo","Abril","Mayo","Junio","Julio","Agosto","Septiembre","Octubre","Noviembre","Diciembre")) -> Enero | D9: Ventas | E9: =IF(D9="","",IFERROR(VLOOKUP(D9,Categorias!$B$5:$C$200,2,FALSE),"Revisar")) -> Ingreso | F9: Venta local | G9: 1450000 | H9: =IF($E9="Ingreso",$G9,0) -> 1450000 | I9: =IF($E9="Gasto",$G9,0) -> 0 | J9: =IF($E9="Reserva",$G9,0) -> 0 | K9: Ventas del día
B10: 46028 | C10: =IF(B10="","",CHOOSE(MONTH(B10),"Enero","Febrero","Marzo","Abril","Mayo","Junio","Julio","Agosto","Septiembre","Octubre","Noviembre","Diciembre")) -> Enero | D10: Arriendo | E10: =IF(D10="","",IFERROR(VLOOKUP(D10,Categorias!$B$5:$C$200,2,FALSE),"Revisar")) -> Gasto | F10: Arriendo local | G10: 700000 | H10: =IF($E10="Ingreso",$G10,0) -> 0 | I10: =IF($E10="Gasto",$G10,0) -> 700000 | J10: =IF($E10="Reserva",$G10,0) -> 0 | K10: Pago fijo mensual
B11: 46030 | C11: =IF(B11="","",CHOOSE(MONTH(B11),"Enero","Febrero","Marzo","Abril","Mayo","Junio","Julio","Agosto","Septiembre","Octubre","Noviembre","Diciembre")) -> Enero | D11: Servicios básicos | E11: =IF(D11="","",IFERROR(VLOOKUP(D11,Categorias!$B$5:$C$200,2,FALSE),"Revisar")) -> Gasto | F11: Luz y agua | G11: 130000 | H11: =IF($E11="Ingreso",$G11,0) -> 0 | I11: =IF($E11="Gasto",$G11,0) -> 130000 | J11: =IF($E11="Reserva",$G11,0) -> 0
B12: 46032 | C12: =IF(B12="","",CHOOSE(MONTH(B12),"Enero","Febrero","Marzo","Abril","Mayo","Junio","Julio","Agosto","Septiembre","Octubre","Noviembre","Diciembre")) -> Enero | D12: Publicidad | E12: =IF(D12="","",IFERROR(VLOOKUP(D12,Categorias!$B$5:$C$200,2,FALSE),"Revisar")) -> Gasto | F12: Campaña redes | G12: 1500000 | H12: =IF($E12="Ingreso",$G12,0) -> 0 | I12: =IF($E12="Gasto",$G12,0) -> 1500000 | J12: =IF($E12="Reserva",$G12,0) -> 0
C13: =IF(B13="","",CHOOSE(MONTH(B13),"Enero","Febrero","Marzo","Abril","Mayo","Junio","Julio","Agosto","Septiembre","Octubre","Noviembre","Diciembre")) | E13: =IF(D13="","",IFERROR(VLOOKUP(D13,Categorias!$B$5:$C$200,2,FALSE),"Revisar")) | H13: =IF($E13="Ingreso",$G13,0) -> 0 | I13: =IF($E13="Gasto",$G13,0) -> 0 | J13: =IF($E13="Reserva",$G13,0) -> 0
C14: =IF(B14="","",CHOOSE(MONTH(B14),"Enero","Febrero","Marzo","Abril","Mayo","Junio","Julio","Agosto","Septiembre","Octubre","Noviembre","Diciembre")) | E14: =IF(D14="","",IFERROR(VLOOKUP(D14,Categorias!$B$5:$C$200,2,FALSE),"Revisar")) | H14: =IF($E14="Ingreso",$G14,0) -> 0 | I14: =IF($E14="Gasto",$G14,0) -> 0 | J14: =IF($E14="Reserva",$G14,0) -> 0
C15: =IF(B15="","",CHOOSE(MONTH(B15),"Enero","Febrero","Marzo","Abril","Mayo","Junio","Julio","Agosto","Septiembre","Octubre","Noviembre","Diciembre")) | E15: =IF(D15="","",IFERROR(VLOOKUP(D15,Categorias!$B$5:$C$200,2,FALSE),"Revisar")) | H15: =IF($E15="Ingreso",$G15,0) -> 0 | I15: =IF($E15="Gasto",$G15,0) -> 0 | J15: =IF($E15="Reserva",$G15,0) -> 0
C16: =IF(B16="","",CHOOSE(MONTH(B16),"Enero","Febrero","Marzo","Abril","Mayo","Junio","Julio","Agosto","Septiembre","Octubre","Noviembre","Diciembre")) | E16: =IF(D16="","",IFERROR(VLOOKUP(D16,Categorias!$B$5:$C$200,2,FALSE),"Revisar")) | H16: =IF($E16="Ingreso",$G16,0) -> 0 | I16: =IF($E16="Gasto",$G16,0) -> 0 | J16: =IF($E16="Reserva",$G16,0) -> 0
C17: =IF(B17="","",CHOOSE(MONTH(B17),"Enero","Febrero","Marzo","Abril","Mayo","Junio","Julio","Agosto","Septiembre","Octubre","Noviembre","Diciembre")) | E17: =IF(D17="","",IFERROR(VLOOKUP(D17,Categorias!$B$5:$C$200,2,FALSE),"Revisar")) | H17: =IF($E17="Ingreso",$G17,0) -> 0 | I17: =IF($E17="Gasto",$G17,0) -> 0 | J17: =IF($E17="Reserva",$G17,0) -> 0
C18: =IF(B18="","",CHOOSE(MONTH(B18),"Enero","Febrero","Marzo","Abril","Mayo","Junio","Julio","Agosto","Septiembre","Octubre","Noviembre","Diciembre")) | E18: =IF(D18="","",IFERROR(VLOOKUP(D18,Categorias!$B$5:$C$200,2,FALSE),"Revisar")) | H18: =IF($E18="Ingreso",$G18,0) -> 0 | I18: =IF($E18="Gasto",$G18,0) -> 0 | J18: =IF($E18="Reserva",$G18,0) -> 0
C19: =IF(B19="","",CHOOSE(MONTH(B19),"Enero","Febrero","Marzo","Abril","Mayo","Junio","Julio","Agosto","Septiembre","Octubre","Noviembre","Diciembre")) | E19: =IF(D19="","",IFERROR(VLOOKUP(D19,Categorias!$B$5:$C$200,2,FALSE),"Revisar")) | H19: =IF($E19="Ingreso",$G19,0) -> 0 | I19: =IF($E19="Gasto",$G19,0) -> 0 | J19: =IF($E19="Reserva",$G19,0) -> 0
C20: =IF(B20="","",CHOOSE(MONTH(B20),"Enero","Febrero","Marzo","Abril","Mayo","Junio","Julio","Agosto","Septiembre","Octubre","Noviembre","Diciembre")) | E20: =IF(D20="","",IFERROR(VLOOKUP(D20,Categorias!$B$5:$C$200,2,FALSE),"Revisar")) | H20: =IF($E20="Ingreso",$G20,0) -> 0 | I20: =IF($E20="Gasto",$G20,0) -> 0 | J20: =IF($E20="Reserva",$G20,0) -> 0
C21: =IF(B21="","",CHOOSE(MONTH(B21),"Enero","Febrero","Marzo","Abril","Mayo","Junio","Julio","Agosto","Septiembre","Octubre","Noviembre","Diciembre")) | E21: =IF(D21="","",IFERROR(VLOOKUP(D21,Categorias!$B$5:$C$200,2,FALSE),"Revisar")) | H21: =IF($E21="Ingreso",$G21,0) -> 0 | I21: =IF($E21="Gasto",$G21,0) -> 0 | J21: =IF($E21="Reserva",$G21,0) -> 0
C22: =IF(B22="","",CHOOSE(MONTH(B22),"Enero","Febrero","Marzo","Abril","Mayo","Junio","Julio","Agosto","Septiembre","Octubre","Noviembre","Diciembre")) | E22: =IF(D22="","",IFERROR(VLOOKUP(D22,Categorias!$B$5:$C$200,2,FALSE),"Revisar")) | H22: =IF($E22="Ingreso",$G22,0) -> 0 | I22: =IF($E22="Gasto",$G22,0) -> 0 | J22: =IF($E22="Reserva",$G22,0) -> 0
C23: =IF(B23="","",CHOOSE(MONTH(B23),"Enero","Febrero","Marzo","Abril","Mayo","Junio","Julio","Agosto","Septiembre","Octubre","Noviembre","Diciembre")) | E23: =IF(D23="","",IFERROR(VLOOKUP(D23,Categorias!$B$5:$C$200,2,FALSE),"Revisar")) | H23: =IF($E23="Ingreso",$G23,0) -> 0 | I23: =IF($E23="Gasto",$G23,0) -> 0 | J23: =IF($E23="Reserva",$G23,0) -> 0
C24: =IF(B24="","",CHOOSE(MONTH(B24),"Enero","Febrero","Marzo","Abril","Mayo","Junio","Julio","Agosto","Septiembre","Octubre","Noviembre","Diciembre")) | E24: =IF(D24="","",IFERROR(VLOOKUP(D24,Categorias!$B$5:$C$200,2,FALSE),"Revisar")) | H24: =IF($E24="Ingreso",$G24,0) -> 0 | I24: =IF($E24="Gasto",$G24,0) -> 0 | J24: =IF($E24="Reserva",$G24,0) -> 0
... C1008: =IF(B1008="","",CHOOSE(MONTH(B1008),"Enero","Febrero","Marzo","Abril","Mayo","Junio","Julio","Agosto","Septiembre","Octubre","Noviembre","Diciembre")) | E1008: =IF(D1008="","",IFERROR(VLOOKUP(D1008,Categorias!$B$5:$C$200,2,FALSE),"Revisar")) | H1008: =IF($E1008="Ingreso",$G1008,0) -> 0 | I1008: =IF($E1008="Gasto",$G1008,0) -> 0 | J1008: =IF($E1008="Reserva",$G1008,0) -> 0

Sheet Categorias
A1: CATEGORÍAS
A2: Edita las categorías. El tipo debe ser Ingreso, Gasto o Reserva.
B4: Categoría | C4: Tipo | E4: Nota | Z4: Orden gasto mes Dashboard | AA4: Orden ingreso mes Dashboard | AB4: Categoría gasto gráfico | AC4: Monto gasto gráfico
B5: Ventas | C5: Ingreso | E5: Puedes agregar nuevas categorías debajo. Usa exactamente estos tipos: Ingreso, Gasto o Reserva. Así el Registro Mensual podrá calcular automáticamente cada movimiento. | Z5: =IF(AND($B5<>"",$C5="Gasto"),COUNT($Z$4:Z4)+1,"") | AA5: =IF(AND($B5<>"",$C5="Ingreso",SUMIFS('Registro Mensual'!$H$9:$H$1008,'Registro Mensual'!$C$9:$C$1008,Dashboard!$B$5,'Registro Mensual'!$D$9:$D$1008,$B5)>0),COUNT($AA$4:AA4)+1,"") -> 1 | AB5: =IFERROR(INDEX($B$5:$B$200,MATCH(ROWS($AB$5:AB5),$Z$5:$Z$200,0)),"") -> Arriendo | AC5: =IF($AB5="","",SUMIFS('Registro Mensual'!$I$9:$I$1008,'Registro Mensual'!$C$9:$C$1008,Dashboard!$B$5,'Registro Mensual'!$D$9:$D$1008,$AB5)) -> 700000
B6: Servicios | C6: Ingreso | Z6: =IF(AND($B6<>"",$C6="Gasto"),COUNT($Z$4:Z5)+1,"") | AA6: =IF(AND($B6<>"",$C6="Ingreso",SUMIFS('Registro Mensual'!$H$9:$H$1008,'Registro Mensual'!$C$9:$C$1008,Dashboard!$B$5,'Registro Mensual'!$D$9:$D$1008,$B6)>0),COUNT($AA$4:AA5)+1,"") | AB6: =IFERROR(INDEX($B$5:$B$200,MATCH(ROWS($AB$5:AB6),$Z$5:$Z$200,0)),"") -> Sueldos | AC6: =IF($AB6="","",SUMIFS('Registro Mensual'!$I$9:$I$1008,'Registro Mensual'!$C$9:$C$1008,Dashboard!$B$5,'Registro Mensual'!$D$9:$D$1008,$AB6)) -> 0
B7: Abonos de clientes | C7: Ingreso | Z7: =IF(AND($B7<>"",$C7="Gasto"),COUNT($Z$4:Z6)+1,"") | AA7: =IF(AND($B7<>"",$C7="Ingreso",SUMIFS('Registro Mensual'!$H$9:$H$1008,'Registro Mensual'!$C$9:$C$1008,Dashboard!$B$5,'Registro Mensual'!$D$9:$D$1008,$B7)>0),COUNT($AA$4:AA6)+1,"") | AB7: =IFERROR(INDEX($B$5:$B$200,MATCH(ROWS($AB$5:AB7),$Z$5:$Z$200,0)),"") -> Servicios básicos | AC7: =IF($AB7="","",SUMIFS('Registro Mensual'!$I$9:$I$1008,'Registro Mensual'!$C$9:$C$1008,Dashboard!$B$5,'Registro Mensual'!$D$9:$D$1008,$AB7)) -> 130000
B8: Venta online | C8: Ingreso | Z8: =IF(AND($B8<>"",$C8="Gasto"),COUNT($Z$4:Z7)+1,"") | AA8: =IF(AND($B8<>"",$C8="Ingreso",SUMIFS('Registro Mensual'!$H$9:$H$1008,'Registro Mensual'!$C$9:$C$1008,Dashboard!$B$5,'Registro Mensual'!$D$9:$D$1008,$B8)>0),COUNT($AA$4:AA7)+1,"") | AB8: =IFERROR(INDEX($B$5:$B$200,MATCH(ROWS($AB$5:AB8),$Z$5:$Z$200,0)),"") -> Insumos | AC8: =IF($AB8="","",SUMIFS('Registro Mensual'!$I$9:$I$1008,'Registro Mensual'!$C$9:$C$1008,Dashboard!$B$5,'Registro Mensual'!$D$9:$D$1008,$AB8)) -> 0
B9: Otros ingresos | C9: Ingreso | Z9: =IF(AND($B9<>"",$C9="Gasto"),COUNT($Z$4:Z8)+1,"") | AA9: =IF(AND($B9<>"",$C9="Ingreso",SUMIFS('Registro Mensual'!$H$9:$H$1008,'Registro Mensual'!$C$9:$C$1008,Dashboard!$B$5,'Registro Mensual'!$D$9:$D$1008,$B9)>0),COUNT($AA$4:AA8)+1,"") | AB9: =IFERROR(INDEX($B$5:$B$200,MATCH(ROWS($AB$5:AB9),$Z$5:$Z$200,0)),"") -> Transporte | AC9: =IF($AB9="","",SUMIFS('Registro Mensual'!$I$9:$I$1008,'Registro Mensual'!$C$9:$C$1008,Dashboard!$B$5,'Registro Mensual'!$D$9:$D$1008,$AB9)) -> 0
B10: Arriendo | C10: Gasto | E10: ¿Qué se hace en esta hoja? | Z10: =IF(AND($B10<>"",$C10="Gasto"),COUNT($Z$4:Z9)+1,"") -> 1 | AA10: =IF(AND($B10<>"",$C10="Ingreso",SUMIFS('Registro Mensual'!$H$9:$H$1008,'Registro Mensual'!$C$9:$C$1008,Dashboard!$B$5,'Registro Mensual'!$D$9:$D$1008,$B10)>0),COUNT($AA$4:AA9)+1,"") | AB10: =IFERROR(INDEX($B$5:$B$200,MATCH(ROWS($AB$5:AB10),$Z$5:$Z$200,0)),"") -> Publicidad | AC10: =IF($AB10="","",SUMIFS('Registro Mensual'!$I$9:$I$1008,'Registro Mensual'!$C$9:$C$1008,Dashboard!$B$5,'Registro Mensual'!$D$9:$D$1008,$AB10)) -> 1500000
B11: Sueldos | C11: Gasto | E11: Aquí se escriben las categorías que usará el negocio. En la columna B va el nombre, por ejemplo: Ventas, Arriendo o Insumos. En la columna C va el tipo exacto: Ingreso, Gasto o Reserva. Después, esas categorías aparecen en el Registro Mensual y el tipo se completa solo. | Z11: =IF(AND($B11<>"",$C11="Gasto"),COUNT($Z$4:Z10)+1,"") -> 2 | AA11: =IF(AND($B11<>"",$C11="Ingreso",SUMIFS('Registro Mensual'!$H$9:$H$1008,'Registro Mensual'!$C$9:$C$1008,Dashboard!$B$5,'Registro Mensual'!$D$9:$D$1008,$B11)>0),COUNT($AA$4:AA10)+1,"") | AB11: =IFERROR(INDEX($B$5:$B$200,MATCH(ROWS($AB$5:AB11),$Z$5:$Z$200,0)),"") -> Internet | AC11: =IF($AB11="","",SUMIFS('Registro Mensual'!$I$9:$I$1008,'Registro Mensual'!$C$9:$C$1008,Dashboard!$B$5,'Registro Mensual'!$D$9:$D$1008,$AB11)) -> 0
B12: Servicios básicos | C12: Gasto | Z12: =IF(AND($B12<>"",$C12="Gasto"),COUNT($Z$4:Z11)+1,"") -> 3 | AA12: =IF(AND($B12<>"",$C12="Ingreso",SUMIFS('Registro Mensual'!$H$9:$H$1008,'Registro Mensual'!$C$9:$C$1008,Dashboard!$B$5,'Registro Mensual'!$D$9:$D$1008,$B12)>0),COUNT($AA$4:AA11)+1,"") | AB12: =IFERROR(INDEX($B$5:$B$200,MATCH(ROWS($AB$5:AB12),$Z$5:$Z$200,0)),"") -> Contabilidad | AC12: =IF($AB12="","",SUMIFS('Registro Mensual'!$I$9:$I$1008,'Registro Mensual'!$C$9:$C$1008,Dashboard!$B$5,'Registro Mensual'!$D$9:$D$1008,$AB12)) -> 0
B13: Insumos | C13: Gasto | Z13: =IF(AND($B13<>"",$C13="Gasto"),COUNT($Z$4:Z12)+1,"") -> 4 | AA13: =IF(AND($B13<>"",$C13="Ingreso",SUMIFS('Registro Mensual'!$H$9:$H$1008,'Registro Mensual'!$C$9:$C$1008,Dashboard!$B$5,'Registro Mensual'!$D$9:$D$1008,$B13)>0),COUNT($AA$4:AA12)+1,"") | AB13: =IFERROR(INDEX($B$5:$B$200,MATCH(ROWS($AB$5:AB13),$Z$5:$Z$200,0)),"") -> Patente / permisos | AC13: =IF($AB13="","",SUMIFS('Registro Mensual'!$I$9:$I$1008,'Registro Mensual'!$C$9:$C$1008,Dashboard!$B$5,'Registro Mensual'!$D$9:$D$1008,$AB13)) -> 0
B14: Transporte | C14: Gasto | Z14: =IF(AND($B14<>"",$C14="Gasto"),COUNT($Z$4:Z13)+1,"") -> 5 | AA14: =IF(AND($B14<>"",$C14="Ingreso",SUMIFS('Registro Mensual'!$H$9:$H$1008,'Registro Mensual'!$C$9:$C$1008,Dashboard!$B$5,'Registro Mensual'!$D$9:$D$1008,$B14)>0),COUNT($AA$4:AA13)+1,"") | AB14: =IFERROR(INDEX($B$5:$B$200,MATCH(ROWS($AB$5:AB14),$Z$5:$Z$200,0)),"") -> Mantenimiento | AC14: =IF($AB14="","",SUMIFS('Registro Mensual'!$I$9:$I$1008,'Registro Mensual'!$C$9:$C$1008,Dashboard!$B$5,'Registro Mensual'!$D$9:$D$1008,$AB14)) -> 0
B15: Publicidad | C15: Gasto | Z15: =IF(AND($B15<>"",$C15="Gasto"),COUNT($Z$4:Z14)+1,"") -> 6 | AA15: =IF(AND($B15<>"",$C15="Ingreso",SUMIFS('Registro Mensual'!$H$9:$H$1008,'Registro Mensual'!$C$9:$C$1008,Dashboard!$B$5,'Registro Mensual'!$D$9:$D$1008,$B15)>0),COUNT($AA$4:AA14)+1,"") | AB15: =IFERROR(INDEX($B$5:$B$200,MATCH(ROWS($AB$5:AB15),$Z$5:$Z$200,0)),"") -> Comisiones | AC15: =IF($AB15="","",SUMIFS('Registro Mensual'!$I$9:$I$1008,'Registro Mensual'!$C$9:$C$1008,Dashboard!$B$5,'Registro Mensual'!$D$9:$D$1008,$AB15)) -> 0
B16: Internet | C16: Gasto | Z16: =IF(AND($B16<>"",$C16="Gasto"),COUNT($Z$4:Z15)+1,"") -> 7 | AA16: =IF(AND($B16<>"",$C16="Ingreso",SUMIFS('Registro Mensual'!$H$9:$H$1008,'Registro Mensual'!$C$9:$C$1008,Dashboard!$B$5,'Registro Mensual'!$D$9:$D$1008,$B16)>0),COUNT($AA$4:AA15)+1,"") | AB16: =IFERROR(INDEX($B$5:$B$200,MATCH(ROWS($AB$5:AB16),$Z$5:$Z$200,0)),"") -> Delivery | AC16: =IF($AB16="","",SUMIFS('Registro Mensual'!$I$9:$I$1008,'Registro Mensual'!$C$9:$C$1008,Dashboard!$B$5,'Registro Mensual'!$D$9:$D$1008,$AB16)) -> 0
B17: Contabilidad | C17: Gasto | Z17: =IF(AND($B17<>"",$C17="Gasto"),COUNT($Z$4:Z16)+1,"") -> 8 | AA17: =IF(AND($B17<>"",$C17="Ingreso",SUMIFS('Registro Mensual'!$H$9:$H$1008,'Registro Mensual'!$C$9:$C$1008,Dashboard!$B$5,'Registro Mensual'!$D$9:$D$1008,$B17)>0),COUNT($AA$4:AA16)+1,"") | AB17: =IFERROR(INDEX($B$5:$B$200,MATCH(ROWS($AB$5:AB17),$Z$5:$Z$200,0)),"") -> Otros gastos | AC17: =IF($AB17="","",SUMIFS('Registro Mensual'!$I$9:$I$1008,'Registro Mensual'!$C$9:$C$1008,Dashboard!$B$5,'Registro Mensual'!$D$9:$D$1008,$AB17)) -> 0
B18: Patente / permisos | C18: Gasto | Z18: =IF(AND($B18<>"",$C18="Gasto"),COUNT($Z$4:Z17)+1,"") -> 9 | AA18: =IF(AND($B18<>"",$C18="Ingreso",SUMIFS('Registro Mensual'!$H$9:$H$1008,'Registro Mensual'!$C$9:$C$1008,Dashboard!$B$5,'Registro Mensual'!$D$9:$D$1008,$B18)>0),COUNT($AA$4:AA17)+1,"") | AB18: =IFERROR(INDEX($B$5:$B$200,MATCH(ROWS($AB$5:AB18),$Z$5:$Z$200,0)),"") | AC18: =IF($AB18="","",SUMIFS('Registro Mensual'!$I$9:$I$1008,'Registro Mensual'!$C$9:$C$1008,Dashboard!$B$5,'Registro Mensual'!$D$9:$D$1008,$AB18))
B19: Mantenimiento | C19: Gasto | Z19: =IF(AND($B19<>"",$C19="Gasto"),COUNT($Z$4:Z18)+1,"") -> 10 | AA19: =IF(AND($B19<>"",$C19="Ingreso",SUMIFS('Registro Mensual'!$H$9:$H$1008,'Registro Mensual'!$C$9:$C$1008,Dashboard!$B$5,'Registro Mensual'!$D$9:$D$1008,$B19)>0),COUNT($AA$4:AA18)+1,"") | AB19: =IFERROR(INDEX($B$5:$B$200,MATCH(ROWS($AB$5:AB19),$Z$5:$Z$200,0)),"") | AC19: =IF($AB19="","",SUMIFS('Registro Mensual'!$I$9:$I$1008,'Registro Mensual'!$C$9:$C$1008,Dashboard!$B$5,'Registro Mensual'!$D$9:$D$1008,$AB19))
B20: Comisiones | C20: Gasto | Z20: =IF(AND($B20<>"",$C20="Gasto"),COUNT($Z$4:Z19)+1,"") -> 11 | AA20: =IF(AND($B20<>"",$C20="Ingreso",SUMIFS('Registro Mensual'!$H$9:$H$1008,'Registro Mensual'!$C$9:$C$1008,Dashboard!$B$5,'Registro Mensual'!$D$9:$D$1008,$B20)>0),COUNT($AA$4:AA19)+1,"") | AB20: =IFERROR(INDEX($B$5:$B$200,MATCH(ROWS($AB$5:AB20),$Z$5:$Z$200,0)),"") | AC20: =IF($AB20="","",SUMIFS('Registro Mensual'!$I$9:$I$1008,'Registro Mensual'!$C$9:$C$1008,Dashboard!$B$5,'Registro Mensual'!$D$9:$D$1008,$AB20))
B21: Delivery | C21: Gasto | Z21: =IF(AND($B21<>"",$C21="Gasto"),COUNT($Z$4:Z20)+1,"") -> 12 | AA21: =IF(AND($B21<>"",$C21="Ingreso",SUMIFS('Registro Mensual'!$H$9:$H$1008,'Registro Mensual'!$C$9:$C$1008,Dashboard!$B$5,'Registro Mensual'!$D$9:$D$1008,$B21)>0),COUNT($AA$4:AA20)+1,"") | AB21: =IFERROR(INDEX($B$5:$B$200,MATCH(ROWS($AB$5:AB21),$Z$5:$Z$200,0)),"") | AC21: =IF($AB21="","",SUMIFS('Registro Mensual'!$I$9:$I$1008,'Registro Mensual'!$C$9:$C$1008,Dashboard!$B$5,'Registro Mensual'!$D$9:$D$1008,$AB21))
B22: Otros gastos | C22: Gasto | Z22: =IF(AND($B22<>"",$C22="Gasto"),COUNT($Z$4:Z21)+1,"") -> 13 | AA22: =IF(AND($B22<>"",$C22="Ingreso",SUMIFS('Registro Mensual'!$H$9:$H$1008,'Registro Mensual'!$C$9:$C$1008,Dashboard!$B$5,'Registro Mensual'!$D$9:$D$1008,$B22)>0),COUNT($AA$4:AA21)+1,"") | AB22: =IFERROR(INDEX($B$5:$B$200,MATCH(ROWS($AB$5:AB22),$Z$5:$Z$200,0)),"") | AC22: =IF($AB22="","",SUMIFS('Registro Mensual'!$I$9:$I$1008,'Registro Mensual'!$C$9:$C$1008,Dashboard!$B$5,'Registro Mensual'!$D$9:$D$1008,$AB22))
B23: Reserva de caja | C23: Reserva | Z23: =IF(AND($B23<>"",$C23="Gasto"),COUNT($Z$4:Z22)+1,"") | AA23: =IF(AND($B23<>"",$C23="Ingreso",SUMIFS('Registro Mensual'!$H$9:$H$1008,'Registro Mensual'!$C$9:$C$1008,Dashboard!$B$5,'Registro Mensual'!$D$9:$D$1008,$B23)>0),COUNT($AA$4:AA22)+1,"") | AB23: =IFERROR(INDEX($B$5:$B$200,MATCH(ROWS($AB$5:AB23),$Z$5:$Z$200,0)),"") | AC23: =IF($AB23="","",SUMIFS('Registro Mensual'!$I$9:$I$1008,'Registro Mensual'!$C$9:$C$1008,Dashboard!$B$5,'Registro Mensual'!$D$9:$D$1008,$AB23))
... B25: Ahorro para inversión | C25: Reserva | Z25: =IF(AND($B25<>"",$C25="Gasto"),COUNT($Z$4:Z24)+1,"") | AA25: =IF(AND($B25<>"",$C25="Ingreso",SUMIFS('Registro Mensual'!$H$9:$H$1008,'Registro Mensual'!$C$9:$C$1008,Dashboard!$B$5,'Registro Mensual'!$D$9:$D$1008,$B25)>0),COUNT($AA$4:AA24)+1,"") | AB25: =IFERROR(INDEX($B$5:$B$200,MATCH(ROWS($AB$5:AB25),$Z$5:$Z$200,0)),"") | AC25: =IF($AB25="","",SUMIFS('Registro Mensual'!$I$9:$I$1008,'Registro Mensual'!$C$9:$C$1008,Dashboard!$B$5,'Registro Mensual'!$D$9:$D$1008,$AB25))
Z26: =IF(AND($B26<>"",$C26="Gasto"),COUNT($Z$4:Z25)+1,"") | AA26: =IF(AND($B26<>"",$C26="Ingreso",SUMIFS('Registro Mensual'!$H$9:$H$1008,'Registro Mensual'!$C$9:$C$1008,Dashboard!$B$5,'Registro Mensual'!$D$9:$D$1008,$B26)>0),COUNT($AA$4:AA25)+1,"") | AB26: =IFERROR(INDEX($B$5:$B$200,MATCH(ROWS($AB$5:AB26),$Z$5:$Z$200,0)),"") | AC26: =IF($AB26="","",SUMIFS('Registro Mensual'!$I$9:$I$1008,'Registro Mensual'!$C$9:$C$1008,Dashboard!$B$5,'Registro Mensual'!$D$9:$D$1008,$AB26))
Z27: =IF(AND($B27<>"",$C27="Gasto"),COUNT($Z$4:Z26)+1,"") | AA27: =IF(AND($B27<>"",$C27="Ingreso",SUMIFS('Registro Mensual'!$H$9:$H$1008,'Registro Mensual'!$C$9:$C$1008,Dashboard!$B$5,'Registro Mensual'!$D$9:$D$1008,$B27)>0),COUNT($AA$4:AA26)+1,"") | AB27: =IFERROR(INDEX($B$5:$B$200,MATCH(ROWS($AB$5:AB27),$Z$5:$Z$200,0)),"") | AC27: =IF($AB27="","",SUMIFS('Registro Mensual'!$I$9:$I$1008,'Registro Mensual'!$C$9:$C$1008,Dashboard!$B$5,'Registro Mensual'!$D$9:$D$1008,$AB27))
Z28: =IF(AND($B28<>"",$C28="Gasto"),COUNT($Z$4:Z27)+1,"") | AA28: =IF(AND($B28<>"",$C28="Ingreso",SUMIFS('Registro Mensual'!$H$9:$H$1008,'Registro Mensual'!$C$9:$C$1008,Dashboard!$B$5,'Registro Mensual'!$D$9:$D$1008,$B28)>0),COUNT($AA$4:AA27)+1,"") | AB28: =IFERROR(INDEX($B$5:$B$200,MATCH(ROWS($AB$5:AB28),$Z$5:$Z$200,0)),"") | AC28: =IF($AB28="","",SUMIFS('Registro Mensual'!$I$9:$I$1008,'Registro Mensual'!$C$9:$C$1008,Dashboard!$B$5,'Registro Mensual'!$D$9:$D$1008,$AB28))
Z29: =IF(AND($B29<>"",$C29="Gasto"),COUNT($Z$4:Z28)+1,"") | AA29: =IF(AND($B29<>"",$C29="Ingreso",SUMIFS('Registro Mensual'!$H$9:$H$1008,'Registro Mensual'!$C$9:$C$1008,Dashboard!$B$5,'Registro Mensual'!$D$9:$D$1008,$B29)>0),COUNT($AA$4:AA28)+1,"") | AB29: =IFERROR(INDEX($B$5:$B$200,MATCH(ROWS($AB$5:AB29),$Z$5:$Z$200,0)),"") | AC29: =IF($AB29="","",SUMIFS('Registro Mensual'!$I$9:$I$1008,'Registro Mensual'!$C$9:$C$1008,Dashboard!$B$5,'Registro Mensual'!$D$9:$D$1008,$AB29))
Z30: =IF(AND($B30<>"",$C30="Gasto"),COUNT($Z$4:Z29)+1,"") | AA30: =IF(AND($B30<>"",$C30="Ingreso",SUMIFS('Registro Mensual'!$H$9:$H$1008,'Registro Mensual'!$C$9:$C$1008,Dashboard!$B$5,'Registro Mensual'!$D$9:$D$1008,$B30)>0),COUNT($AA$4:AA29)+1,"") | AB30: =IFERROR(INDEX($B$5:$B$200,MATCH(ROWS($AB$5:AB30),$Z$5:$Z$200,0)),"") | AC30: =IF($AB30="","",SUMIFS('Registro Mensual'!$I$9:$I$1008,'Registro Mensual'!$C$9:$C$1008,Dashboard!$B$5,'Registro Mensual'!$D$9:$D$1008,$AB30))
Z31: =IF(AND($B31<>"",$C31="Gasto"),COUNT($Z$4:Z30)+1,"") | AA31: =IF(AND($B31<>"",$C31="Ingreso",SUMIFS('Registro Mensual'!$H$9:$H$1008,'Registro Mensual'!$C$9:$C$1008,Dashboard!$B$5,'Registro Mensual'!$D$9:$D$1008,$B31)>0),COUNT($AA$4:AA30)+1,"") | AB31: =IFERROR(INDEX($B$5:$B$200,MATCH(ROWS($AB$5:AB31),$Z$5:$Z$200,0)),"") | AC31: =IF($AB31="","",SUMIFS('Registro Mensual'!$I$9:$I$1008,'Registro Mensual'!$C$9:$C$1008,Dashboard!$B$5,'Registro Mensual'!$D$9:$D$1008,$AB31))
Z32: =IF(AND($B32<>"",$C32="Gasto"),COUNT($Z$4:Z31)+1,"") | AA32: =IF(AND($B32<>"",$C32="Ingreso",SUMIFS('Registro Mensual'!$H$9:$H$1008,'Registro Mensual'!$C$9:$C$1008,Dashboard!$B$5,'Registro Mensual'!$D$9:$D$1008,$B32)>0),COUNT($AA$4:AA31)+1,"") | AB32: =IFERROR(INDEX($B$5:$B$200,MATCH(ROWS($AB$5:AB32),$Z$5:$Z$200,0)),"") | AC32: =IF($AB32="","",SUMIFS('Registro Mensual'!$I$9:$I$1008,'Registro Mensual'!$C$9:$C$1008,Dashboard!$B$5,'Registro Mensual'!$D$9:$D$1008,$AB32))
Z33: =IF(AND($B33<>"",$C33="Gasto"),COUNT($Z$4:Z32)+1,"") | AA33: =IF(AND($B33<>"",$C33="Ingreso",SUMIFS('Registro Mensual'!$H$9:$H$1008,'Registro Mensual'!$C$9:$C$1008,Dashboard!$B$5,'Registro Mensual'!$D$9:$D$1008,$B33)>0),COUNT($AA$4:AA32)+1,"") | AB33: =IFERROR(INDEX($B$5:$B$200,MATCH(ROWS($AB$5:AB33),$Z$5:$Z$200,0)),"") | AC33: =IF($AB33="","",SUMIFS('Registro Mensual'!$I$9:$I$1008,'Registro Mensual'!$C$9:$C$1008,Dashboard!$B$5,'Registro Mensual'!$D$9:$D$1008,$AB33))
Z34: =IF(AND($B34<>"",$C34="Gasto"),COUNT($Z$4:Z33)+1,"") | AA34: =IF(AND($B34<>"",$C34="Ingreso",SUMIFS('Registro Mensual'!$H$9:$H$1008,'Registro Mensual'!$C$9:$C$1008,Dashboard!$B$5,'Registro Mensual'!$D$9:$D$1008,$B34)>0),COUNT($AA$4:AA33)+1,"") | AB34: =IFERROR(INDEX($B$5:$B$200,MATCH(ROWS($AB$5:AB34),$Z$5:$Z$200,0)),"") | AC34: =IF($AB34="","",SUMIFS('Registro Mensual'!$I$9:$I$1008,'Registro Mensual'!$C$9:$C$1008,Dashboard!$B$5,'Registro Mensual'!$D$9:$D$1008,$AB34))
Z35: =IF(AND($B35<>"",$C35="Gasto"),COUNT($Z$4:Z34)+1,"") | AA35: =IF(AND($B35<>"",$C35="Ingreso",SUMIFS('Registro Mensual'!$H$9:$H$1008,'Registro Mensual'!$C$9:$C$1008,Dashboard!$B$5,'Registro Mensual'!$D$9:$D$1008,$B35)>0),COUNT($AA$4:AA34)+1,"") | AB35: =IFERROR(INDEX($B$5:$B$200,MATCH(ROWS($AB$5:AB35),$Z$5:$Z$200,0)),"") | AC35: =IF($AB35="","",SUMIFS('Registro Mensual'!$I$9:$I$1008,'Registro Mensual'!$C$9:$C$1008,Dashboard!$B$5,'Registro Mensual'!$D$9:$D$1008,$AB35))
Z36: =IF(AND($B36<>"",$C36="Gasto"),COUNT($Z$4:Z35)+1,"") | AA36: =IF(AND($B36<>"",$C36="Ingreso",SUMIFS('Registro Mensual'!$H$9:$H$1008,'Registro Mensual'!$C$9:$C$1008,Dashboard!$B$5,'Registro Mensual'!$D$9:$D$1008,$B36)>0),COUNT($AA$4:AA35)+1,"") | AB36: =IFERROR(INDEX($B$5:$B$200,MATCH(ROWS($AB$5:AB36),$Z$5:$Z$200,0)),"") | AC36: =IF($AB36="","",SUMIFS('Registro Mensual'!$I$9:$I$1008,'Registro Mensual'!$C$9:$C$1008,Dashboard!$B$5,'Registro Mensual'!$D$9:$D$1008,$AB36))
Z37: =IF(AND($B37<>"",$C37="Gasto"),COUNT($Z$4:Z36)+1,"") | AA37: =IF(AND($B37<>"",$C37="Ingreso",SUMIFS('Registro Mensual'!$H$9:$H$1008,'Registro Mensual'!$C$9:$C$1008,Dashboard!$B$5,'Registro Mensual'!$D$9:$D$1008,$B37)>0),COUNT($AA$4:AA36)+1,"") | AB37: =IFERROR(INDEX($B$5:$B$200,MATCH(ROWS($AB$5:AB37),$Z$5:$Z$200,0)),"") | AC37: =IF($AB37="","",SUMIFS('Registro Mensual'!$I$9:$I$1008,'Registro Mensual'!$C$9:$C$1008,Dashboard!$B$5,'Registro Mensual'!$D$9:$D$1008,$AB37))
... Z200: =IF(AND($B200<>"",$C200="Gasto"),COUNT($Z$4:Z199)+1,"") | AA200: =IF(AND($B200<>"",$C200="Ingreso",SUMIFS('Registro Mensual'!$H$9:$H$1008,'Registro Mensual'!$C$9:$C$1008,Dashboard!$B$5,'Registro Mensual'!$D$9:$D$1008,$B200)>0),COUNT($AA$4:AA199)+1,"") | AB200: =IFERROR(INDEX($B$5:$B$200,MATCH(ROWS($AB$5:AB200),$Z$5:$Z$200,0)),"") | AC200: =IF($AB200="","",SUMIFS('Registro Mensual'!$I$9:$I$1008,'Registro Mensual'!$C$9:$C$1008,Dashboard!$B$5,'Registro Mensual'!$D$9:$D$1008,$AB200))

Sheet Dashboard
B1: DASHBOARD CONTROL PYME
B2: Visualiza ingresos, gastos, ahorro y ganancia de forma automática.
B4: Mes a analizar | E4: Ingresos año | H4: Gastos año | K4: Ganancia disponible año
A5: Filtro, selecciona el mes en el que te encuentras→ | B5: Enero | E5: ='Resumen Mensual'!$O$5 -> 1450000 | H5: ='Resumen Mensual'!$O$6 -> 2330000 | K5: ='Resumen Mensual'!$O$9 -> -880000
O6: Cambia B5 para revisar ingresos, gastos y reservas del mes seleccionado.
B8: Reserva / ahorro año | E8: Margen anual | H8: Mejor mes | K8: Meses con pérdida
B9: ='Resumen Mensual'!$O$8 -> 0 | E9: ='Resumen Mensual'!$O$10 -> -0.60689655 | H9: =INDEX('Resumen Mensual'!$C$4:$N$4,1,MATCH(MAX('Resumen Mensual'!$C$9:$N$9),'Resumen Mensual'!$C$9:$N$9,0)) -> Febrero | K9: =COUNTIF('Resumen Mensual'!$C$11:$N$11,"Pérdida") -> 1
O12: ¿Qué se hace en esta hoja?
B13: Mes | C13: Ingresos | D13: Gastos | E13: Reserva | F13: Ganancia disponible | O13: Aquí solo se mira la información. Los indicadores, tablas y gráficos vienen del Resumen Mensual y del Registro Mensual. Cambia el Mes a analizar en B5 usando la lista desplegable; ese mismo mes se refleja en el Registro Mensual.
B14: Enero | C14: =INDEX('Resumen Mensual'!$C$5:$N$5,1,MATCH($B14,'Resumen Mensual'!$C$4:$N$4,0)) -> 1450000 | D14: =INDEX('Resumen Mensual'!$C$6:$N$6,1,MATCH($B14,'Resumen Mensual'!$C$4:$N$4,0)) -> 2330000 | E14: =INDEX('Resumen Mensual'!$C$8:$N$8,1,MATCH($B14,'Resumen Mensual'!$C$4:$N$4,0)) -> 0 | F14: =INDEX('Resumen Mensual'!$C$9:$N$9,1,MATCH($B14,'Resumen Mensual'!$C$4:$N$4,0)) -> -880000
B15: Febrero | C15: =INDEX('Resumen Mensual'!$C$5:$N$5,1,MATCH($B15,'Resumen Mensual'!$C$4:$N$4,0)) -> 0 | D15: =INDEX('Resumen Mensual'!$C$6:$N$6,1,MATCH($B15,'Resumen Mensual'!$C$4:$N$4,0)) -> 0 | E15: =INDEX('Resumen Mensual'!$C$8:$N$8,1,MATCH($B15,'Resumen Mensual'!$C$4:$N$4,0)) -> 0 | F15: =INDEX('Resumen Mensual'!$C$9:$N$9,1,MATCH($B15,'Resumen Mensual'!$C$4:$N$4,0)) -> 0
B16: Marzo | C16: =INDEX('Resumen Mensual'!$C$5:$N$5,1,MATCH($B16,'Resumen Mensual'!$C$4:$N$4,0)) -> 0 | D16: =INDEX('Resumen Mensual'!$C$6:$N$6,1,MATCH($B16,'Resumen Mensual'!$C$4:$N$4,0)) -> 0 | E16: =INDEX('Resumen Mensual'!$C$8:$N$8,1,MATCH($B16,'Resumen Mensual'!$C$4:$N$4,0)) -> 0 | F16: =INDEX('Resumen Mensual'!$C$9:$N$9,1,MATCH($B16,'Resumen Mensual'!$C$4:$N$4,0)) -> 0
B17: Abril | C17: =INDEX('Resumen Mensual'!$C$5:$N$5,1,MATCH($B17,'Resumen Mensual'!$C$4:$N$4,0)) -> 0 | D17: =INDEX('Resumen Mensual'!$C$6:$N$6,1,MATCH($B17,'Resumen Mensual'!$C$4:$N$4,0)) -> 0 | E17: =INDEX('Resumen Mensual'!$C$8:$N$8,1,MATCH($B17,'Resumen Mensual'!$C$4:$N$4,0)) -> 0 | F17: =INDEX('Resumen Mensual'!$C$9:$N$9,1,MATCH($B17,'Resumen Mensual'!$C$4:$N$4,0)) -> 0
B18: Mayo | C18: =INDEX('Resumen Mensual'!$C$5:$N$5,1,MATCH($B18,'Resumen Mensual'!$C$4:$N$4,0)) -> 0 | D18: =INDEX('Resumen Mensual'!$C$6:$N$6,1,MATCH($B18,'Resumen Mensual'!$C$4:$N$4,0)) -> 0 | E18: =INDEX('Resumen Mensual'!$C$8:$N$8,1,MATCH($B18,'Resumen Mensual'!$C$4:$N$4,0)) -> 0 | F18: =INDEX('Resumen Mensual'!$C$9:$N$9,1,MATCH($B18,'Resumen Mensual'!$C$4:$N$4,0)) -> 0
B19: Junio | C19: =INDEX('Resumen Mensual'!$C$5:$N$5,1,MATCH($B19,'Resumen Mensual'!$C$4:$N$4,0)) -> 0 | D19: =INDEX('Resumen Mensual'!$C$6:$N$6,1,MATCH($B19,'Resumen Mensual'!$C$4:$N$4,0)) -> 0 | E19: =INDEX('Resumen Mensual'!$C$8:$N$8,1,MATCH($B19,'Resumen Mensual'!$C$4:$N$4,0)) -> 0 | F19: =INDEX('Resumen Mensual'!$C$9:$N$9,1,MATCH($B19,'Resumen Mensual'!$C$4:$N$4,0)) -> 0
B20: Julio | C20: =INDEX('Resumen Mensual'!$C$5:$N$5,1,MATCH($B20,'Resumen Mensual'!$C$4:$N$4,0)) -> 0 | D20: =INDEX('Resumen Mensual'!$C$6:$N$6,1,MATCH($B20,'Resumen Mensual'!$C$4:$N$4,0)) -> 0 | E20: =INDEX('Resumen Mensual'!$C$8:$N$8,1,MATCH($B20,'Resumen Mensual'!$C$4:$N$4,0)) -> 0 | F20: =INDEX('Resumen Mensual'!$C$9:$N$9,1,MATCH($B20,'Resumen Mensual'!$C$4:$N$4,0)) -> 0
B21: Agosto | C21: =INDEX('Resumen Mensual'!$C$5:$N$5,1,MATCH($B21,'Resumen Mensual'!$C$4:$N$4,0)) -> 0 | D21: =INDEX('Resumen Mensual'!$C$6:$N$6,1,MATCH($B21,'Resumen Mensual'!$C$4:$N$4,0)) -> 0 | E21: =INDEX('Resumen Mensual'!$C$8:$N$8,1,MATCH($B21,'Resumen Mensual'!$C$4:$N$4,0)) -> 0 | F21: =INDEX('Resumen Mensual'!$C$9:$N$9,1,MATCH($B21,'Resumen Mensual'!$C$4:$N$4,0)) -> 0
B22: Septiembre | C22: =INDEX('Resumen Mensual'!$C$5:$N$5,1,MATCH($B22,'Resumen Mensual'!$C$4:$N$4,0)) -> 0 | D22: =INDEX('Resumen Mensual'!$C$6:$N$6,1,MATCH($B22,'Resumen Mensual'!$C$4:$N$4,0)) -> 0 | E22: =INDEX('Resumen Mensual'!$C$8:$N$8,1,MATCH($B22,'Resumen Mensual'!$C$4:$N$4,0)) -> 0 | F22: =INDEX('Resumen Mensual'!$C$9:$N$9,1,MATCH($B22,'Resumen Mensual'!$C$4:$N$4,0)) -> 0
B23: Octubre | C23: =INDEX('Resumen Mensual'!$C$5:$N$5,1,MATCH($B23,'Resumen Mensual'!$C$4:$N$4,0)) -> 0 | D23: =INDEX('Resumen Mensual'!$C$6:$N$6,1,MATCH($B23,'Resumen Mensual'!$C$4:$N$4,0)) -> 0 | E23: =INDEX('Resumen Mensual'!$C$8:$N$8,1,MATCH($B23,'Resumen Mensual'!$C$4:$N$4,0)) -> 0 | F23: =INDEX('Resumen Mensual'!$C$9:$N$9,1,MATCH($B23,'Resumen Mensual'!$C$4:$N$4,0)) -> 0
B24: Noviembre | C24: =INDEX('Resumen Mensual'!$C$5:$N$5,1,MATCH($B24,'Resumen Mensual'!$C$4:$N$4,0)) -> 0 | D24: =INDEX('Resumen Mensual'!$C$6:$N$6,1,MATCH($B24,'Resumen Mensual'!$C$4:$N$4,0)) -> 0 | E24: =INDEX('Resumen Mensual'!$C$8:$N$8,1,MATCH($B24,'Resumen Mensual'!$C$4:$N$4,0)) -> 0 | F24: =INDEX('Resumen Mensual'!$C$9:$N$9,1,MATCH($B24,'Resumen Mensual'!$C$4:$N$4,0)) -> 0
B25: Diciembre | C25: =INDEX('Resumen Mensual'!$C$5:$N$5,1,MATCH($B25,'Resumen Mensual'!$C$4:$N$4,0)) -> 0 | D25: =INDEX('Resumen Mensual'!$C$6:$N$6,1,MATCH($B25,'Resumen Mensual'!$C$4:$N$4,0)) -> 0 | E25: =INDEX('Resumen Mensual'!$C$8:$N$8,1,MATCH($B25,'Resumen Mensual'!$C$4:$N$4,0)) -> 0 | F25: =INDEX('Resumen Mensual'!$C$9:$N$9,1,MATCH($B25,'Resumen Mensual'!$C$4:$N$4,0)) -> 0
B28: Gastos por categoría | E28: Ingresos por categoría
B29: Categoría | C29: Monto | E29: Categoría | F29: Monto
B30: =IFERROR(INDEX(Categorias!$AB$5:$AB$200,ROWS($B$30:B30)),"") -> Arriendo | C30: =IF($B30="","",SUMIFS('Registro Mensual'!$I$9:$I$1008,'Registro Mensual'!$C$9:$C$1008,$B$5,'Registro Mensual'!$D$9:$D$1008,$B30)) -> 700000 | E30: =IFERROR(INDEX(Categorias!$B$5:$B$200,MATCH(ROWS($E$30:E30),Categorias!$AA$5:$AA$200,0)),"") -> Ventas | F30: =IF($E30="","",SUMIFS('Registro Mensual'!$H$9:$H$1008,'Registro Mensual'!$C$9:$C$1008,$B$5,'Registro Mensual'!$D$9:$D$1008,$E30)) -> 1450000
B31: =IFERROR(INDEX(Categorias!$AB$5:$AB$200,ROWS($B$30:B31)),"") -> Sueldos | C31: =IF($B31="","",SUMIFS('Registro Mensual'!$I$9:$I$1008,'Registro Mensual'!$C$9:$C$1008,$B$5,'Registro Mensual'!$D$9:$D$1008,$B31)) -> 0 | E31: =IFERROR(INDEX(Categorias!$B$5:$B$200,MATCH(ROWS($E$30:E31),Categorias!$AA$5:$AA$200,0)),"") | F31: =IF($E31="","",SUMIFS('Registro Mensual'!$H$9:$H$1008,'Registro Mensual'!$C$9:$C$1008,$B$5,'Registro Mensual'!$D$9:$D$1008,$E31))
B32: =IFERROR(INDEX(Categorias!$AB$5:$AB$200,ROWS($B$30:B32)),"") -> Servicios básicos | C32: =IF($B32="","",SUMIFS('Registro Mensual'!$I$9:$I$1008,'Registro Mensual'!$C$9:$C$1008,$B$5,'Registro Mensual'!$D$9:$D$1008,$B32)) -> 130000 | E32: =IFERROR(INDEX(Categorias!$B$5:$B$200,MATCH(ROWS($E$30:E32),Categorias!$AA$5:$AA$200,0)),"") | F32: =IF($E32="","",SUMIFS('Registro Mensual'!$H$9:$H$1008,'Registro Mensual'!$C$9:$C$1008,$B$5,'Registro Mensual'!$D$9:$D$1008,$E32))
B33: =IFERROR(INDEX(Categorias!$AB$5:$AB$200,ROWS($B$30:B33)),"") -> Insumos | C33: =IF($B33="","",SUMIFS('Registro Mensual'!$I$9:$I$1008,'Registro Mensual'!$C$9:$C$1008,$B$5,'Registro Mensual'!$D$9:$D$1008,$B33)) -> 0 | E33: =IFERROR(INDEX(Categorias!$B$5:$B$200,MATCH(ROWS($E$30:E33),Categorias!$AA$5:$AA$200,0)),"") | F33: =IF($E33="","",SUMIFS('Registro Mensual'!$H$9:$H$1008,'Registro Mensual'!$C$9:$C$1008,$B$5,'Registro Mensual'!$D$9:$D$1008,$E33))
B34: =IFERROR(INDEX(Categorias!$AB$5:$AB$200,ROWS($B$30:B34)),"") -> Transporte | C34: =IF($B34="","",SUMIFS('Registro Mensual'!$I$9:$I$1008,'Registro Mensual'!$C$9:$C$1008,$B$5,'Registro Mensual'!$D$9:$D$1008,$B34)) -> 0 | E34: =IFERROR(INDEX(Categorias!$B$5:$B$200,MATCH(ROWS($E$30:E34),Categorias!$AA$5:$AA$200,0)),"") | F34: =IF($E34="","",SUMIFS('Registro Mensual'!$H$9:$H$1008,'Registro Mensual'!$C$9:$C$1008,$B$5,'Registro Mensual'!$D$9:$D$1008,$E34))
B35: =IFERROR(INDEX(Categorias!$AB$5:$AB$200,ROWS($B$30:B35)),"") -> Publicidad | C35: =IF($B35="","",SUMIFS('Registro Mensual'!$I$9:$I$1008,'Registro Mensual'!$C$9:$C$1008,$B$5,'Registro Mensual'!$D$9:$D$1008,$B35)) -> 1500000 | E35: =IFERROR(INDEX(Categorias!$B$5:$B$200,MATCH(ROWS($E$30:E35),Categorias!$AA$5:$AA$200,0)),"") | F35: =IF($E35="","",SUMIFS('Registro Mensual'!$H$9:$H$1008,'Registro Mensual'!$C$9:$C$1008,$B$5,'Registro Mensual'!$D$9:$D$1008,$E35))
B36: =IFERROR(INDEX(Categorias!$AB$5:$AB$200,ROWS($B$30:B36)),"") -> Internet | C36: =IF($B36="","",SUMIFS('Registro Mensual'!$I$9:$I$1008,'Registro Mensual'!$C$9:$C$1008,$B$5,'Registro Mensual'!$D$9:$D$1008,$B36)) -> 0 | E36: =IFERROR(INDEX(Categorias!$B$5:$B$200,MATCH(ROWS($E$30:E36),Categorias!$AA$5:$AA$200,0)),"") | F36: =IF($E36="","",SUMIFS('Registro Mensual'!$H$9:$H$1008,'Registro Mensual'!$C$9:$C$1008,$B$5,'Registro Mensual'!$D$9:$D$1008,$E36))
B37: =IFERROR(INDEX(Categorias!$AB$5:$AB$200,ROWS($B$30:B37)),"") -> Contabilidad | C37: =IF($B37="","",SUMIFS('Registro Mensual'!$I$9:$I$1008,'Registro Mensual'!$C$9:$C$1008,$B$5,'Registro Mensual'!$D$9:$D$1008,$B37)) -> 0 | E37: =IFERROR(INDEX(Categorias!$B$5:$B$200,MATCH(ROWS($E$30:E37),Categorias!$AA$5:$AA$200,0)),"") | F37: =IF($E37="","",SUMIFS('Registro Mensual'!$H$9:$H$1008,'Registro Mensual'!$C$9:$C$1008,$B$5,'Registro Mensual'!$D$9:$D$1008,$E37))
B38: =IFERROR(INDEX(Categorias!$AB$5:$AB$200,ROWS($B$30:B38)),"") -> Patente / permisos | C38: =IF($B38="","",SUMIFS('Registro Mensual'!$I$9:$I$1008,'Registro Mensual'!$C$9:$C$1008,$B$5,'Registro Mensual'!$D$9:$D$1008,$B38)) -> 0 | E38: =IFERROR(INDEX(Categorias!$B$5:$B$200,MATCH(ROWS($E$30:E38),Categorias!$AA$5:$AA$200,0)),"") | F38: =IF($E38="","",SUMIFS('Registro Mensual'!$H$9:$H$1008,'Registro Mensual'!$C$9:$C$1008,$B$5,'Registro Mensual'!$D$9:$D$1008,$E38))
B39: =IFERROR(INDEX(Categorias!$AB$5:$AB$200,ROWS($B$30:B39)),"") -> Mantenimiento | C39: =IF($B39="","",SUMIFS('Registro Mensual'!$I$9:$I$1008,'Registro Mensual'!$C$9:$C$1008,$B$5,'Registro Mensual'!$D$9:$D$1008,$B39)) -> 0 | E39: =IFERROR(INDEX(Categorias!$B$5:$B$200,MATCH(ROWS($E$30:E39),Categorias!$AA$5:$AA$200,0)),"") | F39: =IF($E39="","",SUMIFS('Registro Mensual'!$H$9:$H$1008,'Registro Mensual'!$C$9:$C$1008,$B$5,'Registro Mensual'!$D$9:$D$1008,$E39))
B40: =IFERROR(INDEX(Categorias!$AB$5:$AB$200,ROWS($B$30:B40)),"") -> Comisiones | C40: =IF($B40="","",SUMIFS('Registro Mensual'!$I$9:$I$1008,'Registro Mensual'!$C$9:$C$1008,$B$5,'Registro Mensual'!$D$9:$D$1008,$B40)) -> 0 | E40: =IFERROR(INDEX(Categorias!$B$5:$B$200,MATCH(ROWS($E$30:E40),Categorias!$AA$5:$AA$200,0)),"") | F40: =IF($E40="","",SUMIFS('Registro Mensual'!$H$9:$H$1008,'Registro Mensual'!$C$9:$C$1008,$B$5,'Registro Mensual'!$D$9:$D$1008,$E40))
B41: =IFERROR(INDEX(Categorias!$AB$5:$AB$200,ROWS($B$30:B41)),"") -> Delivery | C41: =IF($B41="","",SUMIFS('Registro Mensual'!$I$9:$I$1008,'Registro Mensual'!$C$9:$C$1008,$B$5,'Registro Mensual'!$D$9:$D$1008,$B41)) -> 0 | E41: =IFERROR(INDEX(Categorias!$B$5:$B$200,MATCH(ROWS($E$30:E41),Categorias!$AA$5:$AA$200,0)),"") | F41: =IF($E41="","",SUMIFS('Registro Mensual'!$H$9:$H$1008,'Registro Mensual'!$C$9:$C$1008,$B$5,'Registro Mensual'!$D$9:$D$1008,$E41))
... B49: =IFERROR(INDEX(Categorias!$AB$5:$AB$200,ROWS($B$30:B49)),"") | C49: =IF($B49="","",SUMIFS('Registro Mensual'!$I$9:$I$1008,'Registro Mensual'!$C$9:$C$1008,$B$5,'Registro Mensual'!$D$9:$D$1008,$B49)) | E49: =IFERROR(INDEX(Categorias!$B$5:$B$200,MATCH(ROWS($E$30:E49),Categorias!$AA$5:$AA$200,0)),"") | F49: =IF($E49="","",SUMIFS('Registro Mensual'!$H$9:$H$1008,'Registro Mensual'!$C$9:$C$1008,$B$5,'Registro Mensual'!$D$9:$D$1008,$E49))
B50: TOTAL GASTOS | C50: =SUM(C30:C49) -> 2330000 | E50: TOTAL INGRESOS | F50: =SUM(F30:F49) -> 1450000
B51: Control: estos totales deben coincidir con el mes seleccionado.

Sheet Resumen Mensual
B1: RESUMEN MENSUAL
B2: Consolidado automático desde el Registro Mensual.
B4: Concepto | C4: Enero | D4: Febrero | E4: Marzo | F4: Abril | G4: Mayo | H4: Junio | I4: Julio | J4: Agosto | K4: Septiembre | L4: Octubre | M4: Noviembre | N4: Diciembre | O4: Total | P4: Promedio
B5: Ingresos | C5: =SUMIFS('Registro Mensual'!$H$9:$H$1008,'Registro Mensual'!$C$9:$C$1008,C$4) -> 1450000 | D5: =SUMIFS('Registro Mensual'!$H$9:$H$1008,'Registro Mensual'!$C$9:$C$1008,D$4) -> 0 | E5: =SUMIFS('Registro Mensual'!$H$9:$H$1008,'Registro Mensual'!$C$9:$C$1008,E$4) -> 0 | F5: =SUMIFS('Registro Mensual'!$H$9:$H$1008,'Registro Mensual'!$C$9:$C$1008,F$4) -> 0 | G5: =SUMIFS('Registro Mensual'!$H$9:$H$1008,'Registro Mensual'!$C$9:$C$1008,G$4) -> 0 | H5: =SUMIFS('Registro Mensual'!$H$9:$H$1008,'Registro Mensual'!$C$9:$C$1008,H$4) -> 0 | I5: =SUMIFS('Registro Mensual'!$H$9:$H$1008,'Registro Mensual'!$C$9:$C$1008,I$4) -> 0 | J5: =SUMIFS('Registro Mensual'!$H$9:$H$1008,'Registro Mensual'!$C$9:$C$1008,J$4) -> 0 | ... N5: =SUMIFS('Registro Mensual'!$H$9:$H$1008,'Registro Mensual'!$C$9:$C$1008,N$4) -> 0 | O5: =SUM(C5:N5) -> 1450000 | P5: =AVERAGE(C5:N5) -> 120833.33
B6: Gastos | C6: =SUMIFS('Registro Mensual'!$I$9:$I$1008,'Registro Mensual'!$C$9:$C$1008,C$4) -> 2330000 | D6: =SUMIFS('Registro Mensual'!$I$9:$I$1008,'Registro Mensual'!$C$9:$C$1008,D$4) -> 0 | E6: =SUMIFS('Registro Mensual'!$I$9:$I$1008,'Registro Mensual'!$C$9:$C$1008,E$4) -> 0 | F6: =SUMIFS('Registro Mensual'!$I$9:$I$1008,'Registro Mensual'!$C$9:$C$1008,F$4) -> 0 | G6: =SUMIFS('Registro Mensual'!$I$9:$I$1008,'Registro Mensual'!$C$9:$C$1008,G$4) -> 0 | H6: =SUMIFS('Registro Mensual'!$I$9:$I$1008,'Registro Mensual'!$C$9:$C$1008,H$4) -> 0 | I6: =SUMIFS('Registro Mensual'!$I$9:$I$1008,'Registro Mensual'!$C$9:$C$1008,I$4) -> 0 | J6: =SUMIFS('Registro Mensual'!$I$9:$I$1008,'Registro Mensual'!$C$9:$C$1008,J$4) -> 0 | ... N6: =SUMIFS('Registro Mensual'!$I$9:$I$1008,'Registro Mensual'!$C$9:$C$1008,N$4) -> 0 | O6: =SUM(C6:N6) -> 2330000 | P6: =AVERAGE(C6:N6) -> 194166.67
B7: Ganancia bruta | C7: =C5-C6 -> -880000 | D7: =D5-D6 -> 0 | E7: =E5-E6 -> 0 | F7: =F5-F6 -> 0 | G7: =G5-G6 -> 0 | H7: =H5-H6 -> 0 | I7: =I5-I6 -> 0 | J7: =J5-J6 -> 0 | ... N7: =N5-N6 -> 0 | O7: =SUM(C7:N7) -> -880000 | P7: =AVERAGE(C7:N7) -> -73333.333
B8: Reserva / ahorro | C8: =SUMIFS('Registro Mensual'!$J$9:$J$1008,'Registro Mensual'!$C$9:$C$1008,C$4) -> 0 | D8: =SUMIFS('Registro Mensual'!$J$9:$J$1008,'Registro Mensual'!$C$9:$C$1008,D$4) -> 0 | E8: =SUMIFS('Registro Mensual'!$J$9:$J$1008,'Registro Mensual'!$C$9:$C$1008,E$4) -> 0 | F8: =SUMIFS('Registro Mensual'!$J$9:$J$1008,'Registro Mensual'!$C$9:$C$1008,F$4) -> 0 | G8: =SUMIFS('Registro Mensual'!$J$9:$J$1008,'Registro Mensual'!$C$9:$C$1008,G$4) -> 0 | H8: =SUMIFS('Registro Mensual'!$J$9:$J$1008,'Registro Mensual'!$C$9:$C$1008,H$4) -> 0 | I8: =SUMIFS('Registro Mensual'!$J$9:$J$1008,'Registro Mensual'!$C$9:$C$1008,I$4) -> 0 | J8: =SUMIFS('Registro Mensual'!$J$9:$J$1008,'Registro Mensual'!$C$9:$C$1008,J$4) -> 0 | ... N8: =SUMIFS('Registro Mensual'!$J$9:$J$1008,'Registro Mensual'!$C$9:$C$1008,N$4) -> 0 | O8: =SUM(C8:N8) -> 0 | P8: =AVERAGE(C8:N8) -> 0
B9: Ganancia disponible | C9: =C7-C8 -> -880000 | D9: =D7-D8 -> 0 | E9: =E7-E8 -> 0 | F9: =F7-F8 -> 0 | G9: =G7-G8 -> 0 | H9: =H7-H8 -> 0 | I9: =I7-I8 -> 0 | J9: =J7-J8 -> 0 | ... N9: =N7-N8 -> 0 | O9: =SUM(C9:N9) -> -880000 | P9: =AVERAGE(C9:N9) -> -73333.333
B10: Margen % | C10: =IFERROR(C9/C5,0) -> -0.60689655 | D10: =IFERROR(D9/D5,0) -> 0 | E10: =IFERROR(E9/E5,0) -> 0 | F10: =IFERROR(F9/F5,0) -> 0 | G10: =IFERROR(G9/G5,0) -> 0 | H10: =IFERROR(H9/H5,0) -> 0 | I10: =IFERROR(I9/I5,0) -> 0 | J10: =IFERROR(J9/J5,0) -> 0 | ... O10: =IFERROR(O9/O5,0) -> -0.60689655 | P10: =IFERROR(AVERAGE(C10:N10),0) -> -0.050574713
B11: Estado | C11: =IF(C9<0,"Pérdida","OK") -> Pérdida | D11: =IF(D9<0,"Pérdida","OK") -> OK | E11: =IF(E9<0,"Pérdida","OK") -> OK | F11: =IF(F9<0,"Pérdida","OK") -> OK | G11: =IF(G9<0,"Pérdida","OK") -> OK | H11: =IF(H9<0,"Pérdida","OK") -> OK | I11: =IF(I9<0,"Pérdida","OK") -> OK | J11: =IF(J9<0,"Pérdida","OK") -> OK | ... N11: =IF(N9<0,"Pérdida","OK") -> OK | O11: ="Meses pérdida: "&COUNTIF(C11:N11,"Pérdida") -> Meses pérdida: 1 | P11: ="Meses OK: "&COUNTIF(C11:N11,"OK") -> Meses OK: 11
F13: ¿Qué se hace en esta hoja?
F14: Esta hoja no se rellena manualmente. Toma la información del Registro Mensual y calcula ingresos, gastos, reserva, ganancia disponible, margen y estado de cada mes. Si modificas un movimiento en el Registro, este resumen cambia solo.
